{"streams":[{"id":"690ec48c28d8b","title":"Cerro Largo - Liverpool M.","browser_uuid":"\/regarder-cerro-largo-vs-liverpool-m-23h30-streaming-direct","sport_name":"\u00b7 Liga AUF Uruguaya","sport_flag":"","date_time":"2025\/11\/08 \u00e0 08:18","live":[{"stream_url":"https:\/\/match-live.lol\/\/part\/Ll.php?id=1\/109","flag":"https:\/\/flagcdn.com\/16x12\/es.webp","channel_name":"Wigi"},{"stream_url":"https:\/\/match-live.lol\/\/part\/Ll.php?id=2\/109","flag":"https:\/\/flagcdn.com\/16x12\/es.webp","channel_name":"Hoca"},{"stream_url":"https:\/\/match-live.lol\/\/part\/Ll.php?id=3\/109","flag":"https:\/\/flagcdn.com\/16x12\/es.webp","channel_name":"Obcast"},{"stream_url":"https:\/\/match-live.lol\/\/part\/Ll.php?id=1\/74","flag":"https:\/\/flagcdn.com\/16x12\/es.webp","channel_name":"Wigi"},{"stream_url":"https:\/\/match-live.lol\/\/part\/Ll.php?id=2\/74","flag":"https:\/\/flagcdn.com\/16x12\/es.webp","channel_name":"Hoca"},{"stream_url":"https:\/\/match-live.lol\/\/part\/Ll.php?id=3\/74","flag":"https:\/\/flagcdn.com\/16x12\/es.webp","channel_name":"Obcast"}]},{"id":"690ec48c28d8e","title":"U. Calera - Deportes Iquique","browser_uuid":"\/regarder-u-calera-vs-deportes-iquique-00h00-streaming-direct","sport_name":"\u00b7 Campeonato Ita\u00fa Chile","sport_flag":"","date_time":"2025\/11\/08 \u00e0 08:18","live":[{"stream_url":"https:\/\/match-live.lol\/\/part\/Ll.php?id=1\/83","flag":"https:\/\/flagcdn.com\/16x12\/es.webp","channel_name":"Wigi"},{"stream_url":"https:\/\/match-live.lol\/\/part\/Ll.php?id=2\/83","flag":"https:\/\/flagcdn.com\/16x12\/es.webp","channel_name":"Hoca"},{"stream_url":"https:\/\/match-live.lol\/\/part\/Ll.php?id=3\/83","flag":"https:\/\/flagcdn.com\/16x12\/es.webp","channel_name":"Obcast"}]},{"id":"690ec48c28d8f","title":"Pereira - Ind. Medellin","browser_uuid":"\/regarder-pereira-vs-ind-medellin-00h10-streaming-direct","sport_name":"\u00b7 Liga Betplay Dimayor","sport_flag":"","date_time":"2025\/11\/08 \u00e0 08:18","live":[{"stream_url":"https:\/\/match-live.lol\/\/part\/Ll.php?id=1\/81","flag":"https:\/\/flagcdn.com\/16x12\/es.webp","channel_name":"Wigi"},{"stream_url":"https:\/\/match-live.lol\/\/part\/Ll.php?id=2\/81","flag":"https:\/\/flagcdn.com\/16x12\/es.webp","channel_name":"Hoca"},{"stream_url":"https:\/\/match-live.lol\/\/part\/Ll.php?id=3\/81","flag":"https:\/\/flagcdn.com\/16x12\/es.webp","channel_name":"Obcast"}]},{"id":"690ec48c28d90","title":"Washington Wizards - Cleveland Cavaliers","browser_uuid":"\/regarder-washington-wizards-vs-cleveland-cavaliers-01h00-streaming-direct","sport_name":"\u00b7 NBA","sport_flag":"","date_time":"2025\/11\/08 \u00e0 08:18","live":[{"stream_url":"https:\/\/match-live.lol\/\/part\/Ll.php?id=1\/171","flag":"https:\/\/flagcdn.com\/16x12\/us.webp","channel_name":"Wigi"},{"stream_url":"https:\/\/match-live.lol\/\/part\/Ll.php?id=2\/171","flag":"https:\/\/flagcdn.com\/16x12\/us.webp","channel_name":"Hoca"},{"stream_url":"https:\/\/match-live.lol\/\/part\/Ll.php?id=3\/171","flag":"https:\/\/flagcdn.com\/16x12\/us.webp","channel_name":"Obcast"}]},{"id":"690ec48c28d91","title":"New York Islanders - Minnesota Wild","browser_uuid":"\/regarder-new-york-islanders-vs-minnesota-wild-01h00-streaming-direct","sport_name":"\u00b7 NHL","sport_flag":"","date_time":"2025\/11\/08 \u00e0 08:18","live":[{"stream_url":"https:\/\/match-live.lol\/\/part\/Ll.php?id=1\/173","flag":"https:\/\/flagcdn.com\/16x12\/us.webp","channel_name":"Wigi"},{"stream_url":"https:\/\/match-live.lol\/\/part\/Ll.php?id=2\/173","flag":"https:\/\/flagcdn.com\/16x12\/us.webp","channel_name":"Hoca"},{"stream_url":"https:\/\/match-live.lol\/\/part\/Ll.php?id=3\/173","flag":"https:\/\/flagcdn.com\/16x12\/us.webp","channel_name":"Obcast"}]},{"id":"690ec48c28d92","title":"Charlotte - New York City","browser_uuid":"\/regarder-charlotte-vs-new-york-city-01h00-streaming-direct","sport_name":"\u00b7 MLS","sport_flag":"","date_time":"2025\/11\/08 \u00e0 08:18","live":[{"stream_url":"https:\/\/match-live.lol\/\/part\/Ll.php?id=1\/160","flag":"https:\/\/flagcdn.com\/16x12\/us.webp","channel_name":"Wigi"},{"stream_url":"https:\/\/match-live.lol\/\/part\/Ll.php?id=2\/160","flag":"https:\/\/flagcdn.com\/16x12\/us.webp","channel_name":"Hoca"},{"stream_url":"https:\/\/match-live.lol\/\/part\/Ll.php?id=3\/160","flag":"https:\/\/flagcdn.com\/16x12\/us.webp","channel_name":"Obcast"},{"stream_url":"https:\/\/match-live.lol\/tv.php?id=https:\/\/evfancy.link\/ch?id=10","flag":"https:\/\/flagcdn.com\/16x12\/us.webp","channel_name":"LUC"}]},{"id":"690ec48c28d93","title":"Rosario - San Lorenzo","browser_uuid":"\/regarder-rosario-vs-san-lorenzo-01h00-streaming-direct","sport_name":"\u00b7 Torneo LPF","sport_flag":"","date_time":"2025\/11\/08 \u00e0 08:18","live":[{"stream_url":"https:\/\/match-live.lol\/\/part\/Ll.php?id=1\/61","flag":"https:\/\/flagcdn.com\/16x12\/es.webp","channel_name":"Wigi"},{"stream_url":"https:\/\/match-live.lol\/\/part\/Ll.php?id=2\/61","flag":"https:\/\/flagcdn.com\/16x12\/es.webp","channel_name":"Hoca"},{"stream_url":"https:\/\/match-live.lol\/\/part\/Ll.php?id=3\/61","flag":"https:\/\/flagcdn.com\/16x12\/es.webp","channel_name":"Obcast"},{"stream_url":"https:\/\/match-live.lol\/\/part\/Ll.php?id=1\/75","flag":"https:\/\/flagcdn.com\/16x12\/es.webp","channel_name":"Wigi"},{"stream_url":"https:\/\/match-live.lol\/\/part\/Ll.php?id=2\/75","flag":"https:\/\/flagcdn.com\/16x12\/es.webp","channel_name":"Hoca"},{"stream_url":"https:\/\/match-live.lol\/\/part\/Ll.php?id=3\/75","flag":"https:\/\/flagcdn.com\/16x12\/es.webp","channel_name":"Obcast"}]},{"id":"690ec48c28d94","title":"Detroit Red Wings - New York Rangers","browser_uuid":"\/regarder-detroit-red-wings-vs-new-york-rangers-01h00-streaming-direct","sport_name":"\u00b7 NHL","sport_flag":"","date_time":"2025\/11\/08 \u00e0 08:18","live":[{"stream_url":"https:\/\/match-live.lol\/\/part\/Ll.php?id=1\/172","flag":"https:\/\/flagcdn.com\/16x12\/us.webp","channel_name":"Wigi"},{"stream_url":"https:\/\/match-live.lol\/\/part\/Ll.php?id=2\/172","flag":"https:\/\/flagcdn.com\/16x12\/us.webp","channel_name":"Hoca"},{"stream_url":"https:\/\/match-live.lol\/\/part\/Ll.php?id=3\/172","flag":"https:\/\/flagcdn.com\/16x12\/us.webp","channel_name":"Obcast"}]},{"id":"690ec48c28d95","title":"Orlando Magic - Boston Celtics","browser_uuid":"\/regarder-orlando-magic-vs-boston-celtics-01h00-streaming-direct","sport_name":"\u00b7 NBA","sport_flag":"","date_time":"2025\/11\/08 \u00e0 08:18","live":[{"stream_url":"https:\/\/match-live.lol\/\/part\/Ll.php?id=1\/170","flag":"https:\/\/flagcdn.com\/16x12\/us.webp","channel_name":"Wigi"},{"stream_url":"https:\/\/match-live.lol\/\/part\/Ll.php?id=2\/170","flag":"https:\/\/flagcdn.com\/16x12\/us.webp","channel_name":"Hoca"},{"stream_url":"https:\/\/match-live.lol\/\/part\/Ll.php?id=3\/170","flag":"https:\/\/flagcdn.com\/16x12\/us.webp","channel_name":"Obcast"}]},{"id":"690ec48c28d96","title":"Dep. Cuenca - Macara","browser_uuid":"\/regarder-dep-cuenca-vs-macara-01h00-streaming-direct","sport_name":"\u00b7 Ecuador Ligapro","sport_flag":"","date_time":"2025\/11\/08 \u00e0 08:18","live":[{"stream_url":"https:\/\/match-live.lol\/\/part\/Ll.php?id=1\/86","flag":"https:\/\/flagcdn.com\/16x12\/es.webp","channel_name":"Wigi"},{"stream_url":"https:\/\/match-live.lol\/\/part\/Ll.php?id=2\/86","flag":"https:\/\/flagcdn.com\/16x12\/es.webp","channel_name":"Hoca"},{"stream_url":"https:\/\/match-live.lol\/\/part\/Ll.php?id=3\/86","flag":"https:\/\/flagcdn.com\/16x12\/es.webp","channel_name":"Obcast"}]},{"id":"690ec48c28d97","title":"San Antonio Spurs - Houston Rockets","browser_uuid":"\/regarder-san-antonio-spurs-vs-houston-rockets-01h30-streaming-direct","sport_name":"\u00b7 NBA","sport_flag":"","date_time":"2025\/11\/08 \u00e0 08:18","live":[{"stream_url":"https:\/\/match-live.lol\/\/part\/Ll.php?id=1\/176","flag":"https:\/\/flagcdn.com\/16x12\/us.webp","channel_name":"Wigi"},{"stream_url":"https:\/\/match-live.lol\/\/part\/Ll.php?id=2\/176","flag":"https:\/\/flagcdn.com\/16x12\/us.webp","channel_name":"Hoca"},{"stream_url":"https:\/\/match-live.lol\/\/part\/Ll.php?id=3\/176","flag":"https:\/\/flagcdn.com\/16x12\/us.webp","channel_name":"Obcast"}]},{"id":"690ec48c28d98","title":"Atlanta Hawks - Toronto Raptors","browser_uuid":"\/regarder-atlanta-hawks-vs-toronto-raptors-01h30-streaming-direct","sport_name":"\u00b7 NBA","sport_flag":"","date_time":"2025\/11\/08 \u00e0 08:18","live":[{"stream_url":"https:\/\/match-live.lol\/\/part\/Ll.php?id=1\/174","flag":"https:\/\/flagcdn.com\/16x12\/us.webp","channel_name":"Wigi"},{"stream_url":"https:\/\/match-live.lol\/\/part\/Ll.php?id=2\/174","flag":"https:\/\/flagcdn.com\/16x12\/us.webp","channel_name":"Hoca"},{"stream_url":"https:\/\/match-live.lol\/\/part\/Ll.php?id=3\/174","flag":"https:\/\/flagcdn.com\/16x12\/us.webp","channel_name":"Obcast"}]},{"id":"690ec48c28d99","title":"Brooklyn Nets - Detroit Pistons","browser_uuid":"\/regarder-brooklyn-nets-vs-detroit-pistons-01h30-streaming-direct","sport_name":"\u00b7 NBA","sport_flag":"","date_time":"2025\/11\/08 \u00e0 08:18","live":[{"stream_url":"https:\/\/match-live.lol\/\/part\/Ll.php?id=1\/175","flag":"https:\/\/flagcdn.com\/16x12\/us.webp","channel_name":"Wigi"},{"stream_url":"https:\/\/match-live.lol\/\/part\/Ll.php?id=2\/175","flag":"https:\/\/flagcdn.com\/16x12\/us.webp","channel_name":"Hoca"},{"stream_url":"https:\/\/match-live.lol\/\/part\/Ll.php?id=3\/175","flag":"https:\/\/flagcdn.com\/16x12\/us.webp","channel_name":"Obcast"}]},{"id":"690ec48c28d9a","title":"Miami Heat - Charlotte Hornets","browser_uuid":"\/regarder-miami-heat-vs-charlotte-hornets-02h00-streaming-direct","sport_name":"\u00b7 NBA","sport_flag":"","date_time":"2025\/11\/08 \u00e0 08:18","live":[{"stream_url":"https:\/\/match-live.lol\/\/part\/Ll.php?id=1\/178","flag":"https:\/\/flagcdn.com\/16x12\/us.webp","channel_name":"Wigi"},{"stream_url":"https:\/\/match-live.lol\/\/part\/Ll.php?id=2\/178","flag":"https:\/\/flagcdn.com\/16x12\/us.webp","channel_name":"Hoca"},{"stream_url":"https:\/\/match-live.lol\/\/part\/Ll.php?id=3\/178","flag":"https:\/\/flagcdn.com\/16x12\/us.webp","channel_name":"Obcast"}]},{"id":"690ec48c28d9b","title":"Juarez - Queretaro","browser_uuid":"\/regarder-juarez-vs-queretaro-02h00-streaming-direct","sport_name":"\u00b7 Liga Mx","sport_flag":"","date_time":"2025\/11\/08 \u00e0 08:18","live":[{"stream_url":"https:\/\/match-live.lol\/\/part\/Ll.php?id=1\/108","flag":"https:\/\/flagcdn.com\/16x12\/es.webp","channel_name":"Wigi"},{"stream_url":"https:\/\/match-live.lol\/\/part\/Ll.php?id=2\/108","flag":"https:\/\/flagcdn.com\/16x12\/es.webp","channel_name":"Hoca"},{"stream_url":"https:\/\/match-live.lol\/\/part\/Ll.php?id=3\/108","flag":"https:\/\/flagcdn.com\/16x12\/es.webp","channel_name":"Obcast"},{"stream_url":"https:\/\/match-live.lol\/\/part\/Ll.php?id=1\/72","flag":"https:\/\/flagcdn.com\/16x12\/es.webp","channel_name":"Wigi"},{"stream_url":"https:\/\/match-live.lol\/\/part\/Ll.php?id=2\/72","flag":"https:\/\/flagcdn.com\/16x12\/es.webp","channel_name":"Hoca"},{"stream_url":"https:\/\/match-live.lol\/\/part\/Ll.php?id=3\/72","flag":"https:\/\/flagcdn.com\/16x12\/es.webp","channel_name":"Obcast"},{"stream_url":"https:\/\/match-live.lol\/\/part\/Ll.php?id=1\/70","flag":"https:\/\/flagcdn.com\/16x12\/es.webp","channel_name":"Wigi"},{"stream_url":"https:\/\/match-live.lol\/\/part\/Ll.php?id=2\/70","flag":"https:\/\/flagcdn.com\/16x12\/es.webp","channel_name":"Hoca"},{"stream_url":"https:\/\/match-live.lol\/\/part\/Ll.php?id=3\/70","flag":"https:\/\/flagcdn.com\/16x12\/es.webp","channel_name":"Obcast"}]},{"id":"690ec48c28d9c","title":"Zacatecas Mineros - Irapuato","browser_uuid":"\/regarder-zacatecas-mineros-vs-irapuato-02h00-streaming-direct","sport_name":"\u00b7 Liga De Expansion Mx","sport_flag":"","date_time":"2025\/11\/08 \u00e0 08:18","live":[{"stream_url":"https:\/\/match-live.lol\/\/part\/Ll.php?id=1\/158","flag":"https:\/\/flagcdn.com\/16x12\/es.webp","channel_name":"Wigi"},{"stream_url":"https:\/\/match-live.lol\/\/part\/Ll.php?id=2\/158","flag":"https:\/\/flagcdn.com\/16x12\/es.webp","channel_name":"Hoca"},{"stream_url":"https:\/\/match-live.lol\/\/part\/Ll.php?id=3\/158","flag":"https:\/\/flagcdn.com\/16x12\/es.webp","channel_name":"Obcast"}]},{"id":"690ec48c28d9d","title":"Alebrijes Oaxaca - Correcaminos","browser_uuid":"\/regarder-alebrijes-oaxaca-vs-correcaminos-02h00-streaming-direct","sport_name":"\u00b7 Liga De Expansion Mx","sport_flag":"","date_time":"2025\/11\/08 \u00e0 08:18","live":[{"stream_url":"https:\/\/match-live.lol\/\/part\/Ll.php?id=1\/97","flag":"https:\/\/flagcdn.com\/16x12\/es.webp","channel_name":"Wigi"},{"stream_url":"https:\/\/match-live.lol\/\/part\/Ll.php?id=2\/97","flag":"https:\/\/flagcdn.com\/16x12\/es.webp","channel_name":"Hoca"},{"stream_url":"https:\/\/match-live.lol\/\/part\/Ll.php?id=3\/97","flag":"https:\/\/flagcdn.com\/16x12\/es.webp","channel_name":"Obcast"},{"stream_url":"https:\/\/match-live.lol\/\/part\/Ll.php?id=1\/105","flag":"https:\/\/flagcdn.com\/16x12\/es.webp","channel_name":"Wigi"},{"stream_url":"https:\/\/match-live.lol\/\/part\/Ll.php?id=2\/105","flag":"https:\/\/flagcdn.com\/16x12\/es.webp","channel_name":"Hoca"},{"stream_url":"https:\/\/match-live.lol\/\/part\/Ll.php?id=3\/105","flag":"https:\/\/flagcdn.com\/16x12\/es.webp","channel_name":"Obcast"}]},{"id":"690ec48c28d9e","title":"Milwaukee Bucks - Chicago Bulls","browser_uuid":"\/regarder-milwaukee-bucks-vs-chicago-bulls-02h00-streaming-direct","sport_name":"\u00b7 NBA","sport_flag":"","date_time":"2025\/11\/08 \u00e0 08:18","live":[{"stream_url":"https:\/\/match-live.lol\/\/part\/Ll.php?id=1\/179","flag":"https:\/\/flagcdn.com\/16x12\/us.webp","channel_name":"Wigi"},{"stream_url":"https:\/\/match-live.lol\/\/part\/Ll.php?id=2\/179","flag":"https:\/\/flagcdn.com\/16x12\/us.webp","channel_name":"Hoca"},{"stream_url":"https:\/\/match-live.lol\/\/part\/Ll.php?id=3\/179","flag":"https:\/\/flagcdn.com\/16x12\/us.webp","channel_name":"Obcast"}]},{"id":"690ec48c28d9f","title":"Memphis Grizzlies - Dallas Mavericks","browser_uuid":"\/regarder-memphis-grizzlies-vs-dallas-mavericks-02h00-streaming-direct","sport_name":"\u00b7 NBA","sport_flag":"","date_time":"2025\/11\/08 \u00e0 08:18","live":[{"stream_url":"https:\/\/match-live.lol\/\/part\/Ll.php?id=1\/177","flag":"https:\/\/flagcdn.com\/16x12\/us.webp","channel_name":"Wigi"},{"stream_url":"https:\/\/match-live.lol\/\/part\/Ll.php?id=2\/177","flag":"https:\/\/flagcdn.com\/16x12\/us.webp","channel_name":"Hoca"},{"stream_url":"https:\/\/match-live.lol\/\/part\/Ll.php?id=3\/177","flag":"https:\/\/flagcdn.com\/16x12\/us.webp","channel_name":"Obcast"}]},{"id":"690ec48c28da0","title":"Minnesota Timberwolves - Utah Jazz","browser_uuid":"\/regarder-minnesota-timberwolves-vs-utah-jazz-02h00-streaming-direct","sport_name":"\u00b7 NBA","sport_flag":"","date_time":"2025\/11\/08 \u00e0 08:18","live":[{"stream_url":"https:\/\/match-live.lol\/\/part\/Ll.php?id=1\/180","flag":"https:\/\/flagcdn.com\/16x12\/us.webp","channel_name":"Wigi"},{"stream_url":"https:\/\/match-live.lol\/\/part\/Ll.php?id=2\/180","flag":"https:\/\/flagcdn.com\/16x12\/us.webp","channel_name":"Hoca"},{"stream_url":"https:\/\/match-live.lol\/\/part\/Ll.php?id=3\/180","flag":"https:\/\/flagcdn.com\/16x12\/us.webp","channel_name":"Obcast"}]},{"id":"690ec48c28da1","title":"Tolima - Llaneros","browser_uuid":"\/regarder-tolima-vs-llaneros-02h20-streaming-direct","sport_name":"\u00b7 Liga Betplay Dimayor","sport_flag":"","date_time":"2025\/11\/08 \u00e0 08:18","live":[{"stream_url":"https:\/\/match-live.lol\/\/part\/Ll.php?id=1\/81","flag":"https:\/\/flagcdn.com\/16x12\/es.webp","channel_name":"Wigi"},{"stream_url":"https:\/\/match-live.lol\/\/part\/Ll.php?id=2\/81","flag":"https:\/\/flagcdn.com\/16x12\/es.webp","channel_name":"Hoca"},{"stream_url":"https:\/\/match-live.lol\/\/part\/Ll.php?id=3\/81","flag":"https:\/\/flagcdn.com\/16x12\/es.webp","channel_name":"Obcast"}]},{"id":"690ec48c28da2","title":"Calgary Flames - Chicago Blackhawks","browser_uuid":"\/regarder-calgary-flames-vs-chicago-blackhawks-03h00-streaming-direct","sport_name":"\u00b7 NHL","sport_flag":"","date_time":"2025\/11\/08 \u00e0 08:18","live":[{"stream_url":"https:\/\/match-live.lol\/\/part\/Ll.php?id=1\/181","flag":"https:\/\/flagcdn.com\/16x12\/us.webp","channel_name":"Wigi"},{"stream_url":"https:\/\/match-live.lol\/\/part\/Ll.php?id=2\/181","flag":"https:\/\/flagcdn.com\/16x12\/us.webp","channel_name":"Hoca"},{"stream_url":"https:\/\/match-live.lol\/\/part\/Ll.php?id=3\/181","flag":"https:\/\/flagcdn.com\/16x12\/us.webp","channel_name":"Obcast"}]},{"id":"690ec48c28da3","title":"U. de Deportes - Deportivo Garcilaso","browser_uuid":"\/regarder-u-de-deportes-vs-deportivo-garcilaso-03h00-streaming-direct","sport_name":"\u00b7 Liga 1 Te Apuesto","sport_flag":"","date_time":"2025\/11\/08 \u00e0 08:18","live":[{"stream_url":"https:\/\/match-live.lol\/\/part\/Ll.php?id=1\/85","flag":"https:\/\/flagcdn.com\/16x12\/es.webp","channel_name":"Wigi"},{"stream_url":"https:\/\/match-live.lol\/\/part\/Ll.php?id=2\/85","flag":"https:\/\/flagcdn.com\/16x12\/es.webp","channel_name":"Hoca"},{"stream_url":"https:\/\/match-live.lol\/\/part\/Ll.php?id=3\/85","flag":"https:\/\/flagcdn.com\/16x12\/es.webp","channel_name":"Obcast"},{"stream_url":"https:\/\/match-live.lol\/\/part\/Ll.php?id=1\/74","flag":"https:\/\/flagcdn.com\/16x12\/es.webp","channel_name":"Wigi"},{"stream_url":"https:\/\/match-live.lol\/\/part\/Ll.php?id=2\/74","flag":"https:\/\/flagcdn.com\/16x12\/es.webp","channel_name":"Hoca"},{"stream_url":"https:\/\/match-live.lol\/\/part\/Ll.php?id=3\/74","flag":"https:\/\/flagcdn.com\/16x12\/es.webp","channel_name":"Obcast"}]},{"id":"690ec48c28da4","title":"Mazatlan FC - Necaxa","browser_uuid":"\/regarder-mazatlan-fc-vs-necaxa-04h00-streaming-direct","sport_name":"\u00b7 Liga Mx","sport_flag":"","date_time":"2025\/11\/08 \u00e0 08:18","live":[{"stream_url":"https:\/\/match-live.lol\/\/part\/Ll.php?id=1\/108","flag":"https:\/\/flagcdn.com\/16x12\/es.webp","channel_name":"Wigi"},{"stream_url":"https:\/\/match-live.lol\/\/part\/Ll.php?id=2\/108","flag":"https:\/\/flagcdn.com\/16x12\/es.webp","channel_name":"Hoca"},{"stream_url":"https:\/\/match-live.lol\/\/part\/Ll.php?id=3\/108","flag":"https:\/\/flagcdn.com\/16x12\/es.webp","channel_name":"Obcast"},{"stream_url":"https:\/\/match-live.lol\/\/part\/Ll.php?id=1\/68","flag":"https:\/\/flagcdn.com\/16x12\/es.webp","channel_name":"Wigi"},{"stream_url":"https:\/\/match-live.lol\/\/part\/Ll.php?id=2\/68","flag":"https:\/\/flagcdn.com\/16x12\/es.webp","channel_name":"Hoca"},{"stream_url":"https:\/\/match-live.lol\/\/part\/Ll.php?id=3\/68","flag":"https:\/\/flagcdn.com\/16x12\/es.webp","channel_name":"Obcast"}]},{"id":"690ec48c28da5","title":"Atletico La Paz - Atlante","browser_uuid":"\/regarder-atletico-la-paz-vs-atlante-04h00-streaming-direct","sport_name":"\u00b7 Liga De Expansion Mx","sport_flag":"","date_time":"2025\/11\/08 \u00e0 08:18","live":[{"stream_url":"https:\/\/match-live.lol\/\/part\/Ll.php?id=1\/158","flag":"https:\/\/flagcdn.com\/16x12\/es.webp","channel_name":"Wigi"},{"stream_url":"https:\/\/match-live.lol\/\/part\/Ll.php?id=2\/158","flag":"https:\/\/flagcdn.com\/16x12\/es.webp","channel_name":"Hoca"},{"stream_url":"https:\/\/match-live.lol\/\/part\/Ll.php?id=3\/158","flag":"https:\/\/flagcdn.com\/16x12\/es.webp","channel_name":"Obcast"}]},{"id":"690ec48c28da6","title":"Tijuana - Atlas","browser_uuid":"\/regarder-tijuana-vs-atlas-04h00-streaming-direct","sport_name":"\u00b7 Liga Mx","sport_flag":"","date_time":"2025\/11\/08 \u00e0 08:18","live":[{"stream_url":"https:\/\/match-live.lol\/\/part\/Ll.php?id=1\/156","flag":"https:\/\/flagcdn.com\/16x12\/es.webp","channel_name":"Wigi"},{"stream_url":"https:\/\/match-live.lol\/\/part\/Ll.php?id=2\/156","flag":"https:\/\/flagcdn.com\/16x12\/es.webp","channel_name":"Hoca"},{"stream_url":"https:\/\/match-live.lol\/\/part\/Ll.php?id=3\/156","flag":"https:\/\/flagcdn.com\/16x12\/es.webp","channel_name":"Obcast"}]},{"id":"690ec48c28da7","title":"Denver Nuggets - Golden State Warriors","browser_uuid":"\/regarder-denver-nuggets-vs-golden-state-warriors-04h00-streaming-direct","sport_name":"\u00b7 NBA","sport_flag":"","date_time":"2025\/11\/08 \u00e0 08:18","live":[{"stream_url":"https:\/\/match-live.lol\/\/part\/Ll.php?id=1\/182","flag":"https:\/\/flagcdn.com\/16x12\/us.webp","channel_name":"Wigi"},{"stream_url":"https:\/\/match-live.lol\/\/part\/Ll.php?id=2\/182","flag":"https:\/\/flagcdn.com\/16x12\/us.webp","channel_name":"Hoca"},{"stream_url":"https:\/\/match-live.lol\/\/part\/Ll.php?id=3\/182","flag":"https:\/\/flagcdn.com\/16x12\/us.webp","channel_name":"Obcast"}]},{"id":"690ec48c28da8","title":"Sacramento Kings - Oklahoma City Thunder","browser_uuid":"\/regarder-sacramento-kings-vs-oklahoma-city-thunder-04h00-streaming-direct","sport_name":"\u00b7 NBA","sport_flag":"","date_time":"2025\/11\/08 \u00e0 08:18","live":[{"stream_url":"https:\/\/match-live.lol\/\/part\/Ll.php?id=1\/183","flag":"https:\/\/flagcdn.com\/16x12\/us.webp","channel_name":"Wigi"},{"stream_url":"https:\/\/match-live.lol\/\/part\/Ll.php?id=2\/183","flag":"https:\/\/flagcdn.com\/16x12\/us.webp","channel_name":"Hoca"},{"stream_url":"https:\/\/match-live.lol\/\/part\/Ll.php?id=3\/183","flag":"https:\/\/flagcdn.com\/16x12\/us.webp","channel_name":"Obcast"}]},{"id":"690ec48c28da9","title":"San Jose Sharks - Winnipeg Jets","browser_uuid":"\/regarder-san-jose-sharks-vs-winnipeg-jets-04h00-streaming-direct","sport_name":"\u00b7 NHL","sport_flag":"","date_time":"2025\/11\/08 \u00e0 08:18","live":[{"stream_url":"https:\/\/match-live.lol\/\/part\/Ll.php?id=1\/184","flag":"https:\/\/flagcdn.com\/16x12\/us.webp","channel_name":"Wigi"},{"stream_url":"https:\/\/match-live.lol\/\/part\/Ll.php?id=2\/184","flag":"https:\/\/flagcdn.com\/16x12\/us.webp","channel_name":"Hoca"},{"stream_url":"https:\/\/match-live.lol\/\/part\/Ll.php?id=3\/184","flag":"https:\/\/flagcdn.com\/16x12\/us.webp","channel_name":"Obcast"}]},{"id":"690ec48c28daa","title":"Grand Prix du Portugal Essais libres 2 des Moto 3","browser_uuid":"\/regarder-grand-prix-du-portugal-essais-libres-2-des-moto-3-09h40-streaming-direct","sport_name":"\u00b7 Moto3","sport_flag":"","date_time":"2025\/11\/08 \u00e0 08:18","live":[]},{"id":"690ec48c28dab","title":"Grand Prix du Portugal Essais libres 2 des Moto 2","browser_uuid":"\/regarder-grand-prix-du-portugal-essais-libres-2-des-moto-2-10h25-streaming-direct","sport_name":"\u00b7 Moto2","sport_flag":"","date_time":"2025\/11\/08 \u00e0 08:18","live":[]},{"id":"690ec48c28dac","title":"Grand Prix du Portugal Essais libres 2 des Moto GP","browser_uuid":"\/regarder-grand-prix-du-portugal-essais-libres-2-des-moto-gp-11h00-streaming-direct","sport_name":"\u00b7 MotoGP","sport_flag":"","date_time":"2025\/11\/08 \u00e0 08:18","live":[]},{"id":"690ec48c28dad","title":"Grand Prix du Portugal Essais qualificatifs 1 et 2 des Moto GP","browser_uuid":"\/regarder-grand-prix-du-portugal-essais-qualificatifs-1-et-2-des-moto-gp-11h50-streaming-direct","sport_name":"\u00b7 MotoGP","sport_flag":"","date_time":"2025\/11\/08 \u00e0 08:18","live":[]},{"id":"690ec48c28dae","title":"Gaziantep - Rizespor","browser_uuid":"\/regarder-gaziantep-vs-rizespor-12h30-streaming-direct","sport_name":"\u00b7 Super Lig","sport_flag":"","date_time":"2025\/11\/08 \u00e0 08:18","live":[]},{"id":"690ec48c28daf","title":"Schalke 04 - Elversberg","browser_uuid":"\/regarder-schalke-04-vs-elversberg-13h00-streaming-direct","sport_name":"\u00b7 Bundesliga 2","sport_flag":"","date_time":"2025\/11\/08 \u00e0 08:18","live":[]},{"id":"690ec48c28db0","title":"Bundesliga 2 konferenz","browser_uuid":"\/regarder-bundesliga-2-konferenz-13h00-streaming-direct","sport_name":"\u00b7 Bundesliga 2","sport_flag":"","date_time":"2025\/11\/08 \u00e0 08:18","live":[]},{"id":"690ec48c28db1","title":"Hanovre - Darmstadt","browser_uuid":"\/regarder-hanovre-vs-darmstadt-13h00-streaming-direct","sport_name":"\u00b7 Bundesliga 2","sport_flag":"","date_time":"2025\/11\/08 \u00e0 08:18","live":[]},{"id":"690ec48c28db2","title":"Arminia Bielefeld - Karlsruher","browser_uuid":"\/regarder-arminia-bielefeld-vs-karlsruher-13h00-streaming-direct","sport_name":"\u00b7 Bundesliga 2","sport_flag":"","date_time":"2025\/11\/08 \u00e0 08:18","live":[]},{"id":"690ec48c28db3","title":"Hull - Portsmouth","browser_uuid":"\/regarder-hull-vs-portsmouth-13h30-streaming-direct","sport_name":"\u00b7 Championship","sport_flag":"","date_time":"2025\/11\/08 \u00e0 08:18","live":[]},{"id":"690ec48c28db4","title":"Blackburn - Derby","browser_uuid":"\/regarder-blackburn-vs-derby-13h30-streaming-direct","sport_name":"\u00b7 Championship","sport_flag":"","date_time":"2025\/11\/08 \u00e0 08:18","live":[]},{"id":"690ec48c28db5","title":"Millwall - Preston","browser_uuid":"\/regarder-millwall-vs-preston-13h30-streaming-direct","sport_name":"\u00b7 Championship","sport_flag":"","date_time":"2025\/11\/08 \u00e0 08:18","live":[]},{"id":"690ec48c28db6","title":"Tottenham - Manchester Utd","browser_uuid":"\/regarder-tottenham-vs-manchester-utd-13h30-streaming-direct","sport_name":"\u00b7 Premier League","sport_flag":"","date_time":"2025\/11\/08 \u00e0 08:18","live":[]},{"id":"690ec48c28db7","title":"Irlande - Japon","browser_uuid":"\/regarder-irlande-vs-japon-13h40-streaming-direct","sport_name":"\u00b7 Tourn\u00e9e Automne","sport_flag":"","date_time":"2025\/11\/08 \u00e0 08:18","live":[]},{"id":"690ec48c28db8","title":"Grand Prix du Portugal Essais qualificatifs 1 et 2 des Moto 3","browser_uuid":"\/regarder-grand-prix-du-portugal-essais-qualificatifs-1-et-2-des-moto-3-13h45-streaming-direct","sport_name":"\u00b7 Moto3","sport_flag":"","date_time":"2025\/11\/08 \u00e0 08:18","live":[]},{"id":"690ec48c28db9","title":"Le Mans - Red Star","browser_uuid":"\/regarder-le-mans-vs-red-star-14h00-streaming-direct","sport_name":"\u00b7 Ligue 2","sport_flag":"","date_time":"2025\/11\/08 \u00e0 08:18","live":[]},{"id":"690ec48c28dba","title":"Guingamp - Pau FC","browser_uuid":"\/regarder-guingamp-vs-pau-fc-14h00-streaming-direct","sport_name":"\u00b7 Ligue 2","sport_flag":"","date_time":"2025\/11\/08 \u00e0 08:18","live":[]},{"id":"690ec48c28dbb","title":"G\u00e9rone - Alaves","browser_uuid":"\/regarder-gerone-vs-alaves-14h00-streaming-direct","sport_name":"\u00b7 Laliga","sport_flag":"","date_time":"2025\/11\/08 \u00e0 08:18","live":[]},{"id":"690ec48c28dbc","title":"Real Sociedad B - Leganes","browser_uuid":"\/regarder-real-sociedad-b-vs-leganes-14h00-streaming-direct","sport_name":"\u00b7 Laliga 2","sport_flag":"","date_time":"2025\/11\/08 \u00e0 08:18","live":[]},{"id":"690ec48c28dbd","title":"Grand Prix du Portugal Essais qualificatifs 1 et 2 des Moto 2","browser_uuid":"\/regarder-grand-prix-du-portugal-essais-qualificatifs-1-et-2-des-moto-2-14h40-streaming-direct","sport_name":"\u00b7 Moto2","sport_flag":"","date_time":"2025\/11\/08 \u00e0 08:18","live":[]},{"id":"690ec48c28dbe","title":"Neom SC - Al-Nassr","browser_uuid":"\/regarder-neom-sc-vs-al-nassr-14h50-streaming-direct","sport_name":"\u00b7 Saudi Pro League","sport_flag":"","date_time":"2025\/11\/08 \u00e0 08:18","live":[]},{"id":"690ec48c28dbf","title":"Como - Cagliari","browser_uuid":"\/regarder-como-vs-cagliari-15h00-streaming-direct","sport_name":"\u00b7 Serie A","sport_flag":"","date_time":"2025\/11\/08 \u00e0 08:18","live":[]},{"id":"690ec48c28dc0","title":"Trabzonspor - Alanyaspor","browser_uuid":"\/regarder-trabzonspor-vs-alanyaspor-15h00-streaming-direct","sport_name":"\u00b7 Super Lig","sport_flag":"","date_time":"2025\/11\/08 \u00e0 08:18","live":[]},{"id":"690ec48c28dc1","title":"Grand Prix de Sao Paulo Sprint","browser_uuid":"\/regarder-grand-prix-de-sao-paulo-sprint-15h00-streaming-direct","sport_name":"\u00b7 formula 1","sport_flag":"","date_time":"2025\/11\/08 \u00e0 08:18","live":[]},{"id":"690ec48c28dc2","title":"Lecce - Hellas V\u00e9rone","browser_uuid":"\/regarder-lecce-vs-hellas-verone-15h00-streaming-direct","sport_name":"\u00b7 Serie A","sport_flag":"","date_time":"2025\/11\/08 \u00e0 08:18","live":[]},{"id":"690ec48c28dc3","title":"Union Berlin - Bayern Munich","browser_uuid":"\/regarder-union-berlin-vs-bayern-munich-15h30-streaming-direct","sport_name":"\u00b7 Bundesliga","sport_flag":"","date_time":"2025\/11\/08 \u00e0 08:18","live":[]},{"id":"690ec48c28dc4","title":"Hambourg SV - Dortmund","browser_uuid":"\/regarder-hambourg-sv-vs-dortmund-15h30-streaming-direct","sport_name":"\u00b7 Bundesliga","sport_flag":"","date_time":"2025\/11\/08 \u00e0 08:18","live":[]},{"id":"690ec48c28dc5","title":"Bundesliga konferenz","browser_uuid":"\/regarder-bundesliga-konferenz-15h30-streaming-direct","sport_name":"\u00b7 Bundesliga","sport_flag":"","date_time":"2025\/11\/08 \u00e0 08:18","live":[]},{"id":"690ec48c28dc6","title":"Hoffenheim - RB Leipzig","browser_uuid":"\/regarder-hoffenheim-vs-rb-leipzig-15h30-streaming-direct","sport_name":"\u00b7 Bundesliga","sport_flag":"","date_time":"2025\/11\/08 \u00e0 08:18","live":[]},{"id":"690ec48c28dc7","title":"Bayer Leverkusen - Heidenheim","browser_uuid":"\/regarder-bayer-leverkusen-vs-heidenheim-15h30-streaming-direct","sport_name":"\u00b7 Bundesliga","sport_flag":"","date_time":"2025\/11\/08 \u00e0 08:18","live":[]},{"id":"690ec48c28dc8","title":"Grand Prix du Portugal Sprint des Moto GP","browser_uuid":"\/regarder-grand-prix-du-portugal-sprint-des-moto-gp-16h00-streaming-direct","sport_name":"\u00b7 MotoGP","sport_flag":"","date_time":"2025\/11\/08 \u00e0 08:18","live":[]},{"id":"690ec48c28dc9","title":"West Brom - Oxford Utd","browser_uuid":"\/regarder-west-brom-vs-oxford-utd-16h00-streaming-direct","sport_name":"\u00b7 Championship","sport_flag":"","date_time":"2025\/11\/08 \u00e0 08:18","live":[]},{"id":"690ec48c28dca","title":"Wrexham - Charlton","browser_uuid":"\/regarder-wrexham-vs-charlton-16h00-streaming-direct","sport_name":"\u00b7 Championship","sport_flag":"","date_time":"2025\/11\/08 \u00e0 08:18","live":[]},{"id":"690ec48c28dcb","title":"Everton - Fulham","browser_uuid":"\/regarder-everton-vs-fulham-16h00-streaming-direct","sport_name":"\u00b7 Premier League","sport_flag":"","date_time":"2025\/11\/08 \u00e0 08:18","live":[]},{"id":"690ec48c28dcc","title":"Southampton - Sheffield Wed","browser_uuid":"\/regarder-southampton-vs-sheffield-wed-16h00-streaming-direct","sport_name":"\u00b7 Championship","sport_flag":"","date_time":"2025\/11\/08 \u00e0 08:18","live":[]},{"id":"690ec48c28dcd","title":"West Ham - Burnley","browser_uuid":"\/regarder-west-ham-vs-burnley-16h00-streaming-direct","sport_name":"\u00b7 Premier League","sport_flag":"","date_time":"2025\/11\/08 \u00e0 08:18","live":[]},{"id":"690ec48c28dce","title":"Cercle Bruges - Louvain","browser_uuid":"\/regarder-cercle-bruges-vs-louvain-16h00-streaming-direct","sport_name":"\u00b7 Pro League","sport_flag":"","date_time":"2025\/11\/08 \u00e0 08:18","live":[]},{"id":"690ec48c28dcf","title":"Stoke - Coventry","browser_uuid":"\/regarder-stoke-vs-coventry-16h00-streaming-direct","sport_name":"\u00b7 Championship","sport_flag":"","date_time":"2025\/11\/08 \u00e0 08:18","live":[]},{"id":"690ec48c28dd0","title":"Swansea - Ipswich","browser_uuid":"\/regarder-swansea-vs-ipswich-16h00-streaming-direct","sport_name":"\u00b7 Championship","sport_flag":"","date_time":"2025\/11\/08 \u00e0 08:18","live":[]},{"id":"690ec48c28dd1","title":"Sheffield Utd - QPR","browser_uuid":"\/regarder-sheffield-utd-vs-qpr-16h00-streaming-direct","sport_name":"\u00b7 Championship","sport_flag":"","date_time":"2025\/11\/08 \u00e0 08:18","live":[]},{"id":"690ec48c28dd2","title":"Middlesbrough - Birmingham","browser_uuid":"\/regarder-middlesbrough-vs-birmingham-16h00-streaming-direct","sport_name":"\u00b7 Championship","sport_flag":"","date_time":"2025\/11\/08 \u00e0 08:18","live":[]},{"id":"690ec48c28dd3","title":"Panetolikos - AEL Larissa","browser_uuid":"\/regarder-panetolikos-vs-ael-larissa-16h00-streaming-direct","sport_name":"\u00b7 Betfred Super League","sport_flag":"","date_time":"2025\/11\/08 \u00e0 08:18","live":[]},{"id":"690ec48c28dd4","title":"Norwich - Leicester","browser_uuid":"\/regarder-norwich-vs-leicester-16h00-streaming-direct","sport_name":"\u00b7 Championship","sport_flag":"","date_time":"2025\/11\/08 \u00e0 08:18","live":[]},{"id":"690ec48c28dd5","title":"Ecosse - Nouvelle-Z\u00e9lande","browser_uuid":"\/regarder-ecosse-vs-nouvelle-zelande-16h10-streaming-direct","sport_name":"\u00b7 Tourn\u00e9e Automne","sport_flag":"","date_time":"2025\/11\/08 \u00e0 08:18","live":[]},{"id":"690ec48c28dd6","title":"Eibar - Albacete","browser_uuid":"\/regarder-eibar-vs-albacete-16h15-streaming-direct","sport_name":"\u00b7 Laliga 2","sport_flag":"","date_time":"2025\/11\/08 \u00e0 08:18","live":[]},{"id":"690ec48c28dd7","title":"FC S\u00e9ville - Osasuna","browser_uuid":"\/regarder-fc-seville-vs-osasuna-16h15-streaming-direct","sport_name":"\u00b7 Laliga","sport_flag":"","date_time":"2025\/11\/08 \u00e0 08:18","live":[]},{"id":"690ec48c28dd8","title":"Huesca - Andorra","browser_uuid":"\/regarder-huesca-vs-andorra-16h15-streaming-direct","sport_name":"\u00b7 Laliga 2","sport_flag":"","date_time":"2025\/11\/08 \u00e0 08:18","live":[]},{"id":"690ec48c28dd9","title":"Alverca - Rio Ave","browser_uuid":"\/regarder-alverca-vs-rio-ave-16h30-streaming-direct","sport_name":"\u00b7 Liga Portugal","sport_flag":"","date_time":"2025\/11\/08 \u00e0 08:18","live":[]},{"id":"690ec48c28dda","title":"RC Toulon - Stade Rochelais","browser_uuid":"\/regarder-rc-toulon-vs-stade-rochelais-16h30-streaming-direct","sport_name":"\u00b7 Top 14","sport_flag":"","date_time":"2025\/11\/08 \u00e0 08:18","live":[]},{"id":"690ec48c28ddb","title":"Excelsior - Heracles","browser_uuid":"\/regarder-excelsior-vs-heracles-16h30-streaming-direct","sport_name":"\u00b7 Eredivisie","sport_flag":"","date_time":"2025\/11\/08 \u00e0 08:18","live":[]},{"id":"690ec48c28ddc","title":"La Serena - U. Catolica","browser_uuid":"\/regarder-la-serena-vs-u-catolica-16h30-streaming-direct","sport_name":"\u00b7 Campeonato Ita\u00fa Chile","sport_flag":"","date_time":"2025\/11\/08 \u00e0 08:18","live":[]},{"id":"690ec48c28ddd","title":"Marseille - Brest","browser_uuid":"\/regarder-marseille-vs-brest-17h00-streaming-direct","sport_name":"\u00b7 Ligue 1","sport_flag":"","date_time":"2025\/11\/08 \u00e0 08:18","live":[]},{"id":"690ec48c28dde","title":"Juventus - Torino","browser_uuid":"\/regarder-juventus-vs-torino-18h00-streaming-direct","sport_name":"\u00b7 Serie A","sport_flag":"","date_time":"2025\/11\/08 \u00e0 08:18","live":[]},{"id":"690ec48c28ddf","title":"Kasimpasa - Goztepe","browser_uuid":"\/regarder-kasimpasa-vs-goztepe-18h00-streaming-direct","sport_name":"\u00b7 Super Lig","sport_flag":"","date_time":"2025\/11\/08 \u00e0 08:18","live":[]},{"id":"690ec48c28de0","title":"Antalyaspor - Besiktas","browser_uuid":"\/regarder-antalyaspor-vs-besiktas-18h00-streaming-direct","sport_name":"\u00b7 Super Lig","sport_flag":"","date_time":"2025\/11\/08 \u00e0 08:18","live":[]},{"id":"690ec48c28de1","title":"Charleroi - Westerlo","browser_uuid":"\/regarder-charleroi-vs-westerlo-18h15-streaming-direct","sport_name":"\u00b7 Pro League","sport_flag":"","date_time":"2025\/11\/08 \u00e0 08:18","live":[]},{"id":"690ec48c28de2","title":"B. Monchengladbach - FC Cologne","browser_uuid":"\/regarder-b-monchengladbach-vs-fc-cologne-18h30-streaming-direct","sport_name":"\u00b7 Bundesliga","sport_flag":"","date_time":"2025\/11\/08 \u00e0 08:18","live":[]},{"id":"690ec48c28de3","title":"Al-Ittihad FC - Al Ahli SC","browser_uuid":"\/regarder-al-ittihad-fc-vs-al-ahli-sc-18h30-streaming-direct","sport_name":"\u00b7 Saudi Pro League","sport_flag":"","date_time":"2025\/11\/08 \u00e0 08:18","live":[]},{"id":"690ec48c28de4","title":"Atl. Madrid - Levante","browser_uuid":"\/regarder-atl-madrid-vs-levante-18h30-streaming-direct","sport_name":"\u00b7 Laliga","sport_flag":"","date_time":"2025\/11\/08 \u00e0 08:18","live":[]},{"id":"690ec48c28de5","title":"Sunderland - Arsenal","browser_uuid":"\/regarder-sunderland-vs-arsenal-18h30-streaming-direct","sport_name":"\u00b7 Premier League","sport_flag":"","date_time":"2025\/11\/08 \u00e0 08:18","live":[]},{"id":"690ec48c28de6","title":"New Jersey Devils - Pittsburgh Penguins","browser_uuid":"\/regarder-new-jersey-devils-vs-pittsburgh-penguins-18h30-streaming-direct","sport_name":"\u00b7 NHL","sport_flag":"","date_time":"2025\/11\/08 \u00e0 08:18","live":[]},{"id":"690ec48c28de7","title":"La Corogne - Cultural Leonesa","browser_uuid":"\/regarder-la-corogne-vs-cultural-leonesa-18h30-streaming-direct","sport_name":"\u00b7 Laliga 2","sport_flag":"","date_time":"2025\/11\/08 \u00e0 08:18","live":[]},{"id":"690ec48c28de8","title":"Italie - Australie","browser_uuid":"\/regarder-italie-vs-australie-18h40-streaming-direct","sport_name":"\u00b7 Tourn\u00e9e Automne","sport_flag":"","date_time":"2025\/11\/08 \u00e0 08:18","live":[]},{"id":"690ec48c28de9","title":"Angleterre - Fidji","browser_uuid":"\/regarder-angleterre-vs-fidji-18h40-streaming-direct","sport_name":"\u00b7 Tourn\u00e9e Automne","sport_flag":"","date_time":"2025\/11\/08 \u00e0 08:18","live":[]},{"id":"690ec48c28dea","title":"FC Volendam - Breda","browser_uuid":"\/regarder-fc-volendam-vs-breda-18h45-streaming-direct","sport_name":"\u00b7 Eredivisie","sport_flag":"","date_time":"2025\/11\/08 \u00e0 08:18","live":[]},{"id":"690ec48c28deb","title":"Le Havre - Nantes","browser_uuid":"\/regarder-le-havre-vs-nantes-19h00-streaming-direct","sport_name":"\u00b7 Ligue 1","sport_flag":"","date_time":"2025\/11\/08 \u00e0 08:18","live":[]},{"id":"690ec48c28dec","title":"Tondela - Guimaraes","browser_uuid":"\/regarder-tondela-vs-guimaraes-19h00-streaming-direct","sport_name":"\u00b7 Liga Portugal","sport_flag":"","date_time":"2025\/11\/08 \u00e0 08:18","live":[]},{"id":"690ec48c28ded","title":"Ayacucho - Comerciantes Unidos","browser_uuid":"\/regarder-ayacucho-vs-comerciantes-unidos-19h00-streaming-direct","sport_name":"\u00b7 Liga 1 Te Apuesto","sport_flag":"","date_time":"2025\/11\/08 \u00e0 08:18","live":[]},{"id":"690ec48c28dee","title":"U. Espanola - Colo Colo","browser_uuid":"\/regarder-u-espanola-vs-colo-colo-19h00-streaming-direct","sport_name":"\u00b7 Campeonato Ita\u00fa Chile","sport_flag":"","date_time":"2025\/11\/08 \u00e0 08:18","live":[]},{"id":"690ec48c28def","title":"Philadelphia Flyers - Ottawa Senators","browser_uuid":"\/regarder-philadelphia-flyers-vs-ottawa-senators-19h00-streaming-direct","sport_name":"\u00b7 NHL","sport_flag":"","date_time":"2025\/11\/08 \u00e0 08:18","live":[]},{"id":"690ec48c28df0","title":"Grand Prix de Sao Paulo Essais qualificatifs","browser_uuid":"\/regarder-grand-prix-de-sao-paulo-essais-qualificatifs-19h00-streaming-direct","sport_name":"\u00b7 formula 1","sport_flag":"","date_time":"2025\/11\/08 \u00e0 08:18","live":[]},{"id":"690ec48c28df1","title":"Manta - Mushuc Runa","browser_uuid":"\/regarder-manta-vs-mushuc-runa-20h00-streaming-direct","sport_name":"\u00b7 Ecuador Ligapro","sport_flag":"","date_time":"2025\/11\/08 \u00e0 08:18","live":[]},{"id":"690ec48c28df2","title":"Troyes - Saint-\u00c9tienne","browser_uuid":"\/regarder-troyes-vs-saint-Etienne-20h00-streaming-direct","sport_name":"\u00b7 Ligue 2","sport_flag":"","date_time":"2025\/11\/08 \u00e0 08:18","live":[]},{"id":"690ec48c28df3","title":"Sittard - Heerenveen","browser_uuid":"\/regarder-sittard-vs-heerenveen-20h00-streaming-direct","sport_name":"\u00b7 Eredivisie","sport_flag":"","date_time":"2025\/11\/08 \u00e0 08:18","live":[]},{"id":"690ec48c28df4","title":"Sport Recife - Atletico-MG","browser_uuid":"\/regarder-sport-recife-vs-atletico-mg-20h00-streaming-direct","sport_name":"\u00b7 Serie A Bresil","sport_flag":"","date_time":"2025\/11\/08 \u00e0 08:18","live":[]},{"id":"690ec48c28df5","title":"Danubio - Plaza Colonia","browser_uuid":"\/regarder-danubio-vs-plaza-colonia-20h30-streaming-direct","sport_name":"\u00b7 Liga AUF Uruguaya","sport_flag":"","date_time":"2025\/11\/08 \u00e0 08:18","live":[]},{"id":"690ec48c28df6","title":"Kaiserslautern - Hertha Berlin","browser_uuid":"\/regarder-kaiserslautern-vs-hertha-berlin-20h30-streaming-direct","sport_name":"\u00b7 Bundesliga 2","sport_flag":"","date_time":"2025\/11\/08 \u00e0 08:18","live":[]},{"id":"690ec48c28df7","title":"Antwerp - RAAL La Louviere","browser_uuid":"\/regarder-antwerp-vs-raal-la-louviere-20h45-streaming-direct","sport_name":"\u00b7 Pro League","sport_flag":"","date_time":"2025\/11\/08 \u00e0 08:18","live":[]},{"id":"690ec48c28df8","title":"Parme - AC Milan","browser_uuid":"\/regarder-parme-vs-ac-milan-20h45-streaming-direct","sport_name":"\u00b7 Serie A","sport_flag":"","date_time":"2025\/11\/08 \u00e0 08:18","live":[]},{"id":"690ec48c28df9","title":"Zwolle - Sparta Rotterdam","browser_uuid":"\/regarder-zwolle-vs-sparta-rotterdam-21h00-streaming-direct","sport_name":"\u00b7 Eredivisie","sport_flag":"","date_time":"2025\/11\/08 \u00e0 08:18","live":[]},{"id":"690ec48c28dfa","title":"PSG F - Fleury 91 F","browser_uuid":"\/regarder-psg-f-vs-fleury-91-f-21h00-streaming-direct","sport_name":"\u00b7 D1 F\u00e9minin","sport_flag":"","date_time":"2025\/11\/08 \u00e0 08:18","live":[]},{"id":"690ec48c28dfb","title":"Huracan - Newells Old Boys","browser_uuid":"\/regarder-huracan-vs-newells-old-boys-21h00-streaming-direct","sport_name":"\u00b7 Torneo LPF","sport_flag":"","date_time":"2025\/11\/08 \u00e0 08:18","live":[]},{"id":"690ec48c28dfc","title":"Racing Club - Defensa y Justicia","browser_uuid":"\/regarder-racing-club-vs-defensa-y-justicia-21h00-streaming-direct","sport_name":"\u00b7 Torneo LPF","sport_flag":"","date_time":"2025\/11\/08 \u00e0 08:18","live":[]},{"id":"690ec48c28dfd","title":"Espanyol - Villarreal","browser_uuid":"\/regarder-espanyol-vs-villarreal-21h00-streaming-direct","sport_name":"\u00b7 Laliga","sport_flag":"","date_time":"2025\/11\/08 \u00e0 08:18","live":[]},{"id":"690ec48c28dfe","title":"Chelsea - Wolves","browser_uuid":"\/regarder-chelsea-vs-wolves-21h00-streaming-direct","sport_name":"\u00b7 Premier League","sport_flag":"","date_time":"2025\/11\/08 \u00e0 08:18","live":[]},{"id":"690ec48c28dff","title":"Malaga - Cordoba","browser_uuid":"\/regarder-malaga-vs-cordoba-21h00-streaming-direct","sport_name":"\u00b7 Laliga 2","sport_flag":"","date_time":"2025\/11\/08 \u00e0 08:18","live":[]},{"id":"690ec48c28e00","title":"Monaco - Lens","browser_uuid":"\/regarder-monaco-vs-lens-21h05-streaming-direct","sport_name":"\u00b7 Ligue 1","sport_flag":"","date_time":"2025\/11\/08 \u00e0 08:18","live":[]},{"id":"690ec48c28e01","title":"France - Afrique du Sud","browser_uuid":"\/regarder-france-vs-afrique-du-sud-21h10-streaming-direct","sport_name":"\u00b7 Tourn\u00e9e Automne","sport_flag":"","date_time":"2025\/11\/08 \u00e0 08:18","live":[]},{"id":"690ec48c28e02","title":"Juan Pablo II - Grau","browser_uuid":"\/regarder-juan-pablo-ii-vs-grau-21h15-streaming-direct","sport_name":"\u00b7 Liga 1 Te Apuesto","sport_flag":"","date_time":"2025\/11\/08 \u00e0 08:18","live":[]},{"id":"690ec48c28e03","title":"Nashville Predators - Dallas Stars","browser_uuid":"\/regarder-nashville-predators-vs-dallas-stars-21h30-streaming-direct","sport_name":"\u00b7 NHL","sport_flag":"","date_time":"2025\/11\/08 \u00e0 08:18","live":[]},{"id":"690ec48c28e04","title":"Palestino - Coquimbo","browser_uuid":"\/regarder-palestino-vs-coquimbo-21h30-streaming-direct","sport_name":"\u00b7 Campeonato Ita\u00fa Chile","sport_flag":"","date_time":"2025\/11\/08 \u00e0 08:18","live":[]},{"id":"690ec48c28e05","title":"Santa Clara - Sporting","browser_uuid":"\/regarder-santa-clara-vs-sporting-21h30-streaming-direct","sport_name":"\u00b7 Liga Portugal","sport_flag":"","date_time":"2025\/11\/08 \u00e0 08:18","live":[]},{"id":"690ec48c28e06","title":"Vasco - Juventude","browser_uuid":"\/regarder-vasco-vs-juventude-22h00-streaming-direct","sport_name":"\u00b7 Serie A Bresil","sport_flag":"","date_time":"2025\/11\/08 \u00e0 08:18","live":[]},{"id":"690ec48c28e07","title":"Minnesota - Seattle Sounders","browser_uuid":"\/regarder-minnesota-vs-seattle-sounders-22h00-streaming-direct","sport_name":"\u00b7 MLS","sport_flag":"","date_time":"2025\/11\/08 \u00e0 08:18","live":[]},{"id":"690ec48c28e08","title":"Fortaleza - Junior","browser_uuid":"\/regarder-fortaleza-vs-junior-22h10-streaming-direct","sport_name":"\u00b7 Liga Betplay Dimayor","sport_flag":"","date_time":"2025\/11\/08 \u00e0 08:18","live":[]},{"id":"690ec48c28e09","title":"Internacional - Bahia","browser_uuid":"\/regarder-internacional-vs-bahia-22h30-streaming-direct","sport_name":"\u00b7 Serie A Bresil","sport_flag":"","date_time":"2025\/11\/08 \u00e0 08:18","live":[]},{"id":"690ec48c28e0a","title":"Ind. del Valle - U. Catolica","browser_uuid":"\/regarder-ind-del-valle-vs-u-catolica-22h30-streaming-direct","sport_name":"\u00b7 Ecuador Ligapro","sport_flag":"","date_time":"2025\/11\/08 \u00e0 08:18","live":[]},{"id":"690ec48c28e0b","title":"Wanderers - River Plate","browser_uuid":"\/regarder-wanderers-vs-river-plate-23h00-streaming-direct","sport_name":"\u00b7 Liga AUF Uruguaya","sport_flag":"","date_time":"2025\/11\/08 \u00e0 08:18","live":[]},{"id":"690ec48c28e0c","title":"Talleres Cordoba - Platense","browser_uuid":"\/regarder-talleres-cordoba-vs-platense-23h15-streaming-direct","sport_name":"\u00b7 Torneo LPF","sport_flag":"","date_time":"2025\/11\/08 \u00e0 08:18","live":[]},{"id":"690ec48c28e0d","title":"Tigres - Atl. San Luis","browser_uuid":"\/regarder-tigres-vs-atl-san-luis-00h00-streaming-direct","sport_name":"\u00b7 Liga Mx","sport_flag":"","date_time":"2025\/11\/08 \u00e0 08:18","live":[]},{"id":"690ec48c28e0e","title":"Cincinnati - Columbus Crew","browser_uuid":"\/regarder-cincinnati-vs-columbus-crew-00h00-streaming-direct","sport_name":"\u00b7 MLS","sport_flag":"","date_time":"2025\/11\/08 \u00e0 08:18","live":[]},{"id":"690ec48c28e0f","title":"Guadalajara - Monterrey","browser_uuid":"\/regarder-guadalajara-vs-monterrey-00h07-streaming-direct","sport_name":"\u00b7 Liga Mx","sport_flag":"","date_time":"2025\/11\/08 \u00e0 08:18","live":[]},{"id":"690ec48c28e10","title":"Atl. Nacional - Aguilas","browser_uuid":"\/regarder-atl-nacional-vs-aguilas-00h20-streaming-direct","sport_name":"\u00b7 Liga Betplay Dimayor","sport_flag":"","date_time":"2025\/11\/08 \u00e0 08:18","live":[]},{"id":"690ec48c28e11","title":"O'Higgins - Nublense","browser_uuid":"\/regarder-o-higgins-vs-nublense-00h30-streaming-direct","sport_name":"\u00b7 Campeonato Ita\u00fa Chile","sport_flag":"","date_time":"2025\/11\/08 \u00e0 08:18","live":[]},{"id":"690ec48c28e12","title":"Montreal Canadiens - Utah Mammoth","browser_uuid":"\/regarder-montreal-canadiens-vs-utah-mammoth-01h00-streaming-direct","sport_name":"\u00b7 NHL","sport_flag":"","date_time":"2025\/11\/08 \u00e0 08:18","live":[]},{"id":"690ec48c28e13","title":"New York Rangers - New York Islanders","browser_uuid":"\/regarder-new-york-rangers-vs-new-york-islanders-01h00-streaming-direct","sport_name":"\u00b7 NHL","sport_flag":"","date_time":"2025\/11\/08 \u00e0 08:18","live":[]},{"id":"690ec48c28e14","title":"LDU Quito - Libertad","browser_uuid":"\/regarder-ldu-quito-vs-libertad-01h00-streaming-direct","sport_name":"\u00b7 Ecuador Ligapro","sport_flag":"","date_time":"2025\/11\/08 \u00e0 08:18","live":[]},{"id":"690ec48c28e15","title":"Tampa Bay Lightning - Washington Capitals","browser_uuid":"\/regarder-tampa-bay-lightning-vs-washington-capitals-01h00-streaming-direct","sport_name":"\u00b7 NHL","sport_flag":"","date_time":"2025\/11\/08 \u00e0 08:18","live":[]},{"id":"690ec48c28e16","title":"Sao Paulo - Bragantino","browser_uuid":"\/regarder-sao-paulo-vs-bragantino-01h00-streaming-direct","sport_name":"\u00b7 Serie A Bresil","sport_flag":"","date_time":"2025\/11\/08 \u00e0 08:18","live":[]},{"id":"690ec48c28e17","title":"Washington Wizards - Dallas Mavericks","browser_uuid":"\/regarder-washington-wizards-vs-dallas-mavericks-01h00-streaming-direct","sport_name":"\u00b7 NBA","sport_flag":"","date_time":"2025\/11\/08 \u00e0 08:18","live":[]},{"id":"690ec48c28e18","title":"Toronto Maple Leafs - Boston Bruins","browser_uuid":"\/regarder-toronto-maple-leafs-vs-boston-bruins-01h00-streaming-direct","sport_name":"\u00b7 NHL","sport_flag":"","date_time":"2025\/11\/08 \u00e0 08:18","live":[]},{"id":"690ec48c28e19","title":"St. Louis Blues - Seattle Kraken","browser_uuid":"\/regarder-st-louis-blues-vs-seattle-kraken-01h00-streaming-direct","sport_name":"\u00b7 NHL","sport_flag":"","date_time":"2025\/11\/08 \u00e0 08:18","live":[]},{"id":"690ec48c28e1a","title":"Carolina Hurricanes - Buffalo Sabres","browser_uuid":"\/regarder-carolina-hurricanes-vs-buffalo-sabres-01h00-streaming-direct","sport_name":"\u00b7 NHL","sport_flag":"","date_time":"2025\/11\/08 \u00e0 08:18","live":[]},{"id":"690ec48c28e1b","title":"Philadelphia 76ers - Toronto Raptors","browser_uuid":"\/regarder-philadelphia-76ers-vs-toronto-raptors-01h30-streaming-direct","sport_name":"\u00b7 NBA","sport_flag":"","date_time":"2025\/11\/08 \u00e0 08:18","live":[]},{"id":"690ec48c28e1c","title":"San Martin S.J. - Lanus","browser_uuid":"\/regarder-san-martin-s-j-vs-lanus-01h30-streaming-direct","sport_name":"\u00b7 Torneo LPF","sport_flag":"","date_time":"2025\/11\/08 \u00e0 08:18","live":[]},{"id":"690ec48c28e1d","title":"Union Santa Fe - Barracas Central","browser_uuid":"\/regarder-union-santa-fe-vs-barracas-central-01h30-streaming-direct","sport_name":"\u00b7 Torneo LPF","sport_flag":"","date_time":"2025\/11\/08 \u00e0 08:18","live":[]},{"id":"690ec48c28e1e","title":"Cleveland Cavaliers - Chicago Bulls","browser_uuid":"\/regarder-cleveland-cavaliers-vs-chicago-bulls-02h00-streaming-direct","sport_name":"\u00b7 NBA","sport_flag":"","date_time":"2025\/11\/08 \u00e0 08:18","live":[]},{"id":"690ec48c28e1f","title":"Cancun - Leones Negros","browser_uuid":"\/regarder-cancun-vs-leones-negros-02h00-streaming-direct","sport_name":"\u00b7 Liga De Expansion Mx","sport_flag":"","date_time":"2025\/11\/08 \u00e0 08:18","live":[]},{"id":"690ec48c28e20","title":"Atlanta Hawks - Los Angeles Lakers","browser_uuid":"\/regarder-atlanta-hawks-vs-los-angeles-lakers-02h00-streaming-direct","sport_name":"\u00b7 NBA","sport_flag":"","date_time":"2025\/11\/08 \u00e0 08:18","live":[]},{"id":"690ec48c28e21","title":"San Antonio Spurs - New Orleans Pelicans","browser_uuid":"\/regarder-san-antonio-spurs-vs-new-orleans-pelicans-02h00-streaming-direct","sport_name":"\u00b7 NBA","sport_flag":"","date_time":"2025\/11\/08 \u00e0 08:18","live":[]},{"id":"690ec48c28e22","title":"Miami Heat - Portland Trail Blazers","browser_uuid":"\/regarder-miami-heat-vs-portland-trail-blazers-02h00-streaming-direct","sport_name":"\u00b7 NBA","sport_flag":"","date_time":"2025\/11\/08 \u00e0 08:18","live":[]},{"id":"690ec48c28e23","title":"Inter Miami - Nashville SC","browser_uuid":"\/regarder-inter-miami-vs-nashville-sc-02h00-streaming-direct","sport_name":"\u00b7 MLS","sport_flag":"","date_time":"2025\/11\/08 \u00e0 08:18","live":[]},{"id":"690ec48c28e24","title":"Leon - Puebla","browser_uuid":"\/regarder-leon-vs-puebla-02h00-streaming-direct","sport_name":"\u00b7 Liga Mx","sport_flag":"","date_time":"2025\/11\/08 \u00e0 08:18","live":[]},{"id":"690ec48c28e25","title":"Toluca - Club America","browser_uuid":"\/regarder-toluca-vs-club-america-02h00-streaming-direct","sport_name":"\u00b7 Liga Mx","sport_flag":"","date_time":"2025\/11\/08 \u00e0 08:18","live":[]},{"id":"690ec48c28e26","title":"Bucaramanga - La Equidad","browser_uuid":"\/regarder-bucaramanga-vs-la-equidad-02h30-streaming-direct","sport_name":"\u00b7 Liga Betplay Dimayor","sport_flag":"","date_time":"2025\/11\/08 \u00e0 08:18","live":[]},{"id":"690ec48c28e27","title":"Denver Nuggets - Indiana Pacers","browser_uuid":"\/regarder-denver-nuggets-vs-indiana-pacers-03h00-streaming-direct","sport_name":"\u00b7 NBA","sport_flag":"","date_time":"2025\/11\/08 \u00e0 08:18","live":[]},{"id":"690ec48c28e28","title":"Vegas Golden Knights - Anaheim Ducks","browser_uuid":"\/regarder-vegas-golden-knights-vs-anaheim-ducks-04h00-streaming-direct","sport_name":"\u00b7 NHL","sport_flag":"","date_time":"2025\/11\/08 \u00e0 08:18","live":[]},{"id":"690ec48c28e29","title":"San Jose Sharks - Florida Panthers","browser_uuid":"\/regarder-san-jose-sharks-vs-florida-panthers-04h00-streaming-direct","sport_name":"\u00b7 NHL","sport_flag":"","date_time":"2025\/11\/08 \u00e0 08:18","live":[]},{"id":"690ec48c28e2a","title":"Pachuca F - Cruz Azul F","browser_uuid":"\/regarder-pachuca-f-vs-cruz-azul-f-04h00-streaming-direct","sport_name":"\u00b7 Liga Mx Women","sport_flag":"","date_time":"2025\/11\/08 \u00e0 08:18","live":[]},{"id":"690ec48c28e2b","title":"Edmonton Oilers - Colorado Avalanche","browser_uuid":"\/regarder-edmonton-oilers-vs-colorado-avalanche-04h00-streaming-direct","sport_name":"\u00b7 NHL","sport_flag":"","date_time":"2025\/11\/08 \u00e0 08:18","live":[]},{"id":"690ec48c28e2c","title":"Vancouver Canucks - Columbus Blue Jackets","browser_uuid":"\/regarder-vancouver-canucks-vs-columbus-blue-jackets-04h00-streaming-direct","sport_name":"\u00b7 NHL","sport_flag":"","date_time":"2025\/11\/08 \u00e0 08:18","live":[]},{"id":"690ec48c28e2d","title":"Atl. Morelia - Tampico Madero","browser_uuid":"\/regarder-atl-morelia-vs-tampico-madero-04h00-streaming-direct","sport_name":"\u00b7 Liga De Expansion Mx","sport_flag":"","date_time":"2025\/11\/08 \u00e0 08:18","live":[]},{"id":"690ec48c28e2e","title":"Cruz Azul - U.N.A.M.","browser_uuid":"\/regarder-cruz-azul-vs-u-n-a-m-04h05-streaming-direct","sport_name":"\u00b7 Liga Mx","sport_flag":"","date_time":"2025\/11\/08 \u00e0 08:18","live":[]},{"id":"690ec48c28e2f","title":"Los Angeles Clippers - Phoenix Suns","browser_uuid":"\/regarder-los-angeles-clippers-vs-phoenix-suns-04h30-streaming-direct","sport_name":"\u00b7 NBA","sport_flag":"","date_time":"2025\/11\/08 \u00e0 08:18","live":[]},{"id":"690ec48c28e30","title":"Grand Prix du Portugal Warm Up des Moto GP","browser_uuid":"\/regarder-grand-prix-du-portugal-warm-up-des-moto-gp-10h40-streaming-direct","sport_name":"\u00b7 MotoGP","sport_flag":"","date_time":"2025\/11\/08 \u00e0 08:18","live":[]},{"id":"690ec48c28e31","title":"Grand Prix du Portugal Parade des pilotes","browser_uuid":"\/regarder-grand-prix-du-portugal-parade-des-pilotes-11h00-streaming-direct","sport_name":"\u00b7 MotoGP","sport_flag":"","date_time":"2025\/11\/08 \u00e0 08:18","live":[]},{"id":"690ec48c28e32","title":"Lleida - Baskonia","browser_uuid":"\/regarder-lleida-vs-baskonia-12h00-streaming-direct","sport_name":"\u00b7 Liga Endesa","sport_flag":"","date_time":"2025\/11\/08 \u00e0 08:18","live":[]},{"id":"690ec48c28e33","title":"Basquet Girona - Barcelone","browser_uuid":"\/regarder-basquet-girona-vs-barcelone-12h15-streaming-direct","sport_name":"\u00b7 Liga Endesa","sport_flag":"","date_time":"2025\/11\/08 \u00e0 08:18","live":[]},{"id":"690ec48c28e34","title":"Grand Prix du Portugal La course des Moto 2","browser_uuid":"\/regarder-grand-prix-du-portugal-la-course-des-moto-2-12h15-streaming-direct","sport_name":"\u00b7 Moto2","sport_flag":"","date_time":"2025\/11\/08 \u00e0 08:18","live":[]},{"id":"690ec48c28e35","title":"Utrecht - Ajax","browser_uuid":"\/regarder-utrecht-vs-ajax-12h15-streaming-direct","sport_name":"\u00b7 Eredivisie","sport_flag":"","date_time":"2025\/11\/08 \u00e0 08:18","live":[]},{"id":"690ec48c28e36","title":"Atalanta - Sassuolo","browser_uuid":"\/regarder-atalanta-vs-sassuolo-12h30-streaming-direct","sport_name":"\u00b7 Serie A","sport_flag":"","date_time":"2025\/11\/08 \u00e0 08:18","live":[]},{"id":"690ec48c28e37","title":"Karagumruk - Konyaspor","browser_uuid":"\/regarder-karagumruk-vs-konyaspor-12h30-streaming-direct","sport_name":"\u00b7 Super Lig","sport_flag":"","date_time":"2025\/11\/08 \u00e0 08:18","live":[]},{"id":"690ec48c28e38","title":"Magdeburg - Paderborn","browser_uuid":"\/regarder-magdeburg-vs-paderborn-13h30-streaming-direct","sport_name":"\u00b7 Bundesliga 2","sport_flag":"","date_time":"2025\/11\/08 \u00e0 08:18","live":[]},{"id":"690ec48c28e39","title":"Braunschweig - Bochum","browser_uuid":"\/regarder-braunschweig-vs-bochum-13h30-streaming-direct","sport_name":"\u00b7 Bundesliga 2","sport_flag":"","date_time":"2025\/11\/08 \u00e0 08:18","live":[]},{"id":"690ec48c28e3a","title":"Bundesliga 2 konferenz","browser_uuid":"\/regarder-bundesliga-2-konferenz-13h30-streaming-direct","sport_name":"\u00b7 Bundesliga 2","sport_flag":"","date_time":"2025\/11\/08 \u00e0 08:18","live":[]},{"id":"690ec48c28e3b","title":"Anderlecht - Club Brugge","browser_uuid":"\/regarder-anderlecht-vs-club-brugge-13h30-streaming-direct","sport_name":"\u00b7 Pro League","sport_flag":"","date_time":"2025\/11\/08 \u00e0 08:18","live":[]},{"id":"690ec48c28e3c","title":"Holstein Kiel - D\u00fcsseldorf","browser_uuid":"\/regarder-holstein-kiel-vs-dusseldorf-13h30-streaming-direct","sport_name":"\u00b7 Bundesliga 2","sport_flag":"","date_time":"2025\/11\/08 \u00e0 08:18","live":[]},{"id":"690ec48c28e3d","title":"Ath. Bilbao - Oviedo","browser_uuid":"\/regarder-ath-bilbao-vs-oviedo-14h00-streaming-direct","sport_name":"\u00b7 Laliga","sport_flag":"","date_time":"2025\/11\/08 \u00e0 08:18","live":[]},{"id":"690ec48c28e3e","title":"Cerro CA - Boston River","browser_uuid":"\/regarder-cerro-ca-vs-boston-river-14h00-streaming-direct","sport_name":"\u00b7 Liga AUF Uruguaya","sport_flag":"","date_time":"2025\/11\/08 \u00e0 08:18","live":[]},{"id":"690ec48c28e3f","title":"Moto GP Grand Prix du Portugal","browser_uuid":"\/regarder-moto-gp-grand-prix-du-portugal-14h00-streaming-direct","sport_name":"\u00b7 MotoGP","sport_flag":"","date_time":"2025\/11\/08 \u00e0 08:18","live":[]},{"id":"690ec48c28e40","title":"Las Palmas - Racing Santander","browser_uuid":"\/regarder-las-palmas-vs-racing-santander-14h00-streaming-direct","sport_name":"\u00b7 Laliga 2","sport_flag":"","date_time":"2025\/11\/08 \u00e0 08:18","live":[]},{"id":"690ec48c28e41","title":"Aris - Asteras T.","browser_uuid":"\/regarder-aris-vs-asteras-t-14h00-streaming-direct","sport_name":"\u00b7 Betfred Super League","sport_flag":"","date_time":"2025\/11\/08 \u00e0 08:18","live":[]},{"id":"690ec48c28e42","title":"Kifisia - Olympiakos","browser_uuid":"\/regarder-kifisia-vs-olympiakos-14h00-streaming-direct","sport_name":"\u00b7 Betfred Super League","sport_flag":"","date_time":"2025\/11\/08 \u00e0 08:18","live":[]},{"id":"690ec48c28e43","title":"Nijmegen - Groningen","browser_uuid":"\/regarder-nijmegen-vs-groningen-14h30-streaming-direct","sport_name":"\u00b7 Eredivisie","sport_flag":"","date_time":"2025\/11\/08 \u00e0 08:18","live":[]},{"id":"690ec48c28e44","title":"Multiplex Premier League","browser_uuid":"\/regarder-multiplex-premier-league-15h00-streaming-direct","sport_name":"\u00b7 Premier League","sport_flag":"","date_time":"2025\/11\/08 \u00e0 08:18","live":[]},{"id":"690ec48c28e45","title":"Genoa - Fiorentina","browser_uuid":"\/regarder-genoa-vs-fiorentina-15h00-streaming-direct","sport_name":"\u00b7 Serie A","sport_flag":"","date_time":"2025\/11\/08 \u00e0 08:18","live":[]},{"id":"690ec48c28e46","title":"Aston Villa - Bournemouth","browser_uuid":"\/regarder-aston-villa-vs-bournemouth-15h00-streaming-direct","sport_name":"\u00b7 Premier League","sport_flag":"","date_time":"2025\/11\/08 \u00e0 08:18","live":[]},{"id":"690ec48c28e47","title":"Brentford - Newcastle","browser_uuid":"\/regarder-brentford-vs-newcastle-15h00-streaming-direct","sport_name":"\u00b7 Premier League","sport_flag":"","date_time":"2025\/11\/08 \u00e0 08:18","live":[]},{"id":"690ec48c28e48","title":"Bologne - Naples","browser_uuid":"\/regarder-bologne-vs-naples-15h00-streaming-direct","sport_name":"\u00b7 Serie A","sport_flag":"","date_time":"2025\/11\/08 \u00e0 08:18","live":[]},{"id":"690ec48c28e49","title":"Lorient - Toulouse","browser_uuid":"\/regarder-lorient-vs-toulouse-15h00-streaming-direct","sport_name":"\u00b7 Ligue 1","sport_flag":"","date_time":"2025\/11\/08 \u00e0 08:18","live":[]},{"id":"690ec48c28e4a","title":"Nottingham - Leeds","browser_uuid":"\/regarder-nottingham-vs-leeds-15h00-streaming-direct","sport_name":"\u00b7 Premier League","sport_flag":"","date_time":"2025\/11\/08 \u00e0 08:18","live":[]},{"id":"690ec48c28e4b","title":"Crystal Palace - Brighton","browser_uuid":"\/regarder-crystal-palace-vs-brighton-15h00-streaming-direct","sport_name":"\u00b7 Premier League","sport_flag":"","date_time":"2025\/11\/08 \u00e0 08:18","live":[]},{"id":"690ec48c28e4c","title":"Kocaelispor - Galatasaray","browser_uuid":"\/regarder-kocaelispor-vs-galatasaray-15h00-streaming-direct","sport_name":"\u00b7 Super Lig","sport_flag":"","date_time":"2025\/11\/08 \u00e0 08:18","live":[]},{"id":"690ec48c28e4d","title":"Grand Prix du Portugal La course des Moto 3","browser_uuid":"\/regarder-grand-prix-du-portugal-la-course-des-moto-3-15h30-streaming-direct","sport_name":"\u00b7 Moto3","sport_flag":"","date_time":"2025\/11\/08 \u00e0 08:18","live":[]},{"id":"690ec48c28e4e","title":"Fribourg - St. Pauli","browser_uuid":"\/regarder-fribourg-vs-st-pauli-15h30-streaming-direct","sport_name":"\u00b7 Bundesliga","sport_flag":"","date_time":"2025\/11\/08 \u00e0 08:18","live":[]},{"id":"690ec48c28e4f","title":"Indianapolis Colts - Atlanta Falcons","browser_uuid":"\/regarder-indianapolis-colts-vs-atlanta-falcons-15h30-streaming-direct","sport_name":"\u00b7 NFL","sport_flag":"","date_time":"2025\/11\/08 \u00e0 08:18","live":[]},{"id":"690ec48c28e50","title":"Dundee FC - Rangers","browser_uuid":"\/regarder-dundee-fc-vs-rangers-16h00-streaming-direct","sport_name":"\u00b7 Premiership","sport_flag":"","date_time":"2025\/11\/08 \u00e0 08:18","live":[]},{"id":"690ec48c28e51","title":"Saint-Trond - Standard Li\u00e8ge","browser_uuid":"\/regarder-saint-trond-vs-standard-liege-16h00-streaming-direct","sport_name":"\u00b7 Pro League","sport_flag":"","date_time":"2025\/11\/08 \u00e0 08:18","live":[]},{"id":"690ec48c28e52","title":"Levadiakos - Panserraikos","browser_uuid":"\/regarder-levadiakos-vs-panserraikos-16h00-streaming-direct","sport_name":"\u00b7 Betfred Super League","sport_flag":"","date_time":"2025\/11\/08 \u00e0 08:18","live":[]},{"id":"690ec48c28e53","title":"Pays de Galles - Argentine","browser_uuid":"\/regarder-pays-de-galles-vs-argentine-16h10-streaming-direct","sport_name":"\u00b7 Tourn\u00e9e Automne","sport_flag":"","date_time":"2025\/11\/08 \u00e0 08:18","live":[]},{"id":"690ec48c28e54","title":"Ceuta - Almeria","browser_uuid":"\/regarder-ceuta-vs-almeria-16h15-streaming-direct","sport_name":"\u00b7 Laliga 2","sport_flag":"","date_time":"2025\/11\/08 \u00e0 08:18","live":[]},{"id":"690ec48c28e55","title":"Vallecano - Real Madrid","browser_uuid":"\/regarder-vallecano-vs-real-madrid-16h15-streaming-direct","sport_name":"\u00b7 Laliga","sport_flag":"","date_time":"2025\/11\/08 \u00e0 08:18","live":[]},{"id":"690ec48c28e56","title":"OFI Crete - AEK","browser_uuid":"\/regarder-ofi-crete-vs-aek-16h30-streaming-direct","sport_name":"\u00b7 Betfred Super League","sport_flag":"","date_time":"2025\/11\/08 \u00e0 08:18","live":[]},{"id":"690ec48c28e57","title":"AFS - Gil Vicente","browser_uuid":"\/regarder-afs-vs-gil-vicente-16h30-streaming-direct","sport_name":"\u00b7 Liga Portugal","sport_flag":"","date_time":"2025\/11\/08 \u00e0 08:18","live":[]},{"id":"690ec48c28e58","title":"Estrela - Nacional","browser_uuid":"\/regarder-estrela-vs-nacional-16h30-streaming-direct","sport_name":"\u00b7 Liga Portugal","sport_flag":"","date_time":"2025\/11\/08 \u00e0 08:18","live":[]},{"id":"690ec48c28e59","title":"Alkmaar - PSV","browser_uuid":"\/regarder-alkmaar-vs-psv-16h45-streaming-direct","sport_name":"\u00b7 Eredivisie","sport_flag":"","date_time":"2025\/11\/08 \u00e0 08:18","live":[]},{"id":"690ec48c28e5a","title":"Celtic - Kilmarnock","browser_uuid":"\/regarder-celtic-vs-kilmarnock-17h00-streaming-direct","sport_name":"\u00b7 Premiership","sport_flag":"","date_time":"2025\/11\/08 \u00e0 08:18","live":[]},{"id":"690ec48c28e5b","title":"Grenade - Valence","browser_uuid":"\/regarder-grenade-vs-valence-17h00-streaming-direct","sport_name":"\u00b7 Liga Endesa","sport_flag":"","date_time":"2025\/11\/08 \u00e0 08:18","live":[]},{"id":"690ec48c28e5c","title":"Multiplex Ligue 1","browser_uuid":"\/regarder-multiplex-ligue-1-17h15-streaming-direct","sport_name":"\u00b7 Ligue 1","sport_flag":"","date_time":"2025\/11\/08 \u00e0 08:18","live":[]},{"id":"690ec48c28e5d","title":"Angers - Auxerre","browser_uuid":"\/regarder-angers-vs-auxerre-17h15-streaming-direct","sport_name":"\u00b7 Ligue 1","sport_flag":"","date_time":"2025\/11\/08 \u00e0 08:18","live":[]},{"id":"690ec48c28e5e","title":"Strasbourg - Lille","browser_uuid":"\/regarder-strasbourg-vs-lille-17h15-streaming-direct","sport_name":"\u00b7 Ligue 1","sport_flag":"","date_time":"2025\/11\/08 \u00e0 08:18","live":[]},{"id":"690ec48c28e5f","title":"Metz - Nice","browser_uuid":"\/regarder-metz-vs-nice-17h15-streaming-direct","sport_name":"\u00b7 Ligue 1","sport_flag":"","date_time":"2025\/11\/08 \u00e0 08:18","live":[]},{"id":"690ec48c28e60","title":"Stuttgart - Augsburg","browser_uuid":"\/regarder-stuttgart-vs-augsburg-17h30-streaming-direct","sport_name":"\u00b7 Bundesliga","sport_flag":"","date_time":"2025\/11\/08 \u00e0 08:18","live":[]},{"id":"690ec48c28e61","title":"Manchester City - Liverpool","browser_uuid":"\/regarder-manchester-city-vs-liverpool-17h30-streaming-direct","sport_name":"\u00b7 Premier League","sport_flag":"","date_time":"2025\/11\/08 \u00e0 08:18","live":[]},{"id":"690ec48c28e62","title":"Bilbao - Zaragoza","browser_uuid":"\/regarder-bilbao-vs-zaragoza-18h00-streaming-direct","sport_name":"\u00b7 Liga Endesa","sport_flag":"","date_time":"2025\/11\/08 \u00e0 08:18","live":[]},{"id":"690ec48c28e63","title":"Fenerbahce - Kayserispor","browser_uuid":"\/regarder-fenerbahce-vs-kayserispor-18h00-streaming-direct","sport_name":"\u00b7 Super Lig","sport_flag":"","date_time":"2025\/11\/08 \u00e0 08:18","live":[]},{"id":"690ec48c28e64","title":"Formule 1 GP de Sao Paulo","browser_uuid":"\/regarder-formule-1-gp-de-sao-paulo-18h00-streaming-direct","sport_name":"\u00b7 formula 1","sport_flag":"","date_time":"2025\/11\/08 \u00e0 08:18","live":[]},{"id":"690ec48c28e65","title":"AS Rome - Udinese","browser_uuid":"\/regarder-as-rome-vs-udinese-18h00-streaming-direct","sport_name":"\u00b7 Serie A","sport_flag":"","date_time":"2025\/11\/08 \u00e0 08:18","live":[]},{"id":"690ec48c28e66","title":"Samsunspor - Eyupspor","browser_uuid":"\/regarder-samsunspor-vs-eyupspor-18h00-streaming-direct","sport_name":"\u00b7 Super Lig","sport_flag":"","date_time":"2025\/11\/08 \u00e0 08:18","live":[]},{"id":"690ec48c28e67","title":"Atromitos - Volos","browser_uuid":"\/regarder-atromitos-vs-volos-18h00-streaming-direct","sport_name":"\u00b7 Betfred Super League","sport_flag":"","date_time":"2025\/11\/08 \u00e0 08:18","live":[]},{"id":"690ec48c28e68","title":"Majorque - Getafe","browser_uuid":"\/regarder-majorque-vs-getafe-18h30-streaming-direct","sport_name":"\u00b7 Laliga","sport_flag":"","date_time":"2025\/11\/08 \u00e0 08:18","live":[]},{"id":"690ec48c28e69","title":"Valence - Betis","browser_uuid":"\/regarder-valence-vs-betis-18h30-streaming-direct","sport_name":"\u00b7 Laliga","sport_flag":"","date_time":"2025\/11\/08 \u00e0 08:18","live":[]},{"id":"690ec48c28e6a","title":"Grenade - Saragosse","browser_uuid":"\/regarder-grenade-vs-saragosse-18h30-streaming-direct","sport_name":"\u00b7 Laliga 2","sport_flag":"","date_time":"2025\/11\/08 \u00e0 08:18","live":[]},{"id":"690ec48c28e6b","title":"La Gantoise - Genk","browser_uuid":"\/regarder-la-gantoise-vs-genk-18h30-streaming-direct","sport_name":"\u00b7 Pro League","sport_flag":"","date_time":"2025\/11\/08 \u00e0 08:18","live":[]},{"id":"690ec48c28e6c","title":"Tecnico U. - Vinotinto","browser_uuid":"\/regarder-tecnico-u-vs-vinotinto-19h00-streaming-direct","sport_name":"\u00b7 Ecuador Ligapro","sport_flag":"","date_time":"2025\/11\/08 \u00e0 08:18","live":[]},{"id":"690ec48c28e6d","title":"Houston Texans - Jacksonville Jaguars","browser_uuid":"\/regarder-houston-texans-vs-jacksonville-jaguars-19h00-streaming-direct","sport_name":"\u00b7 NFL","sport_flag":"","date_time":"2025\/11\/08 \u00e0 08:18","live":[]},{"id":"690ec48c28e6e","title":"Miami Dolphins - Buffalo Bills","browser_uuid":"\/regarder-miami-dolphins-vs-buffalo-bills-19h00-streaming-direct","sport_name":"\u00b7 NFL","sport_flag":"","date_time":"2025\/11\/08 \u00e0 08:18","live":[]},{"id":"690ec48c28e6f","title":"Detroit Red Wings - Chicago Blackhawks","browser_uuid":"\/regarder-detroit-red-wings-vs-chicago-blackhawks-19h00-streaming-direct","sport_name":"\u00b7 NHL","sport_flag":"","date_time":"2025\/11\/08 \u00e0 08:18","live":[]},{"id":"690ec48c28e70","title":"Famalicao - FC Porto","browser_uuid":"\/regarder-famalicao-vs-fc-porto-19h00-streaming-direct","sport_name":"\u00b7 Liga Portugal","sport_flag":"","date_time":"2025\/11\/08 \u00e0 08:18","live":[]},{"id":"690ec48c28e71","title":"Cajamarca - Huancayo","browser_uuid":"\/regarder-cajamarca-vs-huancayo-19h00-streaming-direct","sport_name":"\u00b7 Liga 1 Te Apuesto","sport_flag":"","date_time":"2025\/11\/08 \u00e0 08:18","live":[]},{"id":"690ec48c28e72","title":"Chicago Bears - New York Giants","browser_uuid":"\/regarder-chicago-bears-vs-new-york-giants-19h00-streaming-direct","sport_name":"\u00b7 NFL","sport_flag":"","date_time":"2025\/11\/08 \u00e0 08:18","live":[]},{"id":"690ec48c28e73","title":"Minnesota Vikings - Baltimore Ravens","browser_uuid":"\/regarder-minnesota-vikings-vs-baltimore-ravens-19h00-streaming-direct","sport_name":"\u00b7 NFL","sport_flag":"","date_time":"2025\/11\/08 \u00e0 08:18","live":[]},{"id":"690ec48c28e74","title":"NFL RedZONE","browser_uuid":"\/regarder-nfl-redzone-19h00-streaming-direct","sport_name":"\u00b7 NFL","sport_flag":"","date_time":"2025\/11\/08 \u00e0 08:18","live":[]},{"id":"690ec48c28e75","title":"Tampa Bay Buccaneers - New England Patriots","browser_uuid":"\/regarder-tampa-bay-buccaneers-vs-new-england-patriots-19h00-streaming-direct","sport_name":"\u00b7 NFL","sport_flag":"","date_time":"2025\/11\/08 \u00e0 08:18","live":[]},{"id":"690ec48c28e76","title":"Carolina Panthers - New Orleans Saints","browser_uuid":"\/regarder-carolina-panthers-vs-new-orleans-saints-19h00-streaming-direct","sport_name":"\u00b7 NFL","sport_flag":"","date_time":"2025\/11\/08 \u00e0 08:18","live":[]},{"id":"690ec48c28e77","title":"Joventut - Real Madrid","browser_uuid":"\/regarder-joventut-vs-real-madrid-19h00-streaming-direct","sport_name":"\u00b7 Liga Endesa","sport_flag":"","date_time":"2025\/11\/08 \u00e0 08:18","live":[]},{"id":"690ec48c28e78","title":"New York Jets - Cleveland Browns","browser_uuid":"\/regarder-new-york-jets-vs-cleveland-browns-19h00-streaming-direct","sport_name":"\u00b7 NFL","sport_flag":"","date_time":"2025\/11\/08 \u00e0 08:18","live":[]},{"id":"690ec48c28e79","title":"Huachipato - A. Italiano","browser_uuid":"\/regarder-huachipato-vs-a-italiano-19h00-streaming-direct","sport_name":"\u00b7 Campeonato Ita\u00fa Chile","sport_flag":"","date_time":"2025\/11\/08 \u00e0 08:18","live":[]},{"id":"690ec48c28e7a","title":"Malines - Royale Union SG","browser_uuid":"\/regarder-malines-vs-royale-union-sg-19h15-streaming-direct","sport_name":"\u00b7 Pro League","sport_flag":"","date_time":"2025\/11\/08 \u00e0 08:18","live":[]},{"id":"690ec48c28e7b","title":"Eintracht Francfort - Mayence","browser_uuid":"\/regarder-eintracht-francfort-vs-mayence-19h30-streaming-direct","sport_name":"\u00b7 Bundesliga","sport_flag":"","date_time":"2025\/11\/08 \u00e0 08:18","live":[]},{"id":"690ec48c28e7c","title":"Corinthians - Ceara","browser_uuid":"\/regarder-corinthians-vs-ceara-20h00-streaming-direct","sport_name":"\u00b7 Serie A Bresil","sport_flag":"","date_time":"2025\/11\/08 \u00e0 08:18","live":[]},{"id":"690ec48c28e7d","title":"Vitoria - Botafogo RJ","browser_uuid":"\/regarder-vitoria-vs-botafogo-rj-20h00-streaming-direct","sport_name":"\u00b7 Serie A Bresil","sport_flag":"","date_time":"2025\/11\/08 \u00e0 08:18","live":[]},{"id":"690ec48c28e7e","title":"G.A. Eagles - Feyenoord","browser_uuid":"\/regarder-g-a-eagles-vs-feyenoord-20h00-streaming-direct","sport_name":"\u00b7 Eredivisie","sport_flag":"","date_time":"2025\/11\/08 \u00e0 08:18","live":[]},{"id":"690ec48c28e7f","title":"Pittsburgh Penguins - Los Angeles Kings","browser_uuid":"\/regarder-pittsburgh-penguins-vs-los-angeles-kings-20h00-streaming-direct","sport_name":"\u00b7 NHL","sport_flag":"","date_time":"2025\/11\/08 \u00e0 08:18","live":[]},{"id":"690ec48c28e80","title":"Panathinaikos - PAOK","browser_uuid":"\/regarder-panathinaikos-vs-paok-20h00-streaming-direct","sport_name":"\u00b7 Betfred Super League","sport_flag":"","date_time":"2025\/11\/08 \u00e0 08:18","live":[]},{"id":"690ec48c28e81","title":"Cruzeiro - Fluminense","browser_uuid":"\/regarder-cruzeiro-vs-fluminense-20h00-streaming-direct","sport_name":"\u00b7 Serie A Bresil","sport_flag":"","date_time":"2025\/11\/08 \u00e0 08:18","live":[]},{"id":"690ec48c28e82","title":"Once Caldas - Pasto","browser_uuid":"\/regarder-once-caldas-vs-pasto-20h00-streaming-direct","sport_name":"\u00b7 Liga Betplay Dimayor","sport_flag":"","date_time":"2025\/11\/08 \u00e0 08:18","live":[]},{"id":"690ec48c28e83","title":"Juventud - Progreso","browser_uuid":"\/regarder-juventud-vs-progreso-20h30-streaming-direct","sport_name":"\u00b7 Liga AUF Uruguaya","sport_flag":"","date_time":"2025\/11\/08 \u00e0 08:18","live":[]},{"id":"690ec48c28e84","title":"Montevideo City - Penarol","browser_uuid":"\/regarder-montevideo-city-vs-penarol-20h30-streaming-direct","sport_name":"\u00b7 Liga AUF Uruguaya","sport_flag":"","date_time":"2025\/11\/08 \u00e0 08:18","live":[]},{"id":"690ec48c28e85","title":"Defensor Sp. - Nacional","browser_uuid":"\/regarder-defensor-sp-vs-nacional-20h30-streaming-direct","sport_name":"\u00b7 Liga AUF Uruguaya","sport_flag":"","date_time":"2025\/11\/08 \u00e0 08:18","live":[]},{"id":"690ec48c28e86","title":"Boca Juniors - River Plate","browser_uuid":"\/regarder-boca-juniors-vs-river-plate-20h30-streaming-direct","sport_name":"\u00b7 Torneo LPF","sport_flag":"","date_time":"2025\/11\/08 \u00e0 08:18","live":[]},{"id":"690ec48c28e87","title":"Inter - Lazio","browser_uuid":"\/regarder-inter-vs-lazio-20h45-streaming-direct","sport_name":"\u00b7 Serie A","sport_flag":"","date_time":"2025\/11\/08 \u00e0 08:18","live":[]},{"id":"690ec48c28e88","title":"Lyon - PSG","browser_uuid":"\/regarder-lyon-vs-psg-20h45-streaming-direct","sport_name":"\u00b7 Ligue 1","sport_flag":"","date_time":"2025\/11\/08 \u00e0 08:18","live":[]},{"id":"690ec48c28e89","title":"Celta Vigo - Barcelone","browser_uuid":"\/regarder-celta-vigo-vs-barcelone-21h00-streaming-direct","sport_name":"\u00b7 Laliga","sport_flag":"","date_time":"2025\/11\/08 \u00e0 08:18","live":[]},{"id":"690ec48c28e8a","title":"Cadix CF - Valladolid","browser_uuid":"\/regarder-cadix-cf-vs-valladolid-21h00-streaming-direct","sport_name":"\u00b7 Laliga 2","sport_flag":"","date_time":"2025\/11\/08 \u00e0 08:18","live":[]},{"id":"690ec48c28e8b","title":"Alianza Atl. - Alianza Huanuco","browser_uuid":"\/regarder-alianza-atl-vs-alianza-huanuco-21h15-streaming-direct","sport_name":"\u00b7 Liga 1 Te Apuesto","sport_flag":"","date_time":"2025\/11\/08 \u00e0 08:18","live":[]},{"id":"690ec48c28e8c","title":"Benfica - Casa Pia","browser_uuid":"\/regarder-benfica-vs-casa-pia-21h30-streaming-direct","sport_name":"\u00b7 Liga Portugal","sport_flag":"","date_time":"2025\/11\/08 \u00e0 08:18","live":[]},{"id":"690ec48c28e8d","title":"Braga - Moreirense","browser_uuid":"\/regarder-braga-vs-moreirense-21h30-streaming-direct","sport_name":"\u00b7 Liga Portugal","sport_flag":"","date_time":"2025\/11\/08 \u00e0 08:18","live":[]},{"id":"690ec48c28e8e","title":"El Nacional - Emelec","browser_uuid":"\/regarder-el-nacional-vs-emelec-21h30-streaming-direct","sport_name":"\u00b7 Ecuador Ligapro","sport_flag":"","date_time":"2025\/11\/08 \u00e0 08:18","live":[]},{"id":"690ec48c28e8f","title":"U. De Chile - Limache","browser_uuid":"\/regarder-u-de-chile-vs-limache-21h30-streaming-direct","sport_name":"\u00b7 Campeonato Ita\u00fa Chile","sport_flag":"","date_time":"2025\/11\/08 \u00e0 08:18","live":[]},{"id":"690ec48c28e90","title":"Milwaukee Bucks - Houston Rockets","browser_uuid":"\/regarder-milwaukee-bucks-vs-houston-rockets-21h30-streaming-direct","sport_name":"\u00b7 NBA","sport_flag":"","date_time":"2025\/11\/08 \u00e0 08:18","live":[]},{"id":"690ec48c28e91","title":"Seattle Seahawks - Arizona Cardinals","browser_uuid":"\/regarder-seattle-seahawks-vs-arizona-cardinals-22h05-streaming-direct","sport_name":"\u00b7 NFL","sport_flag":"","date_time":"2025\/11\/08 \u00e0 08:18","live":[]},{"id":"690ec48c28e92","title":"Alianza - Chico","browser_uuid":"\/regarder-alianza-vs-chico-22h10-streaming-direct","sport_name":"\u00b7 Liga Betplay Dimayor","sport_flag":"","date_time":"2025\/11\/08 \u00e0 08:18","live":[]},{"id":"690ec48c28e93","title":"Washington Commanders - Detroit Lions","browser_uuid":"\/regarder-washington-commanders-vs-detroit-lions-22h25-streaming-direct","sport_name":"\u00b7 NFL","sport_flag":"","date_time":"2025\/11\/08 \u00e0 08:18","live":[]},{"id":"690ec48c28e94","title":"San Francisco 49ers - Los Angeles Rams","browser_uuid":"\/regarder-san-francisco-49ers-vs-los-angeles-rams-22h25-streaming-direct","sport_name":"\u00b7 NFL","sport_flag":"","date_time":"2025\/11\/08 \u00e0 08:18","live":[]},{"id":"690ec48c28e95","title":"Flamengo - Santos","browser_uuid":"\/regarder-flamengo-vs-santos-22h30-streaming-direct","sport_name":"\u00b7 Serie A Bresil","sport_flag":"","date_time":"2025\/11\/08 \u00e0 08:18","live":[]},{"id":"690ec48c28e96","title":"Banfield - Aldosivi","browser_uuid":"\/regarder-banfield-vs-aldosivi-23h20-streaming-direct","sport_name":"\u00b7 Torneo LPF","sport_flag":"","date_time":"2025\/11\/08 \u00e0 08:18","live":[]},{"id":"690ec48c28e97","title":"Sarmiento Junin - Instituto","browser_uuid":"\/regarder-sarmiento-junin-vs-instituto-23h20-streaming-direct","sport_name":"\u00b7 Torneo LPF","sport_flag":"","date_time":"2025\/11\/08 \u00e0 08:18","live":[]},{"id":"690ec48c28e98","title":"Orlando Magic - Boston Celtics","browser_uuid":"\/regarder-orlando-magic-vs-boston-celtics-00h00-streaming-direct","sport_name":"\u00b7 NBA","sport_flag":"","date_time":"2025\/11\/08 \u00e0 08:18","live":[]},{"id":"690ec48c28e99","title":"Santos Laguna - Pachuca","browser_uuid":"\/regarder-santos-laguna-vs-pachuca-00h00-streaming-direct","sport_name":"\u00b7 Liga Mx","sport_flag":"","date_time":"2025\/11\/08 \u00e0 08:18","live":[]},{"id":"690ec48c28e9a","title":"Tapatio - Dorados","browser_uuid":"\/regarder-tapatio-vs-dorados-00h00-streaming-direct","sport_name":"\u00b7 Liga De Expansion Mx","sport_flag":"","date_time":"2025\/11\/08 \u00e0 08:18","live":[]},{"id":"690ec48c28e9b","title":"Orense - Barcelone SC","browser_uuid":"\/regarder-orense-vs-barcelone-sc-00h00-streaming-direct","sport_name":"\u00b7 Ecuador Ligapro","sport_flag":"","date_time":"2025\/11\/08 \u00e0 08:18","live":[]},{"id":"690ec48c28e9c","title":"New York Knicks - Brooklyn Nets","browser_uuid":"\/regarder-new-york-knicks-vs-brooklyn-nets-00h00-streaming-direct","sport_name":"\u00b7 NBA","sport_flag":"","date_time":"2025\/11\/08 \u00e0 08:18","live":[]},{"id":"690ec48c28e9d","title":"Memphis Grizzlies - Oklahoma City Thunder","browser_uuid":"\/regarder-memphis-grizzlies-vs-oklahoma-city-thunder-00h00-streaming-direct","sport_name":"\u00b7 NBA","sport_flag":"","date_time":"2025\/11\/08 \u00e0 08:18","live":[]},{"id":"690ec48c28e9e","title":"Cobresal - Everton","browser_uuid":"\/regarder-cobresal-vs-everton-00h00-streaming-direct","sport_name":"\u00b7 Campeonato Ita\u00fa Chile","sport_flag":"","date_time":"2025\/11\/08 \u00e0 08:18","live":[]},{"id":"690ec48c28e9f","title":"Tigres F - Juarez F","browser_uuid":"\/regarder-tigres-f-vs-juarez-f-00h00-streaming-direct","sport_name":"\u00b7 Liga Mx Women","sport_flag":"","date_time":"2025\/11\/08 \u00e0 08:18","live":[]},{"id":"690ec48c28ea0","title":"America De Cali - U. Magdalena","browser_uuid":"\/regarder-america-de-cali-vs-u-magdalena-00h20-streaming-direct","sport_name":"\u00b7 Liga Betplay Dimayor","sport_flag":"","date_time":"2025\/11\/08 \u00e0 08:18","live":[]},{"id":"690ec48c28ea1","title":"Fortaleza - Gremio","browser_uuid":"\/regarder-fortaleza-vs-gremio-00h30-streaming-direct","sport_name":"\u00b7 Serie A Bresil","sport_flag":"","date_time":"2025\/11\/08 \u00e0 08:18","live":[]},{"id":"690ec48c28ea2","title":"Mirassol - Palmeiras","browser_uuid":"\/regarder-mirassol-vs-palmeiras-00h30-streaming-direct","sport_name":"\u00b7 Serie A Bresil","sport_flag":"","date_time":"2025\/11\/08 \u00e0 08:18","live":[]},{"id":"690ec48c28ea3","title":"Ottawa Senators - Utah Mammoth","browser_uuid":"\/regarder-ottawa-senators-vs-utah-mammoth-01h00-streaming-direct","sport_name":"\u00b7 NHL","sport_flag":"","date_time":"2025\/11\/08 \u00e0 08:18","live":[]},{"id":"690ec48c28ea4","title":"Dallas Stars - Seattle Kraken","browser_uuid":"\/regarder-dallas-stars-vs-seattle-kraken-01h00-streaming-direct","sport_name":"\u00b7 NHL","sport_flag":"","date_time":"2025\/11\/08 \u00e0 08:18","live":[]},{"id":"690ec48c28ea5","title":"Toronto Maple Leafs - Carolina Hurricanes","browser_uuid":"\/regarder-toronto-maple-leafs-vs-carolina-hurricanes-01h00-streaming-direct","sport_name":"\u00b7 NHL","sport_flag":"","date_time":"2025\/11\/08 \u00e0 08:18","live":[]},{"id":"690ec48c28ea6","title":"Tigre - Estudiantes","browser_uuid":"\/regarder-tigre-vs-estudiantes-01h30-streaming-direct","sport_name":"\u00b7 Torneo LPF","sport_flag":"","date_time":"2025\/11\/08 \u00e0 08:18","live":[]},{"id":"690ec48c28ea7","title":"Atl. Tucuman - Godoy Cruz","browser_uuid":"\/regarder-atl-tucuman-vs-godoy-cruz-01h30-streaming-direct","sport_name":"\u00b7 Torneo LPF","sport_flag":"","date_time":"2025\/11\/08 \u00e0 08:18","live":[]},{"id":"690ec48c28ea8","title":"Philadelphia 76ers - Detroit Pistons","browser_uuid":"\/regarder-philadelphia-76ers-vs-detroit-pistons-01h30-streaming-direct","sport_name":"\u00b7 NBA","sport_flag":"","date_time":"2025\/11\/08 \u00e0 08:18","live":[]},{"id":"690ec48c28ea9","title":"Minnesota Wild - Calgary Flames","browser_uuid":"\/regarder-minnesota-wild-vs-calgary-flames-02h00-streaming-direct","sport_name":"\u00b7 NHL","sport_flag":"","date_time":"2025\/11\/08 \u00e0 08:18","live":[]},{"id":"690ec48c28eaa","title":"Club America F - Monterrey F","browser_uuid":"\/regarder-club-america-f-vs-monterrey-f-02h15-streaming-direct","sport_name":"\u00b7 Liga Mx Women","sport_flag":"","date_time":"2025\/11\/08 \u00e0 08:18","live":[]},{"id":"690ec48c28eab","title":"Los Angeles Chargers - Pittsburgh Steelers","browser_uuid":"\/regarder-los-angeles-chargers-vs-pittsburgh-steelers-02h20-streaming-direct","sport_name":"\u00b7 NFL","sport_flag":"","date_time":"2025\/11\/08 \u00e0 08:18","live":[]},{"id":"690ec48c28eac","title":"Santa Fe - Dep. Cali","browser_uuid":"\/regarder-santa-fe-vs-dep-cali-02h30-streaming-direct","sport_name":"\u00b7 Liga Betplay Dimayor","sport_flag":"","date_time":"2025\/11\/08 \u00e0 08:18","live":[]},{"id":"690ec48c28ead","title":"Golden State Warriors - Indiana Pacers","browser_uuid":"\/regarder-golden-state-warriors-vs-indiana-pacers-02h30-streaming-direct","sport_name":"\u00b7 NBA","sport_flag":"","date_time":"2025\/11\/08 \u00e0 08:18","live":[]},{"id":"690ec48c28eae","title":"San Diego FC - Portland Timbers","browser_uuid":"\/regarder-san-diego-fc-vs-portland-timbers-03h00-streaming-direct","sport_name":"\u00b7 MLS","sport_flag":"","date_time":"2025\/11\/08 \u00e0 08:18","live":[]},{"id":"690ec48c28eaf","title":"Sacramento Kings - Minnesota Timberwolves","browser_uuid":"\/regarder-sacramento-kings-vs-minnesota-timberwolves-03h00-streaming-direct","sport_name":"\u00b7 NBA","sport_flag":"","date_time":"2025\/11\/08 \u00e0 08:18","live":[]},{"id":"690ec48c28eb0","title":"Vancouver Canucks - Colorado Avalanche","browser_uuid":"\/regarder-vancouver-canucks-vs-colorado-avalanche-04h00-streaming-direct","sport_name":"\u00b7 NHL","sport_flag":"","date_time":"2025\/11\/08 \u00e0 08:18","live":[]},{"id":"690ec48c28eb1","title":"Anaheim Ducks - Winnipeg Jets","browser_uuid":"\/regarder-anaheim-ducks-vs-winnipeg-jets-04h00-streaming-direct","sport_name":"\u00b7 NHL","sport_flag":"","date_time":"2025\/11\/08 \u00e0 08:18","live":[]},{"id":"690ec48c28eb2","title":"Toluca F - Guadalajara F","browser_uuid":"\/regarder-toluca-f-vs-guadalajara-f-04h15-streaming-direct","sport_name":"\u00b7 Liga Mx Women","sport_flag":"","date_time":"2025\/11\/08 \u00e0 08:18","live":[]},{"id":"690ec48c28eb3","title":"Burgos CF - Castellon","browser_uuid":"\/regarder-burgos-cf-vs-castellon-20h30-streaming-direct","sport_name":"\u00b7 Laliga 2","sport_flag":"","date_time":"2025\/11\/08 \u00e0 08:18","live":[]},{"id":"690ec48c28eb4","title":"Gimnasia L.P. - Velez Sarsfield","browser_uuid":"\/regarder-gimnasia-l-p-vs-velez-sarsfield-21h00-streaming-direct","sport_name":"\u00b7 Torneo LPF","sport_flag":"","date_time":"2025\/11\/08 \u00e0 08:18","live":[]},{"id":"690ec48c28eb5","title":"AD Tarma - Los Chankas","browser_uuid":"\/regarder-ad-tarma-vs-los-chankas-21h00-streaming-direct","sport_name":"\u00b7 Liga 1 Te Apuesto","sport_flag":"","date_time":"2025\/11\/08 \u00e0 08:18","live":[]},{"id":"690ec48c28eb6","title":"Dep. Riestra - Independiente","browser_uuid":"\/regarder-dep-riestra-vs-independiente-23h00-streaming-direct","sport_name":"\u00b7 Torneo LPF","sport_flag":"","date_time":"2025\/11\/08 \u00e0 08:18","live":[]},{"id":"690ec48c28eb7","title":"Orlando Magic - Portland Trail Blazers","browser_uuid":"\/regarder-orlando-magic-vs-portland-trail-blazers-01h00-streaming-direct","sport_name":"\u00b7 NBA","sport_flag":"","date_time":"2025\/11\/08 \u00e0 08:18","live":[]},{"id":"690ec48c28eb8","title":"Detroit Pistons - Washington Wizards","browser_uuid":"\/regarder-detroit-pistons-vs-washington-wizards-01h00-streaming-direct","sport_name":"\u00b7 NBA","sport_flag":"","date_time":"2025\/11\/08 \u00e0 08:18","live":[]},{"id":"690ec48c28eb9","title":"Aucas - Delfin","browser_uuid":"\/regarder-aucas-vs-delfin-01h00-streaming-direct","sport_name":"\u00b7 Ecuador Ligapro","sport_flag":"","date_time":"2025\/11\/08 \u00e0 08:18","live":[]},{"id":"690ec48c28eba","title":"New York Rangers - Nashville Predators","browser_uuid":"\/regarder-new-york-rangers-vs-nashville-predators-01h00-streaming-direct","sport_name":"\u00b7 NHL","sport_flag":"","date_time":"2025\/11\/08 \u00e0 08:18","live":[]},{"id":"690ec48c28ebb","title":"New Jersey Devils - New York Islanders","browser_uuid":"\/regarder-new-jersey-devils-vs-new-york-islanders-01h00-streaming-direct","sport_name":"\u00b7 NHL","sport_flag":"","date_time":"2025\/11\/08 \u00e0 08:18","live":[]},{"id":"690ec48c28ebc","title":"Charlotte Hornets - Los Angeles Lakers","browser_uuid":"\/regarder-charlotte-hornets-vs-los-angeles-lakers-01h00-streaming-direct","sport_name":"\u00b7 NBA","sport_flag":"","date_time":"2025\/11\/08 \u00e0 08:18","live":[]},{"id":"690ec48c28ebd","title":"Ind. Rivadavia - Central Cordoba","browser_uuid":"\/regarder-ind-rivadavia-vs-central-cordoba-01h15-streaming-direct","sport_name":"\u00b7 Torneo LPF","sport_flag":"","date_time":"2025\/11\/08 \u00e0 08:18","live":[]},{"id":"690ec48c28ebe","title":"Argentinos Jrs - Belgrano","browser_uuid":"\/regarder-argentinos-jrs-vs-belgrano-01h15-streaming-direct","sport_name":"\u00b7 Torneo LPF","sport_flag":"","date_time":"2025\/11\/08 \u00e0 08:18","live":[]},{"id":"690ec48c28ebf","title":"Ind. Medellin - Envigado","browser_uuid":"\/regarder-ind-medellin-vs-envigado-01h30-streaming-direct","sport_name":"\u00b7 Copa Colombia","sport_flag":"","date_time":"2025\/11\/08 \u00e0 08:18","live":[]},{"id":"690ec48c28ec0","title":"Miami Heat - Cleveland Cavaliers","browser_uuid":"\/regarder-miami-heat-vs-cleveland-cavaliers-01h30-streaming-direct","sport_name":"\u00b7 NBA","sport_flag":"","date_time":"2025\/11\/08 \u00e0 08:18","live":[]},{"id":"690ec48c28ec1","title":"Chicago Bulls - San Antonio Spurs","browser_uuid":"\/regarder-chicago-bulls-vs-san-antonio-spurs-02h00-streaming-direct","sport_name":"\u00b7 NBA","sport_flag":"","date_time":"2025\/11\/08 \u00e0 08:18","live":[]},{"id":"690ec48c28ec2","title":"Green Bay Packers - Philadelphia Eagles","browser_uuid":"\/regarder-green-bay-packers-vs-philadelphia-eagles-02h15-streaming-direct","sport_name":"\u00b7 NFL","sport_flag":"","date_time":"2025\/11\/08 \u00e0 08:18","live":[]},{"id":"690ec48c28ec3","title":"Dallas Mavericks - Milwaukee Bucks","browser_uuid":"\/regarder-dallas-mavericks-vs-milwaukee-bucks-02h30-streaming-direct","sport_name":"\u00b7 NBA","sport_flag":"","date_time":"2025\/11\/08 \u00e0 08:18","live":[]},{"id":"690ec48c28ec4","title":"Edmonton Oilers - Columbus Blue Jackets","browser_uuid":"\/regarder-edmonton-oilers-vs-columbus-blue-jackets-02h30-streaming-direct","sport_name":"\u00b7 NHL","sport_flag":"","date_time":"2025\/11\/08 \u00e0 08:18","live":[]},{"id":"690ec48c28ec5","title":"Phoenix Suns - New Orleans Pelicans","browser_uuid":"\/regarder-phoenix-suns-vs-new-orleans-pelicans-03h00-streaming-direct","sport_name":"\u00b7 NBA","sport_flag":"","date_time":"2025\/11\/08 \u00e0 08:18","live":[]},{"id":"690ec48c28ec6","title":"Utah Jazz - Minnesota Timberwolves","browser_uuid":"\/regarder-utah-jazz-vs-minnesota-timberwolves-03h00-streaming-direct","sport_name":"\u00b7 NBA","sport_flag":"","date_time":"2025\/11\/08 \u00e0 08:18","live":[]},{"id":"690ec48c28ec7","title":"Vegas Golden Knights - Florida Panthers","browser_uuid":"\/regarder-vegas-golden-knights-vs-florida-panthers-04h00-streaming-direct","sport_name":"\u00b7 NHL","sport_flag":"","date_time":"2025\/11\/08 \u00e0 08:18","live":[]},{"id":"690ec48c28ec8","title":"Los Angeles Clippers - Atlanta Hawks","browser_uuid":"\/regarder-los-angeles-clippers-vs-atlanta-hawks-04h30-streaming-direct","sport_name":"\u00b7 NBA","sport_flag":"","date_time":"2025\/11\/08 \u00e0 08:18","live":[]}]}