{"streams":[{"id":"671d689b65813","title":"formula 1 : Grand Prix du Mexique Essais libres 3\u00a019:30","browser_uuid":["\/live\/formula\/formula+1\/grand+prix+du+mexique+essais+libres+3\/6\/fr","\/live\/formula\/formula+1\/grand+prix+du+mexique+essais+libres+3\/89\/es"],"sport_name":"-","sport_flag":"https:\/\/img.icons8.com\/?size=48&id=iU4rpa9QGXp0&format=png","date_time":"0000\/00\/00 \u00e0 00:00","live":[{"stream_url":"https:\/\/footdirect.ru\/ply\/1\/6","flag":"https:\/\/www.shareicon.net\/data\/128x128\/2015\/08\/08\/82248_media_16x16.png","channel_name":"FR - Cartel"},{"stream_url":"https:\/\/footdirect.ru\/ply\/2\/6","flag":"https:\/\/www.shareicon.net\/data\/128x128\/2015\/08\/08\/82248_media_16x16.png","channel_name":"FR - Hoca"},{"stream_url":"https:\/\/footdirect.ru\/ply\/5\/6","flag":"https:\/\/www.shareicon.net\/data\/128x128\/2015\/08\/08\/82248_media_16x16.png","channel_name":"FR - CASTER"},{"stream_url":"https:\/\/footdirect.ru\/ply\/3\/6 ","flag":"https:\/\/www.shareicon.net\/data\/128x128\/2015\/08\/08\/82248_media_16x16.png","channel_name":"FR - eplayer"},{"stream_url":"https:\/\/footdirect.ru\/ply\/4\/6","flag":"https:\/\/www.shareicon.net\/data\/128x128\/2015\/08\/08\/82248_media_16x16.png","channel_name":"FR - wigi"},{"stream_url":"https:\/\/footdirect.ru\/ply\/1\/89","flag":"https:\/\/www.shareicon.net\/data\/128x128\/2015\/08\/08\/82248_media_16x16.png","channel_name":"ES - Cartel"},{"stream_url":"https:\/\/footdirect.ru\/ply\/2\/89","flag":"https:\/\/www.shareicon.net\/data\/128x128\/2015\/08\/08\/82248_media_16x16.png","channel_name":"ES - Hoca"},{"stream_url":"https:\/\/footdirect.ru\/ply\/5\/89","flag":"https:\/\/www.shareicon.net\/data\/128x128\/2015\/08\/08\/82248_media_16x16.png","channel_name":"ES - CASTER"},{"stream_url":"https:\/\/footdirect.ru\/ply\/3\/89 ","flag":"https:\/\/www.shareicon.net\/data\/128x128\/2015\/08\/08\/82248_media_16x16.png","channel_name":"ES - eplayer"},{"stream_url":"https:\/\/footdirect.ru\/ply\/4\/89","flag":"https:\/\/www.shareicon.net\/data\/128x128\/2015\/08\/08\/82248_media_16x16.png","channel_name":"ES - wigi"}]},{"id":"671d689b65815","title":"Ecuador Ligapro : U. Catolica vs Emelec\u00a020:00","browser_uuid":["\/live\/foot\/ecuador+ligapro\/u.+catolica+vs+emelec\/121\/es"],"sport_name":"-","sport_flag":"https:\/\/img.icons8.com\/?size=48&id=iU4rpa9QGXp0&format=png","date_time":"0000\/00\/00 \u00e0 00:00","live":[{"stream_url":"https:\/\/footdirect.ru\/ply\/1\/121","flag":"https:\/\/www.shareicon.net\/data\/128x128\/2015\/08\/08\/82248_media_16x16.png","channel_name":"ES - Cartel"},{"stream_url":"https:\/\/footdirect.ru\/ply\/2\/121","flag":"https:\/\/www.shareicon.net\/data\/128x128\/2015\/08\/08\/82248_media_16x16.png","channel_name":"ES - Hoca"},{"stream_url":"https:\/\/footdirect.ru\/ply\/5\/121","flag":"https:\/\/www.shareicon.net\/data\/128x128\/2015\/08\/08\/82248_media_16x16.png","channel_name":"ES - CASTER"},{"stream_url":"https:\/\/footdirect.ru\/ply\/3\/121 ","flag":"https:\/\/www.shareicon.net\/data\/128x128\/2015\/08\/08\/82248_media_16x16.png","channel_name":"ES - eplayer"},{"stream_url":"https:\/\/footdirect.ru\/ply\/4\/121","flag":"https:\/\/www.shareicon.net\/data\/128x128\/2015\/08\/08\/82248_media_16x16.png","channel_name":"ES - wigi"}]},{"id":"671d689b65816","title":"Ligue 2 : AC Ajaccio vs Bastia\u00a020:00","browser_uuid":["\/live\/foot\/ligue+2\/ac+ajaccio+vs+bastia\/2\/fr"],"sport_name":"-","sport_flag":"https:\/\/img.icons8.com\/?size=48&id=iU4rpa9QGXp0&format=png","date_time":"0000\/00\/00 \u00e0 00:00","live":[{"stream_url":"https:\/\/footdirect.ru\/ply\/1\/2","flag":"https:\/\/www.shareicon.net\/data\/128x128\/2015\/08\/08\/82248_media_16x16.png","channel_name":"FR - Cartel"},{"stream_url":"https:\/\/footdirect.ru\/ply\/2\/2","flag":"https:\/\/www.shareicon.net\/data\/128x128\/2015\/08\/08\/82248_media_16x16.png","channel_name":"FR - Hoca"},{"stream_url":"https:\/\/footdirect.ru\/ply\/5\/2","flag":"https:\/\/www.shareicon.net\/data\/128x128\/2015\/08\/08\/82248_media_16x16.png","channel_name":"FR - CASTER"},{"stream_url":"https:\/\/footdirect.ru\/ply\/3\/2 ","flag":"https:\/\/www.shareicon.net\/data\/128x128\/2015\/08\/08\/82248_media_16x16.png","channel_name":"FR - eplayer"},{"stream_url":"https:\/\/footdirect.ru\/ply\/4\/2","flag":"https:\/\/www.shareicon.net\/data\/128x128\/2015\/08\/08\/82248_media_16x16.png","channel_name":"FR - wigi"}]},{"id":"671d689b65817","title":"Saudi Pro League : Al-Hilal vs Al-Taawon\u00a020:00","browser_uuid":["\/live\/foot\/saudi+pro+league\/al-hilal+vs+al-taawon\/120\/es"],"sport_name":"-","sport_flag":"https:\/\/img.icons8.com\/?size=48&id=iU4rpa9QGXp0&format=png","date_time":"0000\/00\/00 \u00e0 00:00","live":[{"stream_url":"https:\/\/footdirect.ru\/ply\/1\/120","flag":"https:\/\/www.shareicon.net\/data\/128x128\/2015\/08\/08\/82248_media_16x16.png","channel_name":"ES - Cartel"},{"stream_url":"https:\/\/footdirect.ru\/ply\/2\/120","flag":"https:\/\/www.shareicon.net\/data\/128x128\/2015\/08\/08\/82248_media_16x16.png","channel_name":"ES - Hoca"},{"stream_url":"https:\/\/footdirect.ru\/ply\/5\/120","flag":"https:\/\/www.shareicon.net\/data\/128x128\/2015\/08\/08\/82248_media_16x16.png","channel_name":"ES - CASTER"},{"stream_url":"https:\/\/footdirect.ru\/ply\/3\/120 ","flag":"https:\/\/www.shareicon.net\/data\/128x128\/2015\/08\/08\/82248_media_16x16.png","channel_name":"ES - eplayer"},{"stream_url":"https:\/\/footdirect.ru\/ply\/4\/120","flag":"https:\/\/www.shareicon.net\/data\/128x128\/2015\/08\/08\/82248_media_16x16.png","channel_name":"ES - wigi"}]},{"id":"671d689b65818","title":"Eredivisie : Breda vs Waalwijk\u00a020:00","browser_uuid":["\/live\/foot\/eredivisie\/breda+vs+waalwijk\/77\/nl"],"sport_name":"-","sport_flag":"https:\/\/img.icons8.com\/?size=48&id=iU4rpa9QGXp0&format=png","date_time":"0000\/00\/00 \u00e0 00:00","live":[{"stream_url":"https:\/\/footdirect.ru\/ply\/1\/77","flag":"https:\/\/www.shareicon.net\/data\/128x128\/2015\/08\/08\/82248_media_16x16.png","channel_name":"NL - Cartel"},{"stream_url":"https:\/\/footdirect.ru\/ply\/2\/77","flag":"https:\/\/www.shareicon.net\/data\/128x128\/2015\/08\/08\/82248_media_16x16.png","channel_name":"NL - Hoca"},{"stream_url":"https:\/\/footdirect.ru\/ply\/5\/77","flag":"https:\/\/www.shareicon.net\/data\/128x128\/2015\/08\/08\/82248_media_16x16.png","channel_name":"NL - CASTER"},{"stream_url":"https:\/\/footdirect.ru\/ply\/3\/77 ","flag":"https:\/\/www.shareicon.net\/data\/128x128\/2015\/08\/08\/82248_media_16x16.png","channel_name":"NL - eplayer"},{"stream_url":"https:\/\/footdirect.ru\/ply\/4\/77","flag":"https:\/\/www.shareicon.net\/data\/128x128\/2015\/08\/08\/82248_media_16x16.png","channel_name":"NL - wigi"}]},{"id":"671d689b65819","title":"Super Liga : Vojvodina vs OFK Beograd\u00a020:00","browser_uuid":["\/live\/foot\/super+liga\/vojvodina+vs+ofk+beograd\/134\/rs"],"sport_name":"-","sport_flag":"https:\/\/img.icons8.com\/?size=48&id=iU4rpa9QGXp0&format=png","date_time":"0000\/00\/00 \u00e0 00:00","live":[{"stream_url":"https:\/\/footdirect.ru\/ply\/1\/134","flag":"https:\/\/www.shareicon.net\/data\/128x128\/2015\/08\/08\/82248_media_16x16.png","channel_name":"RS - Cartel"},{"stream_url":"https:\/\/footdirect.ru\/ply\/2\/134","flag":"https:\/\/www.shareicon.net\/data\/128x128\/2015\/08\/08\/82248_media_16x16.png","channel_name":"RS - Hoca"},{"stream_url":"https:\/\/footdirect.ru\/ply\/5\/134","flag":"https:\/\/www.shareicon.net\/data\/128x128\/2015\/08\/08\/82248_media_16x16.png","channel_name":"RS - CASTER"},{"stream_url":"https:\/\/footdirect.ru\/ply\/3\/134 ","flag":"https:\/\/www.shareicon.net\/data\/128x128\/2015\/08\/08\/82248_media_16x16.png","channel_name":"RS - eplayer"},{"stream_url":"https:\/\/footdirect.ru\/ply\/4\/134","flag":"https:\/\/www.shareicon.net\/data\/128x128\/2015\/08\/08\/82248_media_16x16.png","channel_name":"RS - wigi"}]},{"id":"671d689b6581a","title":"Ekstraklasa : Lech vs Radomiak Radom\u00a020:15","browser_uuid":["\/live\/foot\/ekstraklasa\/lech+vs+radomiak+radom\/130\/pl"],"sport_name":"-","sport_flag":"https:\/\/img.icons8.com\/?size=48&id=iU4rpa9QGXp0&format=png","date_time":"0000\/00\/00 \u00e0 00:00","live":[{"stream_url":"https:\/\/footdirect.ru\/ply\/1\/130","flag":"https:\/\/www.shareicon.net\/data\/128x128\/2015\/08\/08\/82248_media_16x16.png","channel_name":"PL - Cartel"},{"stream_url":"https:\/\/footdirect.ru\/ply\/2\/130","flag":"https:\/\/www.shareicon.net\/data\/128x128\/2015\/08\/08\/82248_media_16x16.png","channel_name":"PL - Hoca"},{"stream_url":"https:\/\/footdirect.ru\/ply\/5\/130","flag":"https:\/\/www.shareicon.net\/data\/128x128\/2015\/08\/08\/82248_media_16x16.png","channel_name":"PL - CASTER"},{"stream_url":"https:\/\/footdirect.ru\/ply\/3\/130 ","flag":"https:\/\/www.shareicon.net\/data\/128x128\/2015\/08\/08\/82248_media_16x16.png","channel_name":"PL - eplayer"},{"stream_url":"https:\/\/footdirect.ru\/ply\/4\/130","flag":"https:\/\/www.shareicon.net\/data\/128x128\/2015\/08\/08\/82248_media_16x16.png","channel_name":"PL - wigi"}]},{"id":"671d689b6581b","title":"Bundesliga 2 : D\u00fcsseldorf vs Kaiserslautern\u00a020:30","browser_uuid":["\/live\/foot\/bundesliga+2\/d\u00fcsseldorf+vs+kaiserslautern\/42\/de"],"sport_name":"-","sport_flag":"https:\/\/img.icons8.com\/?size=48&id=iU4rpa9QGXp0&format=png","date_time":"0000\/00\/00 \u00e0 00:00","live":[{"stream_url":"https:\/\/footdirect.ru\/ply\/1\/42","flag":"https:\/\/www.shareicon.net\/data\/128x128\/2015\/08\/08\/82248_media_16x16.png","channel_name":"DE - Cartel"},{"stream_url":"https:\/\/footdirect.ru\/ply\/2\/42","flag":"https:\/\/www.shareicon.net\/data\/128x128\/2015\/08\/08\/82248_media_16x16.png","channel_name":"DE - Hoca"},{"stream_url":"https:\/\/footdirect.ru\/ply\/5\/42","flag":"https:\/\/www.shareicon.net\/data\/128x128\/2015\/08\/08\/82248_media_16x16.png","channel_name":"DE - CASTER"},{"stream_url":"https:\/\/footdirect.ru\/ply\/3\/42 ","flag":"https:\/\/www.shareicon.net\/data\/128x128\/2015\/08\/08\/82248_media_16x16.png","channel_name":"DE - eplayer"},{"stream_url":"https:\/\/footdirect.ru\/ply\/4\/42","flag":"https:\/\/www.shareicon.net\/data\/128x128\/2015\/08\/08\/82248_media_16x16.png","channel_name":"DE - wigi"}]},{"id":"671d689b6581c","title":"Liga Endesa : Leyma Coruna vs Zaragoza\u00a020:45","browser_uuid":["\/live\/basket\/liga+endesa\/leyma+coruna+vs+zaragoza\/67\/es"],"sport_name":"-","sport_flag":"https:\/\/img.icons8.com\/?size=48&id=iU4rpa9QGXp0&format=png","date_time":"0000\/00\/00 \u00e0 00:00","live":[{"stream_url":"https:\/\/footdirect.ru\/ply\/1\/67","flag":"https:\/\/www.shareicon.net\/data\/128x128\/2015\/08\/08\/82248_media_16x16.png","channel_name":"ES - Cartel"},{"stream_url":"https:\/\/footdirect.ru\/ply\/2\/67","flag":"https:\/\/www.shareicon.net\/data\/128x128\/2015\/08\/08\/82248_media_16x16.png","channel_name":"ES - Hoca"},{"stream_url":"https:\/\/footdirect.ru\/ply\/5\/67","flag":"https:\/\/www.shareicon.net\/data\/128x128\/2015\/08\/08\/82248_media_16x16.png","channel_name":"ES - CASTER"},{"stream_url":"https:\/\/footdirect.ru\/ply\/3\/67 ","flag":"https:\/\/www.shareicon.net\/data\/128x128\/2015\/08\/08\/82248_media_16x16.png","channel_name":"ES - eplayer"},{"stream_url":"https:\/\/footdirect.ru\/ply\/4\/67","flag":"https:\/\/www.shareicon.net\/data\/128x128\/2015\/08\/08\/82248_media_16x16.png","channel_name":"ES - wigi"}]},{"id":"671d689b6581d","title":"Liga Endesa : MoraBanc Andorra vs Grenade\u00a020:45","browser_uuid":["\/live\/basket\/liga+endesa\/morabanc+andorra+vs+grenade\/69\/es"],"sport_name":"-","sport_flag":"https:\/\/img.icons8.com\/?size=48&id=iU4rpa9QGXp0&format=png","date_time":"0000\/00\/00 \u00e0 00:00","live":[{"stream_url":"https:\/\/footdirect.ru\/ply\/1\/69","flag":"https:\/\/www.shareicon.net\/data\/128x128\/2015\/08\/08\/82248_media_16x16.png","channel_name":"ES - Cartel"},{"stream_url":"https:\/\/footdirect.ru\/ply\/2\/69","flag":"https:\/\/www.shareicon.net\/data\/128x128\/2015\/08\/08\/82248_media_16x16.png","channel_name":"ES - Hoca"},{"stream_url":"https:\/\/footdirect.ru\/ply\/5\/69","flag":"https:\/\/www.shareicon.net\/data\/128x128\/2015\/08\/08\/82248_media_16x16.png","channel_name":"ES - CASTER"},{"stream_url":"https:\/\/footdirect.ru\/ply\/3\/69 ","flag":"https:\/\/www.shareicon.net\/data\/128x128\/2015\/08\/08\/82248_media_16x16.png","channel_name":"ES - eplayer"},{"stream_url":"https:\/\/footdirect.ru\/ply\/4\/69","flag":"https:\/\/www.shareicon.net\/data\/128x128\/2015\/08\/08\/82248_media_16x16.png","channel_name":"ES - wigi"}]},{"id":"671d689b6581e","title":"Pro League : Saint-Trond vs Westerlo\u00a020:45","browser_uuid":["\/live\/foot\/pro+league\/saint-trond+vs+westerlo\/58\/fr"],"sport_name":"-","sport_flag":"https:\/\/img.icons8.com\/?size=48&id=iU4rpa9QGXp0&format=png","date_time":"0000\/00\/00 \u00e0 00:00","live":[{"stream_url":"https:\/\/footdirect.ru\/ply\/1\/58","flag":"https:\/\/www.shareicon.net\/data\/128x128\/2015\/08\/08\/82248_media_16x16.png","channel_name":"FR - Cartel"},{"stream_url":"https:\/\/footdirect.ru\/ply\/2\/58","flag":"https:\/\/www.shareicon.net\/data\/128x128\/2015\/08\/08\/82248_media_16x16.png","channel_name":"FR - Hoca"},{"stream_url":"https:\/\/footdirect.ru\/ply\/5\/58","flag":"https:\/\/www.shareicon.net\/data\/128x128\/2015\/08\/08\/82248_media_16x16.png","channel_name":"FR - CASTER"},{"stream_url":"https:\/\/footdirect.ru\/ply\/3\/58 ","flag":"https:\/\/www.shareicon.net\/data\/128x128\/2015\/08\/08\/82248_media_16x16.png","channel_name":"FR - eplayer"},{"stream_url":"https:\/\/footdirect.ru\/ply\/4\/58","flag":"https:\/\/www.shareicon.net\/data\/128x128\/2015\/08\/08\/82248_media_16x16.png","channel_name":"FR - wigi"}]},{"id":"671d689b6581f","title":"Serie A : Atalanta vs Hellas V\u00e9rone\u00a020:45","browser_uuid":["\/live\/foot\/serie+a\/atalanta+vs+hellas+v\u00e9rone\/73\/it","\/live\/foot\/serie+a\/atalanta+vs+hellas+v\u00e9rone\/54\/de","\/live\/foot\/serie+a\/atalanta+vs+hellas+v\u00e9rone\/114\/es"],"sport_name":"-","sport_flag":"https:\/\/img.icons8.com\/?size=48&id=iU4rpa9QGXp0&format=png","date_time":"0000\/00\/00 \u00e0 00:00","live":[{"stream_url":"https:\/\/footdirect.ru\/ply\/1\/73","flag":"https:\/\/www.shareicon.net\/data\/128x128\/2015\/08\/08\/82248_media_16x16.png","channel_name":"IT - Cartel"},{"stream_url":"https:\/\/footdirect.ru\/ply\/2\/73","flag":"https:\/\/www.shareicon.net\/data\/128x128\/2015\/08\/08\/82248_media_16x16.png","channel_name":"IT - Hoca"},{"stream_url":"https:\/\/footdirect.ru\/ply\/5\/73","flag":"https:\/\/www.shareicon.net\/data\/128x128\/2015\/08\/08\/82248_media_16x16.png","channel_name":"IT - CASTER"},{"stream_url":"https:\/\/footdirect.ru\/ply\/3\/73 ","flag":"https:\/\/www.shareicon.net\/data\/128x128\/2015\/08\/08\/82248_media_16x16.png","channel_name":"IT - eplayer"},{"stream_url":"https:\/\/footdirect.ru\/ply\/4\/73","flag":"https:\/\/www.shareicon.net\/data\/128x128\/2015\/08\/08\/82248_media_16x16.png","channel_name":"IT - wigi"},{"stream_url":"https:\/\/footdirect.ru\/ply\/1\/54","flag":"https:\/\/www.shareicon.net\/data\/128x128\/2015\/08\/08\/82248_media_16x16.png","channel_name":"DE - Cartel"},{"stream_url":"https:\/\/footdirect.ru\/ply\/2\/54","flag":"https:\/\/www.shareicon.net\/data\/128x128\/2015\/08\/08\/82248_media_16x16.png","channel_name":"DE - Hoca"},{"stream_url":"https:\/\/footdirect.ru\/ply\/5\/54","flag":"https:\/\/www.shareicon.net\/data\/128x128\/2015\/08\/08\/82248_media_16x16.png","channel_name":"DE - CASTER"},{"stream_url":"https:\/\/footdirect.ru\/ply\/3\/54 ","flag":"https:\/\/www.shareicon.net\/data\/128x128\/2015\/08\/08\/82248_media_16x16.png","channel_name":"DE - eplayer"},{"stream_url":"https:\/\/footdirect.ru\/ply\/4\/54","flag":"https:\/\/www.shareicon.net\/data\/128x128\/2015\/08\/08\/82248_media_16x16.png","channel_name":"DE - wigi"},{"stream_url":"https:\/\/footdirect.ru\/ply\/1\/114","flag":"https:\/\/www.shareicon.net\/data\/128x128\/2015\/08\/08\/82248_media_16x16.png","channel_name":"ES - Cartel"},{"stream_url":"https:\/\/footdirect.ru\/ply\/2\/114","flag":"https:\/\/www.shareicon.net\/data\/128x128\/2015\/08\/08\/82248_media_16x16.png","channel_name":"ES - Hoca"},{"stream_url":"https:\/\/footdirect.ru\/ply\/5\/114","flag":"https:\/\/www.shareicon.net\/data\/128x128\/2015\/08\/08\/82248_media_16x16.png","channel_name":"ES - CASTER"},{"stream_url":"https:\/\/footdirect.ru\/ply\/3\/114 ","flag":"https:\/\/www.shareicon.net\/data\/128x128\/2015\/08\/08\/82248_media_16x16.png","channel_name":"ES - eplayer"},{"stream_url":"https:\/\/footdirect.ru\/ply\/4\/114","flag":"https:\/\/www.shareicon.net\/data\/128x128\/2015\/08\/08\/82248_media_16x16.png","channel_name":"ES - wigi"}]},{"id":"671d689b65820","title":"Laliga : Real Madrid vs Barcelone\u00a021:00","browser_uuid":["\/live\/foot\/laliga\/real+madrid+vs+barcelone\/1\/fr","\/live\/foot\/laliga\/real+madrid+vs+barcelone\/80\/es","\/live\/foot\/laliga\/real+madrid+vs+barcelone\/125\/es","\/live\/foot\/laliga\/real+madrid+vs+barcelone\/123\/es"],"sport_name":"-","sport_flag":"https:\/\/img.icons8.com\/?size=48&id=iU4rpa9QGXp0&format=png","date_time":"0000\/00\/00 \u00e0 00:00","live":[{"stream_url":"https:\/\/footdirect.ru\/ply\/1\/1","flag":"https:\/\/www.shareicon.net\/data\/128x128\/2015\/08\/08\/82248_media_16x16.png","channel_name":"FR - Cartel"},{"stream_url":"https:\/\/footdirect.ru\/ply\/2\/1","flag":"https:\/\/www.shareicon.net\/data\/128x128\/2015\/08\/08\/82248_media_16x16.png","channel_name":"FR - Hoca"},{"stream_url":"https:\/\/footdirect.ru\/ply\/5\/1","flag":"https:\/\/www.shareicon.net\/data\/128x128\/2015\/08\/08\/82248_media_16x16.png","channel_name":"FR - CASTER"},{"stream_url":"https:\/\/footdirect.ru\/ply\/3\/1 ","flag":"https:\/\/www.shareicon.net\/data\/128x128\/2015\/08\/08\/82248_media_16x16.png","channel_name":"FR - eplayer"},{"stream_url":"https:\/\/footdirect.ru\/ply\/4\/1","flag":"https:\/\/www.shareicon.net\/data\/128x128\/2015\/08\/08\/82248_media_16x16.png","channel_name":"FR - wigi"},{"stream_url":"https:\/\/footdirect.ru\/ply\/1\/80","flag":"https:\/\/www.shareicon.net\/data\/128x128\/2015\/08\/08\/82248_media_16x16.png","channel_name":"ES - Cartel"},{"stream_url":"https:\/\/footdirect.ru\/ply\/2\/80","flag":"https:\/\/www.shareicon.net\/data\/128x128\/2015\/08\/08\/82248_media_16x16.png","channel_name":"ES - Hoca"},{"stream_url":"https:\/\/footdirect.ru\/ply\/5\/80","flag":"https:\/\/www.shareicon.net\/data\/128x128\/2015\/08\/08\/82248_media_16x16.png","channel_name":"ES - CASTER"},{"stream_url":"https:\/\/footdirect.ru\/ply\/3\/80 ","flag":"https:\/\/www.shareicon.net\/data\/128x128\/2015\/08\/08\/82248_media_16x16.png","channel_name":"ES - eplayer"},{"stream_url":"https:\/\/footdirect.ru\/ply\/4\/80","flag":"https:\/\/www.shareicon.net\/data\/128x128\/2015\/08\/08\/82248_media_16x16.png","channel_name":"ES - wigi"},{"stream_url":"https:\/\/footdirect.ru\/ply\/1\/125","flag":"https:\/\/www.shareicon.net\/data\/128x128\/2015\/08\/08\/82248_media_16x16.png","channel_name":"ES - Cartel"},{"stream_url":"https:\/\/footdirect.ru\/ply\/2\/125","flag":"https:\/\/www.shareicon.net\/data\/128x128\/2015\/08\/08\/82248_media_16x16.png","channel_name":"ES - Hoca"},{"stream_url":"https:\/\/footdirect.ru\/ply\/5\/125","flag":"https:\/\/www.shareicon.net\/data\/128x128\/2015\/08\/08\/82248_media_16x16.png","channel_name":"ES - CASTER"},{"stream_url":"https:\/\/footdirect.ru\/ply\/3\/125 ","flag":"https:\/\/www.shareicon.net\/data\/128x128\/2015\/08\/08\/82248_media_16x16.png","channel_name":"ES - eplayer"},{"stream_url":"https:\/\/footdirect.ru\/ply\/4\/125","flag":"https:\/\/www.shareicon.net\/data\/128x128\/2015\/08\/08\/82248_media_16x16.png","channel_name":"ES - wigi"},{"stream_url":"https:\/\/footdirect.ru\/ply\/1\/123","flag":"https:\/\/www.shareicon.net\/data\/128x128\/2015\/08\/08\/82248_media_16x16.png","channel_name":"ES - Cartel"},{"stream_url":"https:\/\/footdirect.ru\/ply\/2\/123","flag":"https:\/\/www.shareicon.net\/data\/128x128\/2015\/08\/08\/82248_media_16x16.png","channel_name":"ES - Hoca"},{"stream_url":"https:\/\/footdirect.ru\/ply\/5\/123","flag":"https:\/\/www.shareicon.net\/data\/128x128\/2015\/08\/08\/82248_media_16x16.png","channel_name":"ES - CASTER"},{"stream_url":"https:\/\/footdirect.ru\/ply\/3\/123 ","flag":"https:\/\/www.shareicon.net\/data\/128x128\/2015\/08\/08\/82248_media_16x16.png","channel_name":"ES - eplayer"},{"stream_url":"https:\/\/footdirect.ru\/ply\/4\/123","flag":"https:\/\/www.shareicon.net\/data\/128x128\/2015\/08\/08\/82248_media_16x16.png","channel_name":"ES - wigi"}]},{"id":"671d689b65821","title":"Ligue 1 : Lens vs Lille\u00a021:00","browser_uuid":["\/live\/foot\/ligue+1\/lens+vs+lille\/20\/fr","\/live\/foot\/ligue+1\/lens+vs+lille\/101\/es"],"sport_name":"-","sport_flag":"https:\/\/img.icons8.com\/?size=48&id=iU4rpa9QGXp0&format=png","date_time":"0000\/00\/00 \u00e0 00:00","live":[{"stream_url":"https:\/\/footdirect.ru\/ply\/1\/20","flag":"https:\/\/www.shareicon.net\/data\/128x128\/2015\/08\/08\/82248_media_16x16.png","channel_name":"FR - Cartel"},{"stream_url":"https:\/\/footdirect.ru\/ply\/2\/20","flag":"https:\/\/www.shareicon.net\/data\/128x128\/2015\/08\/08\/82248_media_16x16.png","channel_name":"FR - Hoca"},{"stream_url":"https:\/\/footdirect.ru\/ply\/5\/20","flag":"https:\/\/www.shareicon.net\/data\/128x128\/2015\/08\/08\/82248_media_16x16.png","channel_name":"FR - CASTER"},{"stream_url":"https:\/\/footdirect.ru\/ply\/3\/20 ","flag":"https:\/\/www.shareicon.net\/data\/128x128\/2015\/08\/08\/82248_media_16x16.png","channel_name":"FR - eplayer"},{"stream_url":"https:\/\/footdirect.ru\/ply\/4\/20","flag":"https:\/\/www.shareicon.net\/data\/128x128\/2015\/08\/08\/82248_media_16x16.png","channel_name":"FR - wigi"},{"stream_url":"https:\/\/footdirect.ru\/ply\/1\/101","flag":"https:\/\/www.shareicon.net\/data\/128x128\/2015\/08\/08\/82248_media_16x16.png","channel_name":"ES - Cartel"},{"stream_url":"https:\/\/footdirect.ru\/ply\/2\/101","flag":"https:\/\/www.shareicon.net\/data\/128x128\/2015\/08\/08\/82248_media_16x16.png","channel_name":"ES - Hoca"},{"stream_url":"https:\/\/footdirect.ru\/ply\/5\/101","flag":"https:\/\/www.shareicon.net\/data\/128x128\/2015\/08\/08\/82248_media_16x16.png","channel_name":"ES - CASTER"},{"stream_url":"https:\/\/footdirect.ru\/ply\/3\/101 ","flag":"https:\/\/www.shareicon.net\/data\/128x128\/2015\/08\/08\/82248_media_16x16.png","channel_name":"ES - eplayer"},{"stream_url":"https:\/\/footdirect.ru\/ply\/4\/101","flag":"https:\/\/www.shareicon.net\/data\/128x128\/2015\/08\/08\/82248_media_16x16.png","channel_name":"ES - wigi"}]},{"id":"671d689b65822","title":"Eredivisie : Heerenveen vs Sparta Rotterdam\u00a021:00","browser_uuid":["\/live\/foot\/eredivisie\/heerenveen+vs+sparta+rotterdam\/76\/nl"],"sport_name":"-","sport_flag":"https:\/\/img.icons8.com\/?size=48&id=iU4rpa9QGXp0&format=png","date_time":"0000\/00\/00 \u00e0 00:00","live":[{"stream_url":"https:\/\/footdirect.ru\/ply\/1\/76","flag":"https:\/\/www.shareicon.net\/data\/128x128\/2015\/08\/08\/82248_media_16x16.png","channel_name":"NL - Cartel"},{"stream_url":"https:\/\/footdirect.ru\/ply\/2\/76","flag":"https:\/\/www.shareicon.net\/data\/128x128\/2015\/08\/08\/82248_media_16x16.png","channel_name":"NL - Hoca"},{"stream_url":"https:\/\/footdirect.ru\/ply\/5\/76","flag":"https:\/\/www.shareicon.net\/data\/128x128\/2015\/08\/08\/82248_media_16x16.png","channel_name":"NL - CASTER"},{"stream_url":"https:\/\/footdirect.ru\/ply\/3\/76 ","flag":"https:\/\/www.shareicon.net\/data\/128x128\/2015\/08\/08\/82248_media_16x16.png","channel_name":"NL - eplayer"},{"stream_url":"https:\/\/footdirect.ru\/ply\/4\/76","flag":"https:\/\/www.shareicon.net\/data\/128x128\/2015\/08\/08\/82248_media_16x16.png","channel_name":"NL - wigi"}]},{"id":"671d689b65823","title":"Top 14 : Stade Fran\u00e7ais vs ASM Clermont\u00a021:05","browser_uuid":["\/live\/rugby\/top+14\/stade+fran\u00e7ais+vs+asm+clermont\/5\/fr"],"sport_name":"-","sport_flag":"https:\/\/img.icons8.com\/?size=48&id=iU4rpa9QGXp0&format=png","date_time":"0000\/00\/00 \u00e0 00:00","live":[{"stream_url":"https:\/\/footdirect.ru\/ply\/1\/5","flag":"https:\/\/www.shareicon.net\/data\/128x128\/2015\/08\/08\/82248_media_16x16.png","channel_name":"FR - Cartel"},{"stream_url":"https:\/\/footdirect.ru\/ply\/2\/5","flag":"https:\/\/www.shareicon.net\/data\/128x128\/2015\/08\/08\/82248_media_16x16.png","channel_name":"FR - Hoca"},{"stream_url":"https:\/\/footdirect.ru\/ply\/5\/5","flag":"https:\/\/www.shareicon.net\/data\/128x128\/2015\/08\/08\/82248_media_16x16.png","channel_name":"FR - CASTER"},{"stream_url":"https:\/\/footdirect.ru\/ply\/3\/5 ","flag":"https:\/\/www.shareicon.net\/data\/128x128\/2015\/08\/08\/82248_media_16x16.png","channel_name":"FR - eplayer"},{"stream_url":"https:\/\/footdirect.ru\/ply\/4\/5","flag":"https:\/\/www.shareicon.net\/data\/128x128\/2015\/08\/08\/82248_media_16x16.png","channel_name":"FR - wigi"}]},{"id":"671d689b65824","title":"Serie A Bresil : Flamengo vs Juventude\u00a021:30","browser_uuid":["\/live\/foot\/serie+a+bresil\/flamengo+vs+juventude\/47\/pt"],"sport_name":"-","sport_flag":"https:\/\/img.icons8.com\/?size=48&id=iU4rpa9QGXp0&format=png","date_time":"0000\/00\/00 \u00e0 00:00","live":[{"stream_url":"https:\/\/footdirect.ru\/ply\/1\/47","flag":"https:\/\/www.shareicon.net\/data\/128x128\/2015\/08\/08\/82248_media_16x16.png","channel_name":"PT - Cartel"},{"stream_url":"https:\/\/footdirect.ru\/ply\/2\/47","flag":"https:\/\/www.shareicon.net\/data\/128x128\/2015\/08\/08\/82248_media_16x16.png","channel_name":"PT - Hoca"},{"stream_url":"https:\/\/footdirect.ru\/ply\/5\/47","flag":"https:\/\/www.shareicon.net\/data\/128x128\/2015\/08\/08\/82248_media_16x16.png","channel_name":"PT - CASTER"},{"stream_url":"https:\/\/footdirect.ru\/ply\/3\/47 ","flag":"https:\/\/www.shareicon.net\/data\/128x128\/2015\/08\/08\/82248_media_16x16.png","channel_name":"PT - eplayer"},{"stream_url":"https:\/\/footdirect.ru\/ply\/4\/47","flag":"https:\/\/www.shareicon.net\/data\/128x128\/2015\/08\/08\/82248_media_16x16.png","channel_name":"PT - wigi"}]},{"id":"671d689b65825","title":"Serie A Bresil : Gremio vs Atletico GO\u00a021:30","browser_uuid":["\/live\/foot\/serie+a+bresil\/gremio+vs+atletico+go\/48\/pt"],"sport_name":"-","sport_flag":"https:\/\/img.icons8.com\/?size=48&id=iU4rpa9QGXp0&format=png","date_time":"0000\/00\/00 \u00e0 00:00","live":[{"stream_url":"https:\/\/footdirect.ru\/ply\/1\/48","flag":"https:\/\/www.shareicon.net\/data\/128x128\/2015\/08\/08\/82248_media_16x16.png","channel_name":"PT - Cartel"},{"stream_url":"https:\/\/footdirect.ru\/ply\/2\/48","flag":"https:\/\/www.shareicon.net\/data\/128x128\/2015\/08\/08\/82248_media_16x16.png","channel_name":"PT - Hoca"},{"stream_url":"https:\/\/footdirect.ru\/ply\/5\/48","flag":"https:\/\/www.shareicon.net\/data\/128x128\/2015\/08\/08\/82248_media_16x16.png","channel_name":"PT - CASTER"},{"stream_url":"https:\/\/footdirect.ru\/ply\/3\/48 ","flag":"https:\/\/www.shareicon.net\/data\/128x128\/2015\/08\/08\/82248_media_16x16.png","channel_name":"PT - eplayer"},{"stream_url":"https:\/\/footdirect.ru\/ply\/4\/48","flag":"https:\/\/www.shareicon.net\/data\/128x128\/2015\/08\/08\/82248_media_16x16.png","channel_name":"PT - wigi"}]},{"id":"671d689b65826","title":"Serie A Bresil : Palmeiras vs Fortaleza\u00a021:30","browser_uuid":["\/live\/foot\/serie+a+bresil\/palmeiras+vs+fortaleza\/49\/pt"],"sport_name":"-","sport_flag":"https:\/\/img.icons8.com\/?size=48&id=iU4rpa9QGXp0&format=png","date_time":"0000\/00\/00 \u00e0 00:00","live":[{"stream_url":"https:\/\/footdirect.ru\/ply\/1\/49","flag":"https:\/\/www.shareicon.net\/data\/128x128\/2015\/08\/08\/82248_media_16x16.png","channel_name":"PT - Cartel"},{"stream_url":"https:\/\/footdirect.ru\/ply\/2\/49","flag":"https:\/\/www.shareicon.net\/data\/128x128\/2015\/08\/08\/82248_media_16x16.png","channel_name":"PT - Hoca"},{"stream_url":"https:\/\/footdirect.ru\/ply\/5\/49","flag":"https:\/\/www.shareicon.net\/data\/128x128\/2015\/08\/08\/82248_media_16x16.png","channel_name":"PT - CASTER"},{"stream_url":"https:\/\/footdirect.ru\/ply\/3\/49 ","flag":"https:\/\/www.shareicon.net\/data\/128x128\/2015\/08\/08\/82248_media_16x16.png","channel_name":"PT - eplayer"},{"stream_url":"https:\/\/footdirect.ru\/ply\/4\/49","flag":"https:\/\/www.shareicon.net\/data\/128x128\/2015\/08\/08\/82248_media_16x16.png","channel_name":"PT - wigi"}]},{"id":"671d689b65827","title":"Serie A Bresil : Vitoria vs Fluminense\u00a021:30","browser_uuid":["\/live\/foot\/serie+a+bresil\/vitoria+vs+fluminense\/50\/pt"],"sport_name":"-","sport_flag":"https:\/\/img.icons8.com\/?size=48&id=iU4rpa9QGXp0&format=png","date_time":"0000\/00\/00 \u00e0 00:00","live":[{"stream_url":"https:\/\/footdirect.ru\/ply\/1\/50","flag":"https:\/\/www.shareicon.net\/data\/128x128\/2015\/08\/08\/82248_media_16x16.png","channel_name":"PT - Cartel"},{"stream_url":"https:\/\/footdirect.ru\/ply\/2\/50","flag":"https:\/\/www.shareicon.net\/data\/128x128\/2015\/08\/08\/82248_media_16x16.png","channel_name":"PT - Hoca"},{"stream_url":"https:\/\/footdirect.ru\/ply\/5\/50","flag":"https:\/\/www.shareicon.net\/data\/128x128\/2015\/08\/08\/82248_media_16x16.png","channel_name":"PT - CASTER"},{"stream_url":"https:\/\/footdirect.ru\/ply\/3\/50 ","flag":"https:\/\/www.shareicon.net\/data\/128x128\/2015\/08\/08\/82248_media_16x16.png","channel_name":"PT - eplayer"},{"stream_url":"https:\/\/footdirect.ru\/ply\/4\/50","flag":"https:\/\/www.shareicon.net\/data\/128x128\/2015\/08\/08\/82248_media_16x16.png","channel_name":"PT - wigi"}]},{"id":"671d689b65828","title":"Liga Portugal : Famalicao vs Sporting\u00a021:30","browser_uuid":["\/live\/foot\/liga+portugal\/famalicao+vs+sporting\/10\/fr","\/live\/foot\/liga+portugal\/famalicao+vs+sporting\/91\/pt"],"sport_name":"-","sport_flag":"https:\/\/img.icons8.com\/?size=48&id=iU4rpa9QGXp0&format=png","date_time":"0000\/00\/00 \u00e0 00:00","live":[{"stream_url":"https:\/\/footdirect.ru\/ply\/1\/10","flag":"https:\/\/www.shareicon.net\/data\/128x128\/2015\/08\/08\/82248_media_16x16.png","channel_name":"FR - Cartel"},{"stream_url":"https:\/\/footdirect.ru\/ply\/2\/10","flag":"https:\/\/www.shareicon.net\/data\/128x128\/2015\/08\/08\/82248_media_16x16.png","channel_name":"FR - Hoca"},{"stream_url":"https:\/\/footdirect.ru\/ply\/5\/10","flag":"https:\/\/www.shareicon.net\/data\/128x128\/2015\/08\/08\/82248_media_16x16.png","channel_name":"FR - CASTER"},{"stream_url":"https:\/\/footdirect.ru\/ply\/3\/10 ","flag":"https:\/\/www.shareicon.net\/data\/128x128\/2015\/08\/08\/82248_media_16x16.png","channel_name":"FR - eplayer"},{"stream_url":"https:\/\/footdirect.ru\/ply\/4\/10","flag":"https:\/\/www.shareicon.net\/data\/128x128\/2015\/08\/08\/82248_media_16x16.png","channel_name":"FR - wigi"},{"stream_url":"https:\/\/footdirect.ru\/ply\/1\/91","flag":"https:\/\/www.shareicon.net\/data\/128x128\/2015\/08\/08\/82248_media_16x16.png","channel_name":"PT - Cartel"},{"stream_url":"https:\/\/footdirect.ru\/ply\/2\/91","flag":"https:\/\/www.shareicon.net\/data\/128x128\/2015\/08\/08\/82248_media_16x16.png","channel_name":"PT - Hoca"},{"stream_url":"https:\/\/footdirect.ru\/ply\/5\/91","flag":"https:\/\/www.shareicon.net\/data\/128x128\/2015\/08\/08\/82248_media_16x16.png","channel_name":"PT - CASTER"},{"stream_url":"https:\/\/footdirect.ru\/ply\/3\/91 ","flag":"https:\/\/www.shareicon.net\/data\/128x128\/2015\/08\/08\/82248_media_16x16.png","channel_name":"PT - eplayer"},{"stream_url":"https:\/\/footdirect.ru\/ply\/4\/91","flag":"https:\/\/www.shareicon.net\/data\/128x128\/2015\/08\/08\/82248_media_16x16.png","channel_name":"PT - wigi"}]},{"id":"671d689b65829","title":"NHL : Los Angeles Kings vs Utah\u00a022:00","browser_uuid":["\/live\/hockey\/nhl\/los+angeles+kings+vs+utah\/145\/en"],"sport_name":"-","sport_flag":"https:\/\/img.icons8.com\/?size=48&id=iU4rpa9QGXp0&format=png","date_time":"0000\/00\/00 \u00e0 00:00","live":[{"stream_url":"https:\/\/footdirect.ru\/ply\/1\/145","flag":"https:\/\/www.shareicon.net\/data\/128x128\/2015\/08\/08\/82248_media_16x16.png","channel_name":"EN - Cartel"},{"stream_url":"https:\/\/footdirect.ru\/ply\/2\/145","flag":"https:\/\/www.shareicon.net\/data\/128x128\/2015\/08\/08\/82248_media_16x16.png","channel_name":"EN - Hoca"},{"stream_url":"https:\/\/footdirect.ru\/ply\/5\/145","flag":"https:\/\/www.shareicon.net\/data\/128x128\/2015\/08\/08\/82248_media_16x16.png","channel_name":"EN - CASTER"},{"stream_url":"https:\/\/footdirect.ru\/ply\/3\/145 ","flag":"https:\/\/www.shareicon.net\/data\/128x128\/2015\/08\/08\/82248_media_16x16.png","channel_name":"EN - eplayer"},{"stream_url":"https:\/\/footdirect.ru\/ply\/4\/145","flag":"https:\/\/www.shareicon.net\/data\/128x128\/2015\/08\/08\/82248_media_16x16.png","channel_name":"EN - wigi"}]},{"id":"671d689b6582a","title":"Torneo LPF : Instituto vs Rosario\u00a022:15","browser_uuid":["\/live\/foot\/torneo+lpf\/instituto+vs+rosario\/104\/es"],"sport_name":"-","sport_flag":"https:\/\/img.icons8.com\/?size=48&id=iU4rpa9QGXp0&format=png","date_time":"0000\/00\/00 \u00e0 00:00","live":[{"stream_url":"https:\/\/footdirect.ru\/ply\/1\/104","flag":"https:\/\/www.shareicon.net\/data\/128x128\/2015\/08\/08\/82248_media_16x16.png","channel_name":"ES - Cartel"},{"stream_url":"https:\/\/footdirect.ru\/ply\/2\/104","flag":"https:\/\/www.shareicon.net\/data\/128x128\/2015\/08\/08\/82248_media_16x16.png","channel_name":"ES - Hoca"},{"stream_url":"https:\/\/footdirect.ru\/ply\/5\/104","flag":"https:\/\/www.shareicon.net\/data\/128x128\/2015\/08\/08\/82248_media_16x16.png","channel_name":"ES - CASTER"},{"stream_url":"https:\/\/footdirect.ru\/ply\/3\/104 ","flag":"https:\/\/www.shareicon.net\/data\/128x128\/2015\/08\/08\/82248_media_16x16.png","channel_name":"ES - eplayer"},{"stream_url":"https:\/\/footdirect.ru\/ply\/4\/104","flag":"https:\/\/www.shareicon.net\/data\/128x128\/2015\/08\/08\/82248_media_16x16.png","channel_name":"ES - wigi"}]},{"id":"671d689b6582b","title":"Torneo LPF : Newells Old Boys vs Sarmiento Junin\u00a022:15","browser_uuid":["\/live\/foot\/torneo+lpf\/newells+old+boys+vs+sarmiento+junin\/103\/es"],"sport_name":"-","sport_flag":"https:\/\/img.icons8.com\/?size=48&id=iU4rpa9QGXp0&format=png","date_time":"0000\/00\/00 \u00e0 00:00","live":[{"stream_url":"https:\/\/footdirect.ru\/ply\/1\/103","flag":"https:\/\/www.shareicon.net\/data\/128x128\/2015\/08\/08\/82248_media_16x16.png","channel_name":"ES - Cartel"},{"stream_url":"https:\/\/footdirect.ru\/ply\/2\/103","flag":"https:\/\/www.shareicon.net\/data\/128x128\/2015\/08\/08\/82248_media_16x16.png","channel_name":"ES - Hoca"},{"stream_url":"https:\/\/footdirect.ru\/ply\/5\/103","flag":"https:\/\/www.shareicon.net\/data\/128x128\/2015\/08\/08\/82248_media_16x16.png","channel_name":"ES - CASTER"},{"stream_url":"https:\/\/footdirect.ru\/ply\/3\/103 ","flag":"https:\/\/www.shareicon.net\/data\/128x128\/2015\/08\/08\/82248_media_16x16.png","channel_name":"ES - eplayer"},{"stream_url":"https:\/\/footdirect.ru\/ply\/4\/103","flag":"https:\/\/www.shareicon.net\/data\/128x128\/2015\/08\/08\/82248_media_16x16.png","channel_name":"ES - wigi"}]},{"id":"671d689b6582c","title":"Ecuador Ligapro : LDU Quito vs Mushuc Runa\u00a022:30","browser_uuid":["\/live\/foot\/ecuador+ligapro\/ldu+quito+vs+mushuc+runa\/121\/es"],"sport_name":"-","sport_flag":"https:\/\/img.icons8.com\/?size=48&id=iU4rpa9QGXp0&format=png","date_time":"0000\/00\/00 \u00e0 00:00","live":[{"stream_url":"https:\/\/footdirect.ru\/ply\/1\/121","flag":"https:\/\/www.shareicon.net\/data\/128x128\/2015\/08\/08\/82248_media_16x16.png","channel_name":"ES - Cartel"},{"stream_url":"https:\/\/footdirect.ru\/ply\/2\/121","flag":"https:\/\/www.shareicon.net\/data\/128x128\/2015\/08\/08\/82248_media_16x16.png","channel_name":"ES - Hoca"},{"stream_url":"https:\/\/footdirect.ru\/ply\/5\/121","flag":"https:\/\/www.shareicon.net\/data\/128x128\/2015\/08\/08\/82248_media_16x16.png","channel_name":"ES - CASTER"},{"stream_url":"https:\/\/footdirect.ru\/ply\/3\/121 ","flag":"https:\/\/www.shareicon.net\/data\/128x128\/2015\/08\/08\/82248_media_16x16.png","channel_name":"ES - eplayer"},{"stream_url":"https:\/\/footdirect.ru\/ply\/4\/121","flag":"https:\/\/www.shareicon.net\/data\/128x128\/2015\/08\/08\/82248_media_16x16.png","channel_name":"ES - wigi"}]},{"id":"671d689b6582d","title":"NBA : Denver Nuggets vs Los Angeles Clippers\u00a023:00","browser_uuid":["\/live\/basket\/nba\/denver+nuggets+vs+los+angeles+clippers\/146\/en"],"sport_name":"-","sport_flag":"https:\/\/img.icons8.com\/?size=48&id=iU4rpa9QGXp0&format=png","date_time":"0000\/00\/00 \u00e0 00:00","live":[{"stream_url":"https:\/\/footdirect.ru\/ply\/1\/146","flag":"https:\/\/www.shareicon.net\/data\/128x128\/2015\/08\/08\/82248_media_16x16.png","channel_name":"EN - Cartel"},{"stream_url":"https:\/\/footdirect.ru\/ply\/2\/146","flag":"https:\/\/www.shareicon.net\/data\/128x128\/2015\/08\/08\/82248_media_16x16.png","channel_name":"EN - Hoca"},{"stream_url":"https:\/\/footdirect.ru\/ply\/5\/146","flag":"https:\/\/www.shareicon.net\/data\/128x128\/2015\/08\/08\/82248_media_16x16.png","channel_name":"EN - CASTER"},{"stream_url":"https:\/\/footdirect.ru\/ply\/3\/146 ","flag":"https:\/\/www.shareicon.net\/data\/128x128\/2015\/08\/08\/82248_media_16x16.png","channel_name":"EN - eplayer"},{"stream_url":"https:\/\/footdirect.ru\/ply\/4\/146","flag":"https:\/\/www.shareicon.net\/data\/128x128\/2015\/08\/08\/82248_media_16x16.png","channel_name":"EN - wigi"}]},{"id":"671d689b6582e","title":"Serie A Bresil : Athletico-PR vs Cruzeiro\u00a023:30","browser_uuid":["\/live\/foot\/serie+a+bresil\/athletico-pr+vs+cruzeiro\/47\/pt"],"sport_name":"-","sport_flag":"https:\/\/img.icons8.com\/?size=48&id=iU4rpa9QGXp0&format=png","date_time":"0000\/00\/00 \u00e0 00:00","live":[{"stream_url":"https:\/\/footdirect.ru\/ply\/1\/47","flag":"https:\/\/www.shareicon.net\/data\/128x128\/2015\/08\/08\/82248_media_16x16.png","channel_name":"PT - Cartel"},{"stream_url":"https:\/\/footdirect.ru\/ply\/2\/47","flag":"https:\/\/www.shareicon.net\/data\/128x128\/2015\/08\/08\/82248_media_16x16.png","channel_name":"PT - Hoca"},{"stream_url":"https:\/\/footdirect.ru\/ply\/5\/47","flag":"https:\/\/www.shareicon.net\/data\/128x128\/2015\/08\/08\/82248_media_16x16.png","channel_name":"PT - CASTER"},{"stream_url":"https:\/\/footdirect.ru\/ply\/3\/47 ","flag":"https:\/\/www.shareicon.net\/data\/128x128\/2015\/08\/08\/82248_media_16x16.png","channel_name":"PT - eplayer"},{"stream_url":"https:\/\/footdirect.ru\/ply\/4\/47","flag":"https:\/\/www.shareicon.net\/data\/128x128\/2015\/08\/08\/82248_media_16x16.png","channel_name":"PT - wigi"}]},{"id":"671d689b6582f","title":"Serie A Bresil : Atletico-MG vs Internacional\u00a000:00","browser_uuid":["\/live\/foot\/serie+a+bresil\/atletico-mg+vs+internacional\/48\/pt"],"sport_name":"-","sport_flag":"https:\/\/img.icons8.com\/?size=48&id=iU4rpa9QGXp0&format=png","date_time":"0000\/00\/00 \u00e0 00:00","live":[{"stream_url":"https:\/\/footdirect.ru\/ply\/1\/48","flag":"https:\/\/www.shareicon.net\/data\/128x128\/2015\/08\/08\/82248_media_16x16.png","channel_name":"PT - Cartel"},{"stream_url":"https:\/\/footdirect.ru\/ply\/2\/48","flag":"https:\/\/www.shareicon.net\/data\/128x128\/2015\/08\/08\/82248_media_16x16.png","channel_name":"PT - Hoca"},{"stream_url":"https:\/\/footdirect.ru\/ply\/5\/48","flag":"https:\/\/www.shareicon.net\/data\/128x128\/2015\/08\/08\/82248_media_16x16.png","channel_name":"PT - CASTER"},{"stream_url":"https:\/\/footdirect.ru\/ply\/3\/48 ","flag":"https:\/\/www.shareicon.net\/data\/128x128\/2015\/08\/08\/82248_media_16x16.png","channel_name":"PT - eplayer"},{"stream_url":"https:\/\/footdirect.ru\/ply\/4\/48","flag":"https:\/\/www.shareicon.net\/data\/128x128\/2015\/08\/08\/82248_media_16x16.png","channel_name":"PT - wigi"}]},{"id":"671d689b65830","title":"Serie A Bresil : Bragantino vs Botafogo RJ\u00a000:00","browser_uuid":["\/live\/foot\/serie+a+bresil\/bragantino+vs+botafogo+rj\/49\/pt"],"sport_name":"-","sport_flag":"https:\/\/img.icons8.com\/?size=48&id=iU4rpa9QGXp0&format=png","date_time":"0000\/00\/00 \u00e0 00:00","live":[{"stream_url":"https:\/\/footdirect.ru\/ply\/1\/49","flag":"https:\/\/www.shareicon.net\/data\/128x128\/2015\/08\/08\/82248_media_16x16.png","channel_name":"PT - Cartel"},{"stream_url":"https:\/\/footdirect.ru\/ply\/2\/49","flag":"https:\/\/www.shareicon.net\/data\/128x128\/2015\/08\/08\/82248_media_16x16.png","channel_name":"PT - Hoca"},{"stream_url":"https:\/\/footdirect.ru\/ply\/5\/49","flag":"https:\/\/www.shareicon.net\/data\/128x128\/2015\/08\/08\/82248_media_16x16.png","channel_name":"PT - CASTER"},{"stream_url":"https:\/\/footdirect.ru\/ply\/3\/49 ","flag":"https:\/\/www.shareicon.net\/data\/128x128\/2015\/08\/08\/82248_media_16x16.png","channel_name":"PT - eplayer"},{"stream_url":"https:\/\/footdirect.ru\/ply\/4\/49","flag":"https:\/\/www.shareicon.net\/data\/128x128\/2015\/08\/08\/82248_media_16x16.png","channel_name":"PT - wigi"}]},{"id":"671d689b65831","title":"Colombia Liga Betplay Dimayor : Alianza vs Patriotas\u00a000:15","browser_uuid":["\/live\/foot\/colombia+liga+betplay+dimayor\/alianza+vs+patriotas\/120\/es"],"sport_name":"-","sport_flag":"https:\/\/img.icons8.com\/?size=48&id=iU4rpa9QGXp0&format=png","date_time":"0000\/00\/00 \u00e0 00:00","live":[{"stream_url":"https:\/\/footdirect.ru\/ply\/1\/120","flag":"https:\/\/www.shareicon.net\/data\/128x128\/2015\/08\/08\/82248_media_16x16.png","channel_name":"ES - Cartel"},{"stream_url":"https:\/\/footdirect.ru\/ply\/2\/120","flag":"https:\/\/www.shareicon.net\/data\/128x128\/2015\/08\/08\/82248_media_16x16.png","channel_name":"ES - Hoca"},{"stream_url":"https:\/\/footdirect.ru\/ply\/5\/120","flag":"https:\/\/www.shareicon.net\/data\/128x128\/2015\/08\/08\/82248_media_16x16.png","channel_name":"ES - CASTER"},{"stream_url":"https:\/\/footdirect.ru\/ply\/3\/120 ","flag":"https:\/\/www.shareicon.net\/data\/128x128\/2015\/08\/08\/82248_media_16x16.png","channel_name":"ES - eplayer"},{"stream_url":"https:\/\/footdirect.ru\/ply\/4\/120","flag":"https:\/\/www.shareicon.net\/data\/128x128\/2015\/08\/08\/82248_media_16x16.png","channel_name":"ES - wigi"}]},{"id":"671d689b65832","title":"Torneo LPF : Independiente vs Godoy Cruz\u00a000:30","browser_uuid":["\/live\/foot\/torneo+lpf\/independiente+vs+godoy+cruz\/104\/es"],"sport_name":"-","sport_flag":"https:\/\/img.icons8.com\/?size=48&id=iU4rpa9QGXp0&format=png","date_time":"0000\/00\/00 \u00e0 00:00","live":[{"stream_url":"https:\/\/footdirect.ru\/ply\/1\/104","flag":"https:\/\/www.shareicon.net\/data\/128x128\/2015\/08\/08\/82248_media_16x16.png","channel_name":"ES - Cartel"},{"stream_url":"https:\/\/footdirect.ru\/ply\/2\/104","flag":"https:\/\/www.shareicon.net\/data\/128x128\/2015\/08\/08\/82248_media_16x16.png","channel_name":"ES - Hoca"},{"stream_url":"https:\/\/footdirect.ru\/ply\/5\/104","flag":"https:\/\/www.shareicon.net\/data\/128x128\/2015\/08\/08\/82248_media_16x16.png","channel_name":"ES - CASTER"},{"stream_url":"https:\/\/footdirect.ru\/ply\/3\/104 ","flag":"https:\/\/www.shareicon.net\/data\/128x128\/2015\/08\/08\/82248_media_16x16.png","channel_name":"ES - eplayer"},{"stream_url":"https:\/\/footdirect.ru\/ply\/4\/104","flag":"https:\/\/www.shareicon.net\/data\/128x128\/2015\/08\/08\/82248_media_16x16.png","channel_name":"ES - wigi"}]},{"id":"671d689b65833","title":"Liga Mx : Leon vs Queretaro\u00a001:00","browser_uuid":["\/live\/foot\/liga+mx\/leon+vs+queretaro\/100\/es","\/live\/foot\/liga+mx\/leon+vs+queretaro\/112\/es"],"sport_name":"-","sport_flag":"https:\/\/img.icons8.com\/?size=48&id=iU4rpa9QGXp0&format=png","date_time":"0000\/00\/00 \u00e0 00:00","live":[{"stream_url":"https:\/\/footdirect.ru\/ply\/1\/100","flag":"https:\/\/www.shareicon.net\/data\/128x128\/2015\/08\/08\/82248_media_16x16.png","channel_name":"ES - Cartel"},{"stream_url":"https:\/\/footdirect.ru\/ply\/2\/100","flag":"https:\/\/www.shareicon.net\/data\/128x128\/2015\/08\/08\/82248_media_16x16.png","channel_name":"ES - Hoca"},{"stream_url":"https:\/\/footdirect.ru\/ply\/5\/100","flag":"https:\/\/www.shareicon.net\/data\/128x128\/2015\/08\/08\/82248_media_16x16.png","channel_name":"ES - CASTER"},{"stream_url":"https:\/\/footdirect.ru\/ply\/3\/100 ","flag":"https:\/\/www.shareicon.net\/data\/128x128\/2015\/08\/08\/82248_media_16x16.png","channel_name":"ES - eplayer"},{"stream_url":"https:\/\/footdirect.ru\/ply\/4\/100","flag":"https:\/\/www.shareicon.net\/data\/128x128\/2015\/08\/08\/82248_media_16x16.png","channel_name":"ES - wigi"},{"stream_url":"https:\/\/footdirect.ru\/ply\/1\/112","flag":"https:\/\/www.shareicon.net\/data\/128x128\/2015\/08\/08\/82248_media_16x16.png","channel_name":"ES - Cartel"},{"stream_url":"https:\/\/footdirect.ru\/ply\/2\/112","flag":"https:\/\/www.shareicon.net\/data\/128x128\/2015\/08\/08\/82248_media_16x16.png","channel_name":"ES - Hoca"},{"stream_url":"https:\/\/footdirect.ru\/ply\/5\/112","flag":"https:\/\/www.shareicon.net\/data\/128x128\/2015\/08\/08\/82248_media_16x16.png","channel_name":"ES - CASTER"},{"stream_url":"https:\/\/footdirect.ru\/ply\/3\/112 ","flag":"https:\/\/www.shareicon.net\/data\/128x128\/2015\/08\/08\/82248_media_16x16.png","channel_name":"ES - eplayer"},{"stream_url":"https:\/\/footdirect.ru\/ply\/4\/112","flag":"https:\/\/www.shareicon.net\/data\/128x128\/2015\/08\/08\/82248_media_16x16.png","channel_name":"ES - wigi"}]},{"id":"671d689b65834","title":"NBA : Charlotte Hornets vs Miami Heat\u00a001:00","browser_uuid":["\/live\/basket\/nba\/charlotte+hornets+vs+miami+heat\/147\/en"],"sport_name":"-","sport_flag":"https:\/\/img.icons8.com\/?size=48&id=iU4rpa9QGXp0&format=png","date_time":"0000\/00\/00 \u00e0 00:00","live":[{"stream_url":"https:\/\/footdirect.ru\/ply\/1\/147","flag":"https:\/\/www.shareicon.net\/data\/128x128\/2015\/08\/08\/82248_media_16x16.png","channel_name":"EN - Cartel"},{"stream_url":"https:\/\/footdirect.ru\/ply\/2\/147","flag":"https:\/\/www.shareicon.net\/data\/128x128\/2015\/08\/08\/82248_media_16x16.png","channel_name":"EN - Hoca"},{"stream_url":"https:\/\/footdirect.ru\/ply\/5\/147","flag":"https:\/\/www.shareicon.net\/data\/128x128\/2015\/08\/08\/82248_media_16x16.png","channel_name":"EN - CASTER"},{"stream_url":"https:\/\/footdirect.ru\/ply\/3\/147 ","flag":"https:\/\/www.shareicon.net\/data\/128x128\/2015\/08\/08\/82248_media_16x16.png","channel_name":"EN - eplayer"},{"stream_url":"https:\/\/footdirect.ru\/ply\/4\/147","flag":"https:\/\/www.shareicon.net\/data\/128x128\/2015\/08\/08\/82248_media_16x16.png","channel_name":"EN - wigi"}]},{"id":"671d689b65835","title":"NBA : Detroit Pistons vs Boston Celtics\u00a001:00","browser_uuid":["\/live\/basket\/nba\/detroit+pistons+vs+boston+celtics\/148\/en"],"sport_name":"-","sport_flag":"https:\/\/img.icons8.com\/?size=48&id=iU4rpa9QGXp0&format=png","date_time":"0000\/00\/00 \u00e0 00:00","live":[{"stream_url":"https:\/\/footdirect.ru\/ply\/1\/148","flag":"https:\/\/www.shareicon.net\/data\/128x128\/2015\/08\/08\/82248_media_16x16.png","channel_name":"EN - Cartel"},{"stream_url":"https:\/\/footdirect.ru\/ply\/2\/148","flag":"https:\/\/www.shareicon.net\/data\/128x128\/2015\/08\/08\/82248_media_16x16.png","channel_name":"EN - Hoca"},{"stream_url":"https:\/\/footdirect.ru\/ply\/5\/148","flag":"https:\/\/www.shareicon.net\/data\/128x128\/2015\/08\/08\/82248_media_16x16.png","channel_name":"EN - CASTER"},{"stream_url":"https:\/\/footdirect.ru\/ply\/3\/148 ","flag":"https:\/\/www.shareicon.net\/data\/128x128\/2015\/08\/08\/82248_media_16x16.png","channel_name":"EN - eplayer"},{"stream_url":"https:\/\/footdirect.ru\/ply\/4\/148","flag":"https:\/\/www.shareicon.net\/data\/128x128\/2015\/08\/08\/82248_media_16x16.png","channel_name":"EN - wigi"}]},{"id":"671d689b65836","title":"NBA : Washington Wizards vs Cleveland Cavaliers\u00a001:00","browser_uuid":["\/live\/basket\/nba\/washington+wizards+vs+cleveland+cavaliers\/149\/en"],"sport_name":"-","sport_flag":"https:\/\/img.icons8.com\/?size=48&id=iU4rpa9QGXp0&format=png","date_time":"0000\/00\/00 \u00e0 00:00","live":[{"stream_url":"https:\/\/footdirect.ru\/ply\/1\/149","flag":"https:\/\/www.shareicon.net\/data\/128x128\/2015\/08\/08\/82248_media_16x16.png","channel_name":"EN - Cartel"},{"stream_url":"https:\/\/footdirect.ru\/ply\/2\/149","flag":"https:\/\/www.shareicon.net\/data\/128x128\/2015\/08\/08\/82248_media_16x16.png","channel_name":"EN - Hoca"},{"stream_url":"https:\/\/footdirect.ru\/ply\/5\/149","flag":"https:\/\/www.shareicon.net\/data\/128x128\/2015\/08\/08\/82248_media_16x16.png","channel_name":"EN - CASTER"},{"stream_url":"https:\/\/footdirect.ru\/ply\/3\/149 ","flag":"https:\/\/www.shareicon.net\/data\/128x128\/2015\/08\/08\/82248_media_16x16.png","channel_name":"EN - eplayer"},{"stream_url":"https:\/\/footdirect.ru\/ply\/4\/149","flag":"https:\/\/www.shareicon.net\/data\/128x128\/2015\/08\/08\/82248_media_16x16.png","channel_name":"EN - wigi"}]},{"id":"671d689b65837","title":"NHL : Boston Bruins vs Toronto Maple Leafs\u00a001:00","browser_uuid":["\/live\/hockey\/nhl\/boston+bruins+vs+toronto+maple+leafs\/150\/en"],"sport_name":"-","sport_flag":"https:\/\/img.icons8.com\/?size=48&id=iU4rpa9QGXp0&format=png","date_time":"0000\/00\/00 \u00e0 00:00","live":[{"stream_url":"https:\/\/footdirect.ru\/ply\/1\/150","flag":"https:\/\/www.shareicon.net\/data\/128x128\/2015\/08\/08\/82248_media_16x16.png","channel_name":"EN - Cartel"},{"stream_url":"https:\/\/footdirect.ru\/ply\/2\/150","flag":"https:\/\/www.shareicon.net\/data\/128x128\/2015\/08\/08\/82248_media_16x16.png","channel_name":"EN - Hoca"},{"stream_url":"https:\/\/footdirect.ru\/ply\/5\/150","flag":"https:\/\/www.shareicon.net\/data\/128x128\/2015\/08\/08\/82248_media_16x16.png","channel_name":"EN - CASTER"},{"stream_url":"https:\/\/footdirect.ru\/ply\/3\/150 ","flag":"https:\/\/www.shareicon.net\/data\/128x128\/2015\/08\/08\/82248_media_16x16.png","channel_name":"EN - eplayer"},{"stream_url":"https:\/\/footdirect.ru\/ply\/4\/150","flag":"https:\/\/www.shareicon.net\/data\/128x128\/2015\/08\/08\/82248_media_16x16.png","channel_name":"EN - wigi"}]},{"id":"671d689b65838","title":"NHL : Calgary Flames vs Winnipeg Jets\u00a001:00","browser_uuid":["\/live\/hockey\/nhl\/calgary+flames+vs+winnipeg+jets\/151\/en"],"sport_name":"-","sport_flag":"https:\/\/img.icons8.com\/?size=48&id=iU4rpa9QGXp0&format=png","date_time":"0000\/00\/00 \u00e0 00:00","live":[{"stream_url":"https:\/\/footdirect.ru\/ply\/1\/151","flag":"https:\/\/www.shareicon.net\/data\/128x128\/2015\/08\/08\/82248_media_16x16.png","channel_name":"EN - Cartel"},{"stream_url":"https:\/\/footdirect.ru\/ply\/2\/151","flag":"https:\/\/www.shareicon.net\/data\/128x128\/2015\/08\/08\/82248_media_16x16.png","channel_name":"EN - Hoca"},{"stream_url":"https:\/\/footdirect.ru\/ply\/5\/151","flag":"https:\/\/www.shareicon.net\/data\/128x128\/2015\/08\/08\/82248_media_16x16.png","channel_name":"EN - CASTER"},{"stream_url":"https:\/\/footdirect.ru\/ply\/3\/151 ","flag":"https:\/\/www.shareicon.net\/data\/128x128\/2015\/08\/08\/82248_media_16x16.png","channel_name":"EN - eplayer"},{"stream_url":"https:\/\/footdirect.ru\/ply\/4\/151","flag":"https:\/\/www.shareicon.net\/data\/128x128\/2015\/08\/08\/82248_media_16x16.png","channel_name":"EN - wigi"}]},{"id":"671d689b65839","title":"NHL : Montreal Canadiens vs St. Louis Blues\u00a001:00","browser_uuid":["\/live\/hockey\/nhl\/montreal+canadiens+vs+st.+louis+blues\/152\/en"],"sport_name":"-","sport_flag":"https:\/\/img.icons8.com\/?size=48&id=iU4rpa9QGXp0&format=png","date_time":"0000\/00\/00 \u00e0 00:00","live":[{"stream_url":"https:\/\/footdirect.ru\/ply\/1\/152","flag":"https:\/\/www.shareicon.net\/data\/128x128\/2015\/08\/08\/82248_media_16x16.png","channel_name":"EN - Cartel"},{"stream_url":"https:\/\/footdirect.ru\/ply\/2\/152","flag":"https:\/\/www.shareicon.net\/data\/128x128\/2015\/08\/08\/82248_media_16x16.png","channel_name":"EN - Hoca"},{"stream_url":"https:\/\/footdirect.ru\/ply\/5\/152","flag":"https:\/\/www.shareicon.net\/data\/128x128\/2015\/08\/08\/82248_media_16x16.png","channel_name":"EN - CASTER"},{"stream_url":"https:\/\/footdirect.ru\/ply\/3\/152 ","flag":"https:\/\/www.shareicon.net\/data\/128x128\/2015\/08\/08\/82248_media_16x16.png","channel_name":"EN - eplayer"},{"stream_url":"https:\/\/footdirect.ru\/ply\/4\/152","flag":"https:\/\/www.shareicon.net\/data\/128x128\/2015\/08\/08\/82248_media_16x16.png","channel_name":"EN - wigi"}]},{"id":"671d689b6583a","title":"NHL : New York Rangers vs Anaheim Ducks\u00a001:00","browser_uuid":["\/live\/hockey\/nhl\/new+york+rangers+vs+anaheim+ducks\/153\/en"],"sport_name":"-","sport_flag":"https:\/\/img.icons8.com\/?size=48&id=iU4rpa9QGXp0&format=png","date_time":"0000\/00\/00 \u00e0 00:00","live":[{"stream_url":"https:\/\/footdirect.ru\/ply\/1\/153","flag":"https:\/\/www.shareicon.net\/data\/128x128\/2015\/08\/08\/82248_media_16x16.png","channel_name":"EN - Cartel"},{"stream_url":"https:\/\/footdirect.ru\/ply\/2\/153","flag":"https:\/\/www.shareicon.net\/data\/128x128\/2015\/08\/08\/82248_media_16x16.png","channel_name":"EN - Hoca"},{"stream_url":"https:\/\/footdirect.ru\/ply\/5\/153","flag":"https:\/\/www.shareicon.net\/data\/128x128\/2015\/08\/08\/82248_media_16x16.png","channel_name":"EN - CASTER"},{"stream_url":"https:\/\/footdirect.ru\/ply\/3\/153 ","flag":"https:\/\/www.shareicon.net\/data\/128x128\/2015\/08\/08\/82248_media_16x16.png","channel_name":"EN - eplayer"},{"stream_url":"https:\/\/footdirect.ru\/ply\/4\/153","flag":"https:\/\/www.shareicon.net\/data\/128x128\/2015\/08\/08\/82248_media_16x16.png","channel_name":"EN - wigi"}]},{"id":"671d689b6583b","title":"NHL : Tampa Bay Lightning vs Washington Capitals\u00a001:00","browser_uuid":["\/live\/hockey\/nhl\/tampa+bay+lightning+vs+washington+capitals\/154\/en"],"sport_name":"-","sport_flag":"https:\/\/img.icons8.com\/?size=48&id=iU4rpa9QGXp0&format=png","date_time":"0000\/00\/00 \u00e0 00:00","live":[{"stream_url":"https:\/\/footdirect.ru\/ply\/1\/154","flag":"https:\/\/www.shareicon.net\/data\/128x128\/2015\/08\/08\/82248_media_16x16.png","channel_name":"EN - Cartel"},{"stream_url":"https:\/\/footdirect.ru\/ply\/2\/154","flag":"https:\/\/www.shareicon.net\/data\/128x128\/2015\/08\/08\/82248_media_16x16.png","channel_name":"EN - Hoca"},{"stream_url":"https:\/\/footdirect.ru\/ply\/5\/154","flag":"https:\/\/www.shareicon.net\/data\/128x128\/2015\/08\/08\/82248_media_16x16.png","channel_name":"EN - CASTER"},{"stream_url":"https:\/\/footdirect.ru\/ply\/3\/154 ","flag":"https:\/\/www.shareicon.net\/data\/128x128\/2015\/08\/08\/82248_media_16x16.png","channel_name":"EN - eplayer"},{"stream_url":"https:\/\/footdirect.ru\/ply\/4\/154","flag":"https:\/\/www.shareicon.net\/data\/128x128\/2015\/08\/08\/82248_media_16x16.png","channel_name":"EN - wigi"}]},{"id":"671d689b6583c","title":"Liga 1 Te Apuesto : Deportivo Garcilaso vs A. Lima\u00a001:00","browser_uuid":["\/live\/foot\/liga+1+te+apuesto\/deportivo+garcilaso+vs+a.+lima\/122\/es"],"sport_name":"-","sport_flag":"https:\/\/img.icons8.com\/?size=48&id=iU4rpa9QGXp0&format=png","date_time":"0000\/00\/00 \u00e0 00:00","live":[{"stream_url":"https:\/\/footdirect.ru\/ply\/1\/122","flag":"https:\/\/www.shareicon.net\/data\/128x128\/2015\/08\/08\/82248_media_16x16.png","channel_name":"ES - Cartel"},{"stream_url":"https:\/\/footdirect.ru\/ply\/2\/122","flag":"https:\/\/www.shareicon.net\/data\/128x128\/2015\/08\/08\/82248_media_16x16.png","channel_name":"ES - Hoca"},{"stream_url":"https:\/\/footdirect.ru\/ply\/5\/122","flag":"https:\/\/www.shareicon.net\/data\/128x128\/2015\/08\/08\/82248_media_16x16.png","channel_name":"ES - CASTER"},{"stream_url":"https:\/\/footdirect.ru\/ply\/3\/122 ","flag":"https:\/\/www.shareicon.net\/data\/128x128\/2015\/08\/08\/82248_media_16x16.png","channel_name":"ES - eplayer"},{"stream_url":"https:\/\/footdirect.ru\/ply\/4\/122","flag":"https:\/\/www.shareicon.net\/data\/128x128\/2015\/08\/08\/82248_media_16x16.png","channel_name":"ES - wigi"}]},{"id":"671d689b6583d","title":"NHL : New York Islanders vs Florida Panthers\u00a001:30","browser_uuid":["\/live\/hockey\/nhl\/new+york+islanders+vs+florida+panthers\/155\/en"],"sport_name":"-","sport_flag":"https:\/\/img.icons8.com\/?size=48&id=iU4rpa9QGXp0&format=png","date_time":"0000\/00\/00 \u00e0 00:00","live":[{"stream_url":"https:\/\/footdirect.ru\/ply\/1\/155","flag":"https:\/\/www.shareicon.net\/data\/128x128\/2015\/08\/08\/82248_media_16x16.png","channel_name":"EN - Cartel"},{"stream_url":"https:\/\/footdirect.ru\/ply\/2\/155","flag":"https:\/\/www.shareicon.net\/data\/128x128\/2015\/08\/08\/82248_media_16x16.png","channel_name":"EN - Hoca"},{"stream_url":"https:\/\/footdirect.ru\/ply\/5\/155","flag":"https:\/\/www.shareicon.net\/data\/128x128\/2015\/08\/08\/82248_media_16x16.png","channel_name":"EN - CASTER"},{"stream_url":"https:\/\/footdirect.ru\/ply\/3\/155 ","flag":"https:\/\/www.shareicon.net\/data\/128x128\/2015\/08\/08\/82248_media_16x16.png","channel_name":"EN - eplayer"},{"stream_url":"https:\/\/footdirect.ru\/ply\/4\/155","flag":"https:\/\/www.shareicon.net\/data\/128x128\/2015\/08\/08\/82248_media_16x16.png","channel_name":"EN - wigi"}]},{"id":"671d689b6583e","title":"Torneo LPF : Velez Sarsfield vs Belgrano\u00a002:00","browser_uuid":["\/live\/foot\/torneo+lpf\/velez+sarsfield+vs+belgrano\/103\/es"],"sport_name":"-","sport_flag":"https:\/\/img.icons8.com\/?size=48&id=iU4rpa9QGXp0&format=png","date_time":"0000\/00\/00 \u00e0 00:00","live":[{"stream_url":"https:\/\/footdirect.ru\/ply\/1\/103","flag":"https:\/\/www.shareicon.net\/data\/128x128\/2015\/08\/08\/82248_media_16x16.png","channel_name":"ES - Cartel"},{"stream_url":"https:\/\/footdirect.ru\/ply\/2\/103","flag":"https:\/\/www.shareicon.net\/data\/128x128\/2015\/08\/08\/82248_media_16x16.png","channel_name":"ES - Hoca"},{"stream_url":"https:\/\/footdirect.ru\/ply\/5\/103","flag":"https:\/\/www.shareicon.net\/data\/128x128\/2015\/08\/08\/82248_media_16x16.png","channel_name":"ES - CASTER"},{"stream_url":"https:\/\/footdirect.ru\/ply\/3\/103 ","flag":"https:\/\/www.shareicon.net\/data\/128x128\/2015\/08\/08\/82248_media_16x16.png","channel_name":"ES - eplayer"},{"stream_url":"https:\/\/footdirect.ru\/ply\/4\/103","flag":"https:\/\/www.shareicon.net\/data\/128x128\/2015\/08\/08\/82248_media_16x16.png","channel_name":"ES - wigi"}]},{"id":"671d689b6583f","title":"Serie A Bresil : Criciuma vs Sao Paulo\u00a002:00","browser_uuid":["\/live\/foot\/serie+a+bresil\/criciuma+vs+sao+paulo\/47\/pt"],"sport_name":"-","sport_flag":"https:\/\/img.icons8.com\/?size=48&id=iU4rpa9QGXp0&format=png","date_time":"0000\/00\/00 \u00e0 00:00","live":[{"stream_url":"https:\/\/footdirect.ru\/ply\/1\/47","flag":"https:\/\/www.shareicon.net\/data\/128x128\/2015\/08\/08\/82248_media_16x16.png","channel_name":"PT - Cartel"},{"stream_url":"https:\/\/footdirect.ru\/ply\/2\/47","flag":"https:\/\/www.shareicon.net\/data\/128x128\/2015\/08\/08\/82248_media_16x16.png","channel_name":"PT - Hoca"},{"stream_url":"https:\/\/footdirect.ru\/ply\/5\/47","flag":"https:\/\/www.shareicon.net\/data\/128x128\/2015\/08\/08\/82248_media_16x16.png","channel_name":"PT - CASTER"},{"stream_url":"https:\/\/footdirect.ru\/ply\/3\/47 ","flag":"https:\/\/www.shareicon.net\/data\/128x128\/2015\/08\/08\/82248_media_16x16.png","channel_name":"PT - eplayer"},{"stream_url":"https:\/\/footdirect.ru\/ply\/4\/47","flag":"https:\/\/www.shareicon.net\/data\/128x128\/2015\/08\/08\/82248_media_16x16.png","channel_name":"PT - wigi"}]},{"id":"671d689b65840","title":"NBA : Chicago Bulls vs Oklahoma City Thunder\u00a002:00","browser_uuid":["\/live\/basket\/nba\/chicago+bulls+vs+oklahoma+city+thunder\/156\/en"],"sport_name":"-","sport_flag":"https:\/\/img.icons8.com\/?size=48&id=iU4rpa9QGXp0&format=png","date_time":"0000\/00\/00 \u00e0 00:00","live":[{"stream_url":"https:\/\/footdirect.ru\/ply\/1\/156","flag":"https:\/\/www.shareicon.net\/data\/128x128\/2015\/08\/08\/82248_media_16x16.png","channel_name":"EN - Cartel"},{"stream_url":"https:\/\/footdirect.ru\/ply\/2\/156","flag":"https:\/\/www.shareicon.net\/data\/128x128\/2015\/08\/08\/82248_media_16x16.png","channel_name":"EN - Hoca"},{"stream_url":"https:\/\/footdirect.ru\/ply\/5\/156","flag":"https:\/\/www.shareicon.net\/data\/128x128\/2015\/08\/08\/82248_media_16x16.png","channel_name":"EN - CASTER"},{"stream_url":"https:\/\/footdirect.ru\/ply\/3\/156 ","flag":"https:\/\/www.shareicon.net\/data\/128x128\/2015\/08\/08\/82248_media_16x16.png","channel_name":"EN - eplayer"},{"stream_url":"https:\/\/footdirect.ru\/ply\/4\/156","flag":"https:\/\/www.shareicon.net\/data\/128x128\/2015\/08\/08\/82248_media_16x16.png","channel_name":"EN - wigi"}]},{"id":"671d689b65841","title":"NBA : Memphis Grizzlies vs Orlando Magic\u00a002:00","browser_uuid":["\/live\/basket\/nba\/memphis+grizzlies+vs+orlando+magic\/157\/en"],"sport_name":"-","sport_flag":"https:\/\/img.icons8.com\/?size=48&id=iU4rpa9QGXp0&format=png","date_time":"0000\/00\/00 \u00e0 00:00","live":[{"stream_url":"https:\/\/footdirect.ru\/ply\/1\/157","flag":"https:\/\/www.shareicon.net\/data\/128x128\/2015\/08\/08\/82248_media_16x16.png","channel_name":"EN - Cartel"},{"stream_url":"https:\/\/footdirect.ru\/ply\/2\/157","flag":"https:\/\/www.shareicon.net\/data\/128x128\/2015\/08\/08\/82248_media_16x16.png","channel_name":"EN - Hoca"},{"stream_url":"https:\/\/footdirect.ru\/ply\/5\/157","flag":"https:\/\/www.shareicon.net\/data\/128x128\/2015\/08\/08\/82248_media_16x16.png","channel_name":"EN - CASTER"},{"stream_url":"https:\/\/footdirect.ru\/ply\/3\/157 ","flag":"https:\/\/www.shareicon.net\/data\/128x128\/2015\/08\/08\/82248_media_16x16.png","channel_name":"EN - eplayer"},{"stream_url":"https:\/\/footdirect.ru\/ply\/4\/157","flag":"https:\/\/www.shareicon.net\/data\/128x128\/2015\/08\/08\/82248_media_16x16.png","channel_name":"EN - wigi"}]},{"id":"671d689b65842","title":"NBA : Minnesota Timberwolves vs Toronto Raptors\u00a002:00","browser_uuid":["\/live\/basket\/nba\/minnesota+timberwolves+vs+toronto+raptors\/148\/en"],"sport_name":"-","sport_flag":"https:\/\/img.icons8.com\/?size=48&id=iU4rpa9QGXp0&format=png","date_time":"0000\/00\/00 \u00e0 00:00","live":[{"stream_url":"https:\/\/footdirect.ru\/ply\/1\/148","flag":"https:\/\/www.shareicon.net\/data\/128x128\/2015\/08\/08\/82248_media_16x16.png","channel_name":"EN - Cartel"},{"stream_url":"https:\/\/footdirect.ru\/ply\/2\/148","flag":"https:\/\/www.shareicon.net\/data\/128x128\/2015\/08\/08\/82248_media_16x16.png","channel_name":"EN - Hoca"},{"stream_url":"https:\/\/footdirect.ru\/ply\/5\/148","flag":"https:\/\/www.shareicon.net\/data\/128x128\/2015\/08\/08\/82248_media_16x16.png","channel_name":"EN - CASTER"},{"stream_url":"https:\/\/footdirect.ru\/ply\/3\/148 ","flag":"https:\/\/www.shareicon.net\/data\/128x128\/2015\/08\/08\/82248_media_16x16.png","channel_name":"EN - eplayer"},{"stream_url":"https:\/\/footdirect.ru\/ply\/4\/148","flag":"https:\/\/www.shareicon.net\/data\/128x128\/2015\/08\/08\/82248_media_16x16.png","channel_name":"EN - wigi"}]},{"id":"671d689b65843","title":"NHL : Dallas Stars vs Chicago Blackhawks\u00a002:00","browser_uuid":["\/live\/hockey\/nhl\/dallas+stars+vs+chicago+blackhawks\/149\/en"],"sport_name":"-","sport_flag":"https:\/\/img.icons8.com\/?size=48&id=iU4rpa9QGXp0&format=png","date_time":"0000\/00\/00 \u00e0 00:00","live":[{"stream_url":"https:\/\/footdirect.ru\/ply\/1\/149","flag":"https:\/\/www.shareicon.net\/data\/128x128\/2015\/08\/08\/82248_media_16x16.png","channel_name":"EN - Cartel"},{"stream_url":"https:\/\/footdirect.ru\/ply\/2\/149","flag":"https:\/\/www.shareicon.net\/data\/128x128\/2015\/08\/08\/82248_media_16x16.png","channel_name":"EN - Hoca"},{"stream_url":"https:\/\/footdirect.ru\/ply\/5\/149","flag":"https:\/\/www.shareicon.net\/data\/128x128\/2015\/08\/08\/82248_media_16x16.png","channel_name":"EN - CASTER"},{"stream_url":"https:\/\/footdirect.ru\/ply\/3\/149 ","flag":"https:\/\/www.shareicon.net\/data\/128x128\/2015\/08\/08\/82248_media_16x16.png","channel_name":"EN - eplayer"},{"stream_url":"https:\/\/footdirect.ru\/ply\/4\/149","flag":"https:\/\/www.shareicon.net\/data\/128x128\/2015\/08\/08\/82248_media_16x16.png","channel_name":"EN - wigi"}]},{"id":"671d689b65844","title":"NHL : Nashville Predators vs Columbus Blue Jackets\u00a002:00","browser_uuid":["\/live\/hockey\/nhl\/nashville+predators+vs+columbus+blue+jackets\/150\/en"],"sport_name":"-","sport_flag":"https:\/\/img.icons8.com\/?size=48&id=iU4rpa9QGXp0&format=png","date_time":"0000\/00\/00 \u00e0 00:00","live":[{"stream_url":"https:\/\/footdirect.ru\/ply\/1\/150","flag":"https:\/\/www.shareicon.net\/data\/128x128\/2015\/08\/08\/82248_media_16x16.png","channel_name":"EN - Cartel"},{"stream_url":"https:\/\/footdirect.ru\/ply\/2\/150","flag":"https:\/\/www.shareicon.net\/data\/128x128\/2015\/08\/08\/82248_media_16x16.png","channel_name":"EN - Hoca"},{"stream_url":"https:\/\/footdirect.ru\/ply\/5\/150","flag":"https:\/\/www.shareicon.net\/data\/128x128\/2015\/08\/08\/82248_media_16x16.png","channel_name":"EN - CASTER"},{"stream_url":"https:\/\/footdirect.ru\/ply\/3\/150 ","flag":"https:\/\/www.shareicon.net\/data\/128x128\/2015\/08\/08\/82248_media_16x16.png","channel_name":"EN - eplayer"},{"stream_url":"https:\/\/footdirect.ru\/ply\/4\/150","flag":"https:\/\/www.shareicon.net\/data\/128x128\/2015\/08\/08\/82248_media_16x16.png","channel_name":"EN - wigi"}]},{"id":"671d689b65845","title":"Colombia Liga Betplay Dimayor : Santa Fe vs Millonarios\u00a002:30","browser_uuid":["\/live\/foot\/colombia+liga+betplay+dimayor\/santa+fe+vs+millonarios\/120\/es"],"sport_name":"-","sport_flag":"https:\/\/img.icons8.com\/?size=48&id=iU4rpa9QGXp0&format=png","date_time":"0000\/00\/00 \u00e0 00:00","live":[{"stream_url":"https:\/\/footdirect.ru\/ply\/1\/120","flag":"https:\/\/www.shareicon.net\/data\/128x128\/2015\/08\/08\/82248_media_16x16.png","channel_name":"ES - Cartel"},{"stream_url":"https:\/\/footdirect.ru\/ply\/2\/120","flag":"https:\/\/www.shareicon.net\/data\/128x128\/2015\/08\/08\/82248_media_16x16.png","channel_name":"ES - Hoca"},{"stream_url":"https:\/\/footdirect.ru\/ply\/5\/120","flag":"https:\/\/www.shareicon.net\/data\/128x128\/2015\/08\/08\/82248_media_16x16.png","channel_name":"ES - CASTER"},{"stream_url":"https:\/\/footdirect.ru\/ply\/3\/120 ","flag":"https:\/\/www.shareicon.net\/data\/128x128\/2015\/08\/08\/82248_media_16x16.png","channel_name":"ES - eplayer"},{"stream_url":"https:\/\/footdirect.ru\/ply\/4\/120","flag":"https:\/\/www.shareicon.net\/data\/128x128\/2015\/08\/08\/82248_media_16x16.png","channel_name":"ES - wigi"}]},{"id":"671d689b65846","title":"NBA : San Antonio Spurs vs Houston Rockets\u00a002:30","browser_uuid":["\/live\/basket\/nba\/san+antonio+spurs+vs+houston+rockets\/130\/en"],"sport_name":"-","sport_flag":"https:\/\/img.icons8.com\/?size=48&id=iU4rpa9QGXp0&format=png","date_time":"0000\/00\/00 \u00e0 00:00","live":[{"stream_url":"https:\/\/footdirect.ru\/ply\/1\/130","flag":"https:\/\/www.shareicon.net\/data\/128x128\/2015\/08\/08\/82248_media_16x16.png","channel_name":"EN - Cartel"},{"stream_url":"https:\/\/footdirect.ru\/ply\/2\/130","flag":"https:\/\/www.shareicon.net\/data\/128x128\/2015\/08\/08\/82248_media_16x16.png","channel_name":"EN - Hoca"},{"stream_url":"https:\/\/footdirect.ru\/ply\/5\/130","flag":"https:\/\/www.shareicon.net\/data\/128x128\/2015\/08\/08\/82248_media_16x16.png","channel_name":"EN - CASTER"},{"stream_url":"https:\/\/footdirect.ru\/ply\/3\/130 ","flag":"https:\/\/www.shareicon.net\/data\/128x128\/2015\/08\/08\/82248_media_16x16.png","channel_name":"EN - eplayer"},{"stream_url":"https:\/\/footdirect.ru\/ply\/4\/130","flag":"https:\/\/www.shareicon.net\/data\/128x128\/2015\/08\/08\/82248_media_16x16.png","channel_name":"EN - wigi"}]},{"id":"671d689b65847","title":"Torneo LPF : Ind. Rivadavia vs San Lorenzo\u00a002:45","browser_uuid":["\/live\/foot\/torneo+lpf\/ind.+rivadavia+vs+san+lorenzo\/104\/es"],"sport_name":"-","sport_flag":"https:\/\/img.icons8.com\/?size=48&id=iU4rpa9QGXp0&format=png","date_time":"0000\/00\/00 \u00e0 00:00","live":[{"stream_url":"https:\/\/footdirect.ru\/ply\/1\/104","flag":"https:\/\/www.shareicon.net\/data\/128x128\/2015\/08\/08\/82248_media_16x16.png","channel_name":"ES - Cartel"},{"stream_url":"https:\/\/footdirect.ru\/ply\/2\/104","flag":"https:\/\/www.shareicon.net\/data\/128x128\/2015\/08\/08\/82248_media_16x16.png","channel_name":"ES - Hoca"},{"stream_url":"https:\/\/footdirect.ru\/ply\/5\/104","flag":"https:\/\/www.shareicon.net\/data\/128x128\/2015\/08\/08\/82248_media_16x16.png","channel_name":"ES - CASTER"},{"stream_url":"https:\/\/footdirect.ru\/ply\/3\/104 ","flag":"https:\/\/www.shareicon.net\/data\/128x128\/2015\/08\/08\/82248_media_16x16.png","channel_name":"ES - eplayer"},{"stream_url":"https:\/\/footdirect.ru\/ply\/4\/104","flag":"https:\/\/www.shareicon.net\/data\/128x128\/2015\/08\/08\/82248_media_16x16.png","channel_name":"ES - wigi"}]},{"id":"671d689b65848","title":"Liga Mx : U.N.A.M. vs Cruz Azul\u00a003:00","browser_uuid":["\/live\/foot\/liga+mx\/u.n.a.m.+vs+cruz+azul\/100\/es","\/live\/foot\/liga+mx\/u.n.a.m.+vs+cruz+azul\/128\/es"],"sport_name":"-","sport_flag":"https:\/\/img.icons8.com\/?size=48&id=iU4rpa9QGXp0&format=png","date_time":"0000\/00\/00 \u00e0 00:00","live":[{"stream_url":"https:\/\/footdirect.ru\/ply\/1\/100","flag":"https:\/\/www.shareicon.net\/data\/128x128\/2015\/08\/08\/82248_media_16x16.png","channel_name":"ES - Cartel"},{"stream_url":"https:\/\/footdirect.ru\/ply\/2\/100","flag":"https:\/\/www.shareicon.net\/data\/128x128\/2015\/08\/08\/82248_media_16x16.png","channel_name":"ES - Hoca"},{"stream_url":"https:\/\/footdirect.ru\/ply\/5\/100","flag":"https:\/\/www.shareicon.net\/data\/128x128\/2015\/08\/08\/82248_media_16x16.png","channel_name":"ES - CASTER"},{"stream_url":"https:\/\/footdirect.ru\/ply\/3\/100 ","flag":"https:\/\/www.shareicon.net\/data\/128x128\/2015\/08\/08\/82248_media_16x16.png","channel_name":"ES - eplayer"},{"stream_url":"https:\/\/footdirect.ru\/ply\/4\/100","flag":"https:\/\/www.shareicon.net\/data\/128x128\/2015\/08\/08\/82248_media_16x16.png","channel_name":"ES - wigi"},{"stream_url":"https:\/\/footdirect.ru\/ply\/1\/128","flag":"https:\/\/www.shareicon.net\/data\/128x128\/2015\/08\/08\/82248_media_16x16.png","channel_name":"ES - Cartel"},{"stream_url":"https:\/\/footdirect.ru\/ply\/2\/128","flag":"https:\/\/www.shareicon.net\/data\/128x128\/2015\/08\/08\/82248_media_16x16.png","channel_name":"ES - Hoca"},{"stream_url":"https:\/\/footdirect.ru\/ply\/5\/128","flag":"https:\/\/www.shareicon.net\/data\/128x128\/2015\/08\/08\/82248_media_16x16.png","channel_name":"ES - CASTER"},{"stream_url":"https:\/\/footdirect.ru\/ply\/3\/128 ","flag":"https:\/\/www.shareicon.net\/data\/128x128\/2015\/08\/08\/82248_media_16x16.png","channel_name":"ES - eplayer"},{"stream_url":"https:\/\/footdirect.ru\/ply\/4\/128","flag":"https:\/\/www.shareicon.net\/data\/128x128\/2015\/08\/08\/82248_media_16x16.png","channel_name":"ES - wigi"}]},{"id":"671d689b65849","title":"NBA : Phoenix Suns vs Dallas Mavericks\u00a003:00","browser_uuid":["\/live\/basket\/nba\/phoenix+suns+vs+dallas+mavericks\/131\/en"],"sport_name":"-","sport_flag":"https:\/\/img.icons8.com\/?size=48&id=iU4rpa9QGXp0&format=png","date_time":"0000\/00\/00 \u00e0 00:00","live":[{"stream_url":"https:\/\/footdirect.ru\/ply\/1\/131","flag":"https:\/\/www.shareicon.net\/data\/128x128\/2015\/08\/08\/82248_media_16x16.png","channel_name":"EN - Cartel"},{"stream_url":"https:\/\/footdirect.ru\/ply\/2\/131","flag":"https:\/\/www.shareicon.net\/data\/128x128\/2015\/08\/08\/82248_media_16x16.png","channel_name":"EN - Hoca"},{"stream_url":"https:\/\/footdirect.ru\/ply\/5\/131","flag":"https:\/\/www.shareicon.net\/data\/128x128\/2015\/08\/08\/82248_media_16x16.png","channel_name":"EN - CASTER"},{"stream_url":"https:\/\/footdirect.ru\/ply\/3\/131 ","flag":"https:\/\/www.shareicon.net\/data\/128x128\/2015\/08\/08\/82248_media_16x16.png","channel_name":"EN - eplayer"},{"stream_url":"https:\/\/footdirect.ru\/ply\/4\/131","flag":"https:\/\/www.shareicon.net\/data\/128x128\/2015\/08\/08\/82248_media_16x16.png","channel_name":"EN - wigi"}]},{"id":"671d689b6584a","title":"NHL : Seattle Kraken vs Carolina Hurricanes\u00a003:00","browser_uuid":["\/live\/hockey\/nhl\/seattle+kraken+vs+carolina+hurricanes\/132\/en"],"sport_name":"-","sport_flag":"https:\/\/img.icons8.com\/?size=48&id=iU4rpa9QGXp0&format=png","date_time":"0000\/00\/00 \u00e0 00:00","live":[{"stream_url":"https:\/\/footdirect.ru\/ply\/1\/132","flag":"https:\/\/www.shareicon.net\/data\/128x128\/2015\/08\/08\/82248_media_16x16.png","channel_name":"EN - Cartel"},{"stream_url":"https:\/\/footdirect.ru\/ply\/2\/132","flag":"https:\/\/www.shareicon.net\/data\/128x128\/2015\/08\/08\/82248_media_16x16.png","channel_name":"EN - Hoca"},{"stream_url":"https:\/\/footdirect.ru\/ply\/5\/132","flag":"https:\/\/www.shareicon.net\/data\/128x128\/2015\/08\/08\/82248_media_16x16.png","channel_name":"EN - CASTER"},{"stream_url":"https:\/\/footdirect.ru\/ply\/3\/132 ","flag":"https:\/\/www.shareicon.net\/data\/128x128\/2015\/08\/08\/82248_media_16x16.png","channel_name":"EN - eplayer"},{"stream_url":"https:\/\/footdirect.ru\/ply\/4\/132","flag":"https:\/\/www.shareicon.net\/data\/128x128\/2015\/08\/08\/82248_media_16x16.png","channel_name":"EN - wigi"}]},{"id":"671d689b6584b","title":"NHL : Vancouver Canucks vs Pittsburgh Penguins\u00a003:00","browser_uuid":["\/live\/hockey\/nhl\/vancouver+canucks+vs+pittsburgh+penguins\/133\/en"],"sport_name":"-","sport_flag":"https:\/\/img.icons8.com\/?size=48&id=iU4rpa9QGXp0&format=png","date_time":"0000\/00\/00 \u00e0 00:00","live":[{"stream_url":"https:\/\/footdirect.ru\/ply\/1\/133","flag":"https:\/\/www.shareicon.net\/data\/128x128\/2015\/08\/08\/82248_media_16x16.png","channel_name":"EN - Cartel"},{"stream_url":"https:\/\/footdirect.ru\/ply\/2\/133","flag":"https:\/\/www.shareicon.net\/data\/128x128\/2015\/08\/08\/82248_media_16x16.png","channel_name":"EN - Hoca"},{"stream_url":"https:\/\/footdirect.ru\/ply\/5\/133","flag":"https:\/\/www.shareicon.net\/data\/128x128\/2015\/08\/08\/82248_media_16x16.png","channel_name":"EN - CASTER"},{"stream_url":"https:\/\/footdirect.ru\/ply\/3\/133 ","flag":"https:\/\/www.shareicon.net\/data\/128x128\/2015\/08\/08\/82248_media_16x16.png","channel_name":"EN - eplayer"},{"stream_url":"https:\/\/footdirect.ru\/ply\/4\/133","flag":"https:\/\/www.shareicon.net\/data\/128x128\/2015\/08\/08\/82248_media_16x16.png","channel_name":"EN - wigi"}]},{"id":"671d689b6584c","title":"NHL : Vegas Golden Knights vs San Jose Sharks\u00a003:00","browser_uuid":["\/live\/hockey\/nhl\/vegas+golden+knights+vs+san+jose+sharks\/134\/en"],"sport_name":"-","sport_flag":"https:\/\/img.icons8.com\/?size=48&id=iU4rpa9QGXp0&format=png","date_time":"0000\/00\/00 \u00e0 00:00","live":[{"stream_url":"https:\/\/footdirect.ru\/ply\/1\/134","flag":"https:\/\/www.shareicon.net\/data\/128x128\/2015\/08\/08\/82248_media_16x16.png","channel_name":"EN - Cartel"},{"stream_url":"https:\/\/footdirect.ru\/ply\/2\/134","flag":"https:\/\/www.shareicon.net\/data\/128x128\/2015\/08\/08\/82248_media_16x16.png","channel_name":"EN - Hoca"},{"stream_url":"https:\/\/footdirect.ru\/ply\/5\/134","flag":"https:\/\/www.shareicon.net\/data\/128x128\/2015\/08\/08\/82248_media_16x16.png","channel_name":"EN - CASTER"},{"stream_url":"https:\/\/footdirect.ru\/ply\/3\/134 ","flag":"https:\/\/www.shareicon.net\/data\/128x128\/2015\/08\/08\/82248_media_16x16.png","channel_name":"EN - eplayer"},{"stream_url":"https:\/\/footdirect.ru\/ply\/4\/134","flag":"https:\/\/www.shareicon.net\/data\/128x128\/2015\/08\/08\/82248_media_16x16.png","channel_name":"EN - wigi"}]},{"id":"671d689b6584d","title":"Liga De Expansion Mx : Tlaxcala vs Venados\u00a003:06","browser_uuid":["\/live\/foot\/liga+de+expansion+mx\/tlaxcala+vs+venados\/113\/es"],"sport_name":"-","sport_flag":"https:\/\/img.icons8.com\/?size=48&id=iU4rpa9QGXp0&format=png","date_time":"0000\/00\/00 \u00e0 00:00","live":[{"stream_url":"https:\/\/footdirect.ru\/ply\/1\/113","flag":"https:\/\/www.shareicon.net\/data\/128x128\/2015\/08\/08\/82248_media_16x16.png","channel_name":"ES - Cartel"},{"stream_url":"https:\/\/footdirect.ru\/ply\/2\/113","flag":"https:\/\/www.shareicon.net\/data\/128x128\/2015\/08\/08\/82248_media_16x16.png","channel_name":"ES - Hoca"},{"stream_url":"https:\/\/footdirect.ru\/ply\/5\/113","flag":"https:\/\/www.shareicon.net\/data\/128x128\/2015\/08\/08\/82248_media_16x16.png","channel_name":"ES - CASTER"},{"stream_url":"https:\/\/footdirect.ru\/ply\/3\/113 ","flag":"https:\/\/www.shareicon.net\/data\/128x128\/2015\/08\/08\/82248_media_16x16.png","channel_name":"ES - eplayer"},{"stream_url":"https:\/\/footdirect.ru\/ply\/4\/113","flag":"https:\/\/www.shareicon.net\/data\/128x128\/2015\/08\/08\/82248_media_16x16.png","channel_name":"ES - wigi"}]},{"id":"671d689b6584e","title":"NBA : Los Angeles Lakers vs Sacramento Kings\u00a003:30","browser_uuid":["\/live\/basket\/nba\/los+angeles+lakers+vs+sacramento+kings\/135\/en","\/live\/basket\/nba\/los+angeles+lakers+vs+sacramento+kings\/108\/es"],"sport_name":"-","sport_flag":"https:\/\/img.icons8.com\/?size=48&id=iU4rpa9QGXp0&format=png","date_time":"0000\/00\/00 \u00e0 00:00","live":[{"stream_url":"https:\/\/footdirect.ru\/ply\/1\/135","flag":"https:\/\/www.shareicon.net\/data\/128x128\/2015\/08\/08\/82248_media_16x16.png","channel_name":"EN - Cartel"},{"stream_url":"https:\/\/footdirect.ru\/ply\/2\/135","flag":"https:\/\/www.shareicon.net\/data\/128x128\/2015\/08\/08\/82248_media_16x16.png","channel_name":"EN - Hoca"},{"stream_url":"https:\/\/footdirect.ru\/ply\/5\/135","flag":"https:\/\/www.shareicon.net\/data\/128x128\/2015\/08\/08\/82248_media_16x16.png","channel_name":"EN - CASTER"},{"stream_url":"https:\/\/footdirect.ru\/ply\/3\/135 ","flag":"https:\/\/www.shareicon.net\/data\/128x128\/2015\/08\/08\/82248_media_16x16.png","channel_name":"EN - eplayer"},{"stream_url":"https:\/\/footdirect.ru\/ply\/4\/135","flag":"https:\/\/www.shareicon.net\/data\/128x128\/2015\/08\/08\/82248_media_16x16.png","channel_name":"EN - wigi"},{"stream_url":"https:\/\/footdirect.ru\/ply\/1\/108","flag":"https:\/\/www.shareicon.net\/data\/128x128\/2015\/08\/08\/82248_media_16x16.png","channel_name":"ES - Cartel"},{"stream_url":"https:\/\/footdirect.ru\/ply\/2\/108","flag":"https:\/\/www.shareicon.net\/data\/128x128\/2015\/08\/08\/82248_media_16x16.png","channel_name":"ES - Hoca"},{"stream_url":"https:\/\/footdirect.ru\/ply\/5\/108","flag":"https:\/\/www.shareicon.net\/data\/128x128\/2015\/08\/08\/82248_media_16x16.png","channel_name":"ES - CASTER"},{"stream_url":"https:\/\/footdirect.ru\/ply\/3\/108 ","flag":"https:\/\/www.shareicon.net\/data\/128x128\/2015\/08\/08\/82248_media_16x16.png","channel_name":"ES - eplayer"},{"stream_url":"https:\/\/footdirect.ru\/ply\/4\/108","flag":"https:\/\/www.shareicon.net\/data\/128x128\/2015\/08\/08\/82248_media_16x16.png","channel_name":"ES - wigi"}]},{"id":"671d689b6584f","title":"Liga 1 Te Apuesto : Cesar Vallejo vs Carlos Mannucci\u00a003:30","browser_uuid":["\/live\/foot\/liga+1+te+apuesto\/cesar+vallejo+vs+carlos+mannucci\/122\/es"],"sport_name":"-","sport_flag":"https:\/\/img.icons8.com\/?size=48&id=iU4rpa9QGXp0&format=png","date_time":"0000\/00\/00 \u00e0 00:00","live":[{"stream_url":"https:\/\/footdirect.ru\/ply\/1\/122","flag":"https:\/\/www.shareicon.net\/data\/128x128\/2015\/08\/08\/82248_media_16x16.png","channel_name":"ES - Cartel"},{"stream_url":"https:\/\/footdirect.ru\/ply\/2\/122","flag":"https:\/\/www.shareicon.net\/data\/128x128\/2015\/08\/08\/82248_media_16x16.png","channel_name":"ES - Hoca"},{"stream_url":"https:\/\/footdirect.ru\/ply\/5\/122","flag":"https:\/\/www.shareicon.net\/data\/128x128\/2015\/08\/08\/82248_media_16x16.png","channel_name":"ES - CASTER"},{"stream_url":"https:\/\/footdirect.ru\/ply\/3\/122 ","flag":"https:\/\/www.shareicon.net\/data\/128x128\/2015\/08\/08\/82248_media_16x16.png","channel_name":"ES - eplayer"},{"stream_url":"https:\/\/footdirect.ru\/ply\/4\/122","flag":"https:\/\/www.shareicon.net\/data\/128x128\/2015\/08\/08\/82248_media_16x16.png","channel_name":"ES - wigi"}]},{"id":"671d689b65850","title":"Liga Mx : Tigres vs Pachuca\u00a004:00","browser_uuid":["\/live\/foot\/liga+mx\/tigres+vs+pachuca\/126\/es"],"sport_name":"-","sport_flag":"https:\/\/img.icons8.com\/?size=48&id=iU4rpa9QGXp0&format=png","date_time":"0000\/00\/00 \u00e0 00:00","live":[{"stream_url":"https:\/\/footdirect.ru\/ply\/1\/126","flag":"https:\/\/www.shareicon.net\/data\/128x128\/2015\/08\/08\/82248_media_16x16.png","channel_name":"ES - Cartel"},{"stream_url":"https:\/\/footdirect.ru\/ply\/2\/126","flag":"https:\/\/www.shareicon.net\/data\/128x128\/2015\/08\/08\/82248_media_16x16.png","channel_name":"ES - Hoca"},{"stream_url":"https:\/\/footdirect.ru\/ply\/5\/126","flag":"https:\/\/www.shareicon.net\/data\/128x128\/2015\/08\/08\/82248_media_16x16.png","channel_name":"ES - CASTER"},{"stream_url":"https:\/\/footdirect.ru\/ply\/3\/126 ","flag":"https:\/\/www.shareicon.net\/data\/128x128\/2015\/08\/08\/82248_media_16x16.png","channel_name":"ES - eplayer"},{"stream_url":"https:\/\/footdirect.ru\/ply\/4\/126","flag":"https:\/\/www.shareicon.net\/data\/128x128\/2015\/08\/08\/82248_media_16x16.png","channel_name":"ES - wigi"}]},{"id":"671d689b65851","title":"MLS : Los Angeles Galaxy vs Colorado Rapids\u00a004:00","browser_uuid":["\/live\/foot\/mls\/los+angeles+galaxy+vs+colorado+rapids\/136\/en"],"sport_name":"-","sport_flag":"https:\/\/img.icons8.com\/?size=48&id=iU4rpa9QGXp0&format=png","date_time":"0000\/00\/00 \u00e0 00:00","live":[{"stream_url":"https:\/\/footdirect.ru\/ply\/1\/136","flag":"https:\/\/www.shareicon.net\/data\/128x128\/2015\/08\/08\/82248_media_16x16.png","channel_name":"EN - Cartel"},{"stream_url":"https:\/\/footdirect.ru\/ply\/2\/136","flag":"https:\/\/www.shareicon.net\/data\/128x128\/2015\/08\/08\/82248_media_16x16.png","channel_name":"EN - Hoca"},{"stream_url":"https:\/\/footdirect.ru\/ply\/5\/136","flag":"https:\/\/www.shareicon.net\/data\/128x128\/2015\/08\/08\/82248_media_16x16.png","channel_name":"EN - CASTER"},{"stream_url":"https:\/\/footdirect.ru\/ply\/3\/136 ","flag":"https:\/\/www.shareicon.net\/data\/128x128\/2015\/08\/08\/82248_media_16x16.png","channel_name":"EN - eplayer"},{"stream_url":"https:\/\/footdirect.ru\/ply\/4\/136","flag":"https:\/\/www.shareicon.net\/data\/128x128\/2015\/08\/08\/82248_media_16x16.png","channel_name":"EN - wigi"}]},{"id":"671d689b65852","title":"Liga Mx : Atlas vs Tijuana\u00a004:05","browser_uuid":["\/live\/foot\/liga+mx\/atlas+vs+tijuana\/100\/es","\/live\/foot\/liga+mx\/atlas+vs+tijuana\/128\/es"],"sport_name":"-","sport_flag":"https:\/\/img.icons8.com\/?size=48&id=iU4rpa9QGXp0&format=png","date_time":"0000\/00\/00 \u00e0 00:00","live":[{"stream_url":"https:\/\/footdirect.ru\/ply\/1\/100","flag":"https:\/\/www.shareicon.net\/data\/128x128\/2015\/08\/08\/82248_media_16x16.png","channel_name":"ES - Cartel"},{"stream_url":"https:\/\/footdirect.ru\/ply\/2\/100","flag":"https:\/\/www.shareicon.net\/data\/128x128\/2015\/08\/08\/82248_media_16x16.png","channel_name":"ES - Hoca"},{"stream_url":"https:\/\/footdirect.ru\/ply\/5\/100","flag":"https:\/\/www.shareicon.net\/data\/128x128\/2015\/08\/08\/82248_media_16x16.png","channel_name":"ES - CASTER"},{"stream_url":"https:\/\/footdirect.ru\/ply\/3\/100 ","flag":"https:\/\/www.shareicon.net\/data\/128x128\/2015\/08\/08\/82248_media_16x16.png","channel_name":"ES - eplayer"},{"stream_url":"https:\/\/footdirect.ru\/ply\/4\/100","flag":"https:\/\/www.shareicon.net\/data\/128x128\/2015\/08\/08\/82248_media_16x16.png","channel_name":"ES - wigi"},{"stream_url":"https:\/\/footdirect.ru\/ply\/1\/128","flag":"https:\/\/www.shareicon.net\/data\/128x128\/2015\/08\/08\/82248_media_16x16.png","channel_name":"ES - Cartel"},{"stream_url":"https:\/\/footdirect.ru\/ply\/2\/128","flag":"https:\/\/www.shareicon.net\/data\/128x128\/2015\/08\/08\/82248_media_16x16.png","channel_name":"ES - Hoca"},{"stream_url":"https:\/\/footdirect.ru\/ply\/5\/128","flag":"https:\/\/www.shareicon.net\/data\/128x128\/2015\/08\/08\/82248_media_16x16.png","channel_name":"ES - CASTER"},{"stream_url":"https:\/\/footdirect.ru\/ply\/3\/128 ","flag":"https:\/\/www.shareicon.net\/data\/128x128\/2015\/08\/08\/82248_media_16x16.png","channel_name":"ES - eplayer"},{"stream_url":"https:\/\/footdirect.ru\/ply\/4\/128","flag":"https:\/\/www.shareicon.net\/data\/128x128\/2015\/08\/08\/82248_media_16x16.png","channel_name":"ES - wigi"}]},{"id":"671d689b65853","title":"Liga De Expansion Mx : Dorados vs Atletico La Paz\u00a004:10","browser_uuid":["\/live\/foot\/liga+de+expansion+mx\/dorados+vs+atletico+la+paz\/113\/es"],"sport_name":"-","sport_flag":"https:\/\/img.icons8.com\/?size=48&id=iU4rpa9QGXp0&format=png","date_time":"0000\/00\/00 \u00e0 00:00","live":[{"stream_url":"https:\/\/footdirect.ru\/ply\/1\/113","flag":"https:\/\/www.shareicon.net\/data\/128x128\/2015\/08\/08\/82248_media_16x16.png","channel_name":"ES - Cartel"},{"stream_url":"https:\/\/footdirect.ru\/ply\/2\/113","flag":"https:\/\/www.shareicon.net\/data\/128x128\/2015\/08\/08\/82248_media_16x16.png","channel_name":"ES - Hoca"},{"stream_url":"https:\/\/footdirect.ru\/ply\/5\/113","flag":"https:\/\/www.shareicon.net\/data\/128x128\/2015\/08\/08\/82248_media_16x16.png","channel_name":"ES - CASTER"},{"stream_url":"https:\/\/footdirect.ru\/ply\/3\/113 ","flag":"https:\/\/www.shareicon.net\/data\/128x128\/2015\/08\/08\/82248_media_16x16.png","channel_name":"ES - eplayer"},{"stream_url":"https:\/\/footdirect.ru\/ply\/4\/113","flag":"https:\/\/www.shareicon.net\/data\/128x128\/2015\/08\/08\/82248_media_16x16.png","channel_name":"ES - wigi"}]},{"id":"671d689b65854","title":"MotoGP : Grand Prix de Tha\u00eflande Warm up des Moto GP\u00a004:40","browser_uuid":["\/live\/moto\/motogp\/grand+prix+de+tha\u00eflande+warm+up+des+moto+gp\/28\/fr","\/live\/moto\/motogp\/grand+prix+de+tha\u00eflande+warm+up+des+moto+gp\/81\/es"],"sport_name":"-","sport_flag":"https:\/\/img.icons8.com\/?size=48&id=iU4rpa9QGXp0&format=png","date_time":"0000\/00\/00 \u00e0 00:00","live":[{"stream_url":"https:\/\/footdirect.ru\/ply\/1\/28","flag":"https:\/\/www.shareicon.net\/data\/128x128\/2015\/08\/08\/82248_media_16x16.png","channel_name":"FR - Cartel"},{"stream_url":"https:\/\/footdirect.ru\/ply\/2\/28","flag":"https:\/\/www.shareicon.net\/data\/128x128\/2015\/08\/08\/82248_media_16x16.png","channel_name":"FR - Hoca"},{"stream_url":"https:\/\/footdirect.ru\/ply\/5\/28","flag":"https:\/\/www.shareicon.net\/data\/128x128\/2015\/08\/08\/82248_media_16x16.png","channel_name":"FR - CASTER"},{"stream_url":"https:\/\/footdirect.ru\/ply\/3\/28 ","flag":"https:\/\/www.shareicon.net\/data\/128x128\/2015\/08\/08\/82248_media_16x16.png","channel_name":"FR - eplayer"},{"stream_url":"https:\/\/footdirect.ru\/ply\/4\/28","flag":"https:\/\/www.shareicon.net\/data\/128x128\/2015\/08\/08\/82248_media_16x16.png","channel_name":"FR - wigi"},{"stream_url":"https:\/\/footdirect.ru\/ply\/1\/81","flag":"https:\/\/www.shareicon.net\/data\/128x128\/2015\/08\/08\/82248_media_16x16.png","channel_name":"ES - Cartel"},{"stream_url":"https:\/\/footdirect.ru\/ply\/2\/81","flag":"https:\/\/www.shareicon.net\/data\/128x128\/2015\/08\/08\/82248_media_16x16.png","channel_name":"ES - Hoca"},{"stream_url":"https:\/\/footdirect.ru\/ply\/5\/81","flag":"https:\/\/www.shareicon.net\/data\/128x128\/2015\/08\/08\/82248_media_16x16.png","channel_name":"ES - CASTER"},{"stream_url":"https:\/\/footdirect.ru\/ply\/3\/81 ","flag":"https:\/\/www.shareicon.net\/data\/128x128\/2015\/08\/08\/82248_media_16x16.png","channel_name":"ES - eplayer"},{"stream_url":"https:\/\/footdirect.ru\/ply\/4\/81","flag":"https:\/\/www.shareicon.net\/data\/128x128\/2015\/08\/08\/82248_media_16x16.png","channel_name":"ES - wigi"}]},{"id":"671d689b65855","title":"MotoGP : Grand Prix de Tha\u00eflande La course des Moto 3\u00a006:00","browser_uuid":["\/live\/moto\/motogp\/grand+prix+de+tha\u00eflande+la+course+des+moto+3\/28\/fr","\/live\/moto\/motogp\/grand+prix+de+tha\u00eflande+la+course+des+moto+3\/81\/es"],"sport_name":"-","sport_flag":"https:\/\/img.icons8.com\/?size=48&id=iU4rpa9QGXp0&format=png","date_time":"0000\/00\/00 \u00e0 00:00","live":[{"stream_url":"https:\/\/footdirect.ru\/ply\/1\/28","flag":"https:\/\/www.shareicon.net\/data\/128x128\/2015\/08\/08\/82248_media_16x16.png","channel_name":"FR - Cartel"},{"stream_url":"https:\/\/footdirect.ru\/ply\/2\/28","flag":"https:\/\/www.shareicon.net\/data\/128x128\/2015\/08\/08\/82248_media_16x16.png","channel_name":"FR - Hoca"},{"stream_url":"https:\/\/footdirect.ru\/ply\/5\/28","flag":"https:\/\/www.shareicon.net\/data\/128x128\/2015\/08\/08\/82248_media_16x16.png","channel_name":"FR - CASTER"},{"stream_url":"https:\/\/footdirect.ru\/ply\/3\/28 ","flag":"https:\/\/www.shareicon.net\/data\/128x128\/2015\/08\/08\/82248_media_16x16.png","channel_name":"FR - eplayer"},{"stream_url":"https:\/\/footdirect.ru\/ply\/4\/28","flag":"https:\/\/www.shareicon.net\/data\/128x128\/2015\/08\/08\/82248_media_16x16.png","channel_name":"FR - wigi"},{"stream_url":"https:\/\/footdirect.ru\/ply\/1\/81","flag":"https:\/\/www.shareicon.net\/data\/128x128\/2015\/08\/08\/82248_media_16x16.png","channel_name":"ES - Cartel"},{"stream_url":"https:\/\/footdirect.ru\/ply\/2\/81","flag":"https:\/\/www.shareicon.net\/data\/128x128\/2015\/08\/08\/82248_media_16x16.png","channel_name":"ES - Hoca"},{"stream_url":"https:\/\/footdirect.ru\/ply\/5\/81","flag":"https:\/\/www.shareicon.net\/data\/128x128\/2015\/08\/08\/82248_media_16x16.png","channel_name":"ES - CASTER"},{"stream_url":"https:\/\/footdirect.ru\/ply\/3\/81 ","flag":"https:\/\/www.shareicon.net\/data\/128x128\/2015\/08\/08\/82248_media_16x16.png","channel_name":"ES - eplayer"},{"stream_url":"https:\/\/footdirect.ru\/ply\/4\/81","flag":"https:\/\/www.shareicon.net\/data\/128x128\/2015\/08\/08\/82248_media_16x16.png","channel_name":"ES - wigi"}]},{"id":"671d689b65856","title":"MotoGP : Grand Prix de Tha\u00eflande La course des Moto 2\u00a007:30","browser_uuid":["\/live\/moto\/motogp\/grand+prix+de+tha\u00eflande+la+course+des+moto+2\/28\/fr","\/live\/moto\/motogp\/grand+prix+de+tha\u00eflande+la+course+des+moto+2\/81\/es"],"sport_name":"-","sport_flag":"https:\/\/img.icons8.com\/?size=48&id=iU4rpa9QGXp0&format=png","date_time":"0000\/00\/00 \u00e0 00:00","live":[{"stream_url":"https:\/\/footdirect.ru\/ply\/1\/28","flag":"https:\/\/www.shareicon.net\/data\/128x128\/2015\/08\/08\/82248_media_16x16.png","channel_name":"FR - Cartel"},{"stream_url":"https:\/\/footdirect.ru\/ply\/2\/28","flag":"https:\/\/www.shareicon.net\/data\/128x128\/2015\/08\/08\/82248_media_16x16.png","channel_name":"FR - Hoca"},{"stream_url":"https:\/\/footdirect.ru\/ply\/5\/28","flag":"https:\/\/www.shareicon.net\/data\/128x128\/2015\/08\/08\/82248_media_16x16.png","channel_name":"FR - CASTER"},{"stream_url":"https:\/\/footdirect.ru\/ply\/3\/28 ","flag":"https:\/\/www.shareicon.net\/data\/128x128\/2015\/08\/08\/82248_media_16x16.png","channel_name":"FR - eplayer"},{"stream_url":"https:\/\/footdirect.ru\/ply\/4\/28","flag":"https:\/\/www.shareicon.net\/data\/128x128\/2015\/08\/08\/82248_media_16x16.png","channel_name":"FR - wigi"},{"stream_url":"https:\/\/footdirect.ru\/ply\/1\/81","flag":"https:\/\/www.shareicon.net\/data\/128x128\/2015\/08\/08\/82248_media_16x16.png","channel_name":"ES - Cartel"},{"stream_url":"https:\/\/footdirect.ru\/ply\/2\/81","flag":"https:\/\/www.shareicon.net\/data\/128x128\/2015\/08\/08\/82248_media_16x16.png","channel_name":"ES - Hoca"},{"stream_url":"https:\/\/footdirect.ru\/ply\/5\/81","flag":"https:\/\/www.shareicon.net\/data\/128x128\/2015\/08\/08\/82248_media_16x16.png","channel_name":"ES - CASTER"},{"stream_url":"https:\/\/footdirect.ru\/ply\/3\/81 ","flag":"https:\/\/www.shareicon.net\/data\/128x128\/2015\/08\/08\/82248_media_16x16.png","channel_name":"ES - eplayer"},{"stream_url":"https:\/\/footdirect.ru\/ply\/4\/81","flag":"https:\/\/www.shareicon.net\/data\/128x128\/2015\/08\/08\/82248_media_16x16.png","channel_name":"ES - wigi"}]},{"id":"671d689b65857","title":"MotoGP : Grand Prix de Tha\u00eflande La course des Moto GP\u00a009:00","browser_uuid":["\/live\/moto\/motogp\/grand+prix+de+tha\u00eflande+la+course+des+moto+gp\/5\/fr","\/live\/moto\/motogp\/grand+prix+de+tha\u00eflande+la+course+des+moto+gp\/81\/es"],"sport_name":"-","sport_flag":"https:\/\/img.icons8.com\/?size=48&id=iU4rpa9QGXp0&format=png","date_time":"0000\/00\/00 \u00e0 00:00","live":[{"stream_url":"https:\/\/footdirect.ru\/ply\/1\/5","flag":"https:\/\/www.shareicon.net\/data\/128x128\/2015\/08\/08\/82248_media_16x16.png","channel_name":"FR - Cartel"},{"stream_url":"https:\/\/footdirect.ru\/ply\/2\/5","flag":"https:\/\/www.shareicon.net\/data\/128x128\/2015\/08\/08\/82248_media_16x16.png","channel_name":"FR - Hoca"},{"stream_url":"https:\/\/footdirect.ru\/ply\/5\/5","flag":"https:\/\/www.shareicon.net\/data\/128x128\/2015\/08\/08\/82248_media_16x16.png","channel_name":"FR - CASTER"},{"stream_url":"https:\/\/footdirect.ru\/ply\/3\/5 ","flag":"https:\/\/www.shareicon.net\/data\/128x128\/2015\/08\/08\/82248_media_16x16.png","channel_name":"FR - eplayer"},{"stream_url":"https:\/\/footdirect.ru\/ply\/4\/5","flag":"https:\/\/www.shareicon.net\/data\/128x128\/2015\/08\/08\/82248_media_16x16.png","channel_name":"FR - wigi"},{"stream_url":"https:\/\/footdirect.ru\/ply\/1\/81","flag":"https:\/\/www.shareicon.net\/data\/128x128\/2015\/08\/08\/82248_media_16x16.png","channel_name":"ES - Cartel"},{"stream_url":"https:\/\/footdirect.ru\/ply\/2\/81","flag":"https:\/\/www.shareicon.net\/data\/128x128\/2015\/08\/08\/82248_media_16x16.png","channel_name":"ES - Hoca"},{"stream_url":"https:\/\/footdirect.ru\/ply\/5\/81","flag":"https:\/\/www.shareicon.net\/data\/128x128\/2015\/08\/08\/82248_media_16x16.png","channel_name":"ES - CASTER"},{"stream_url":"https:\/\/footdirect.ru\/ply\/3\/81 ","flag":"https:\/\/www.shareicon.net\/data\/128x128\/2015\/08\/08\/82248_media_16x16.png","channel_name":"ES - eplayer"},{"stream_url":"https:\/\/footdirect.ru\/ply\/4\/81","flag":"https:\/\/www.shareicon.net\/data\/128x128\/2015\/08\/08\/82248_media_16x16.png","channel_name":"ES - wigi"}]}]}